Workbook
Name aaa: #REF!
Name aaa: #REF!
Name aaa: #REF!
Name aaa: #REF!
Name aaa: #REF!
Name aaa: #REF!
Name aaa: #REF!
Name aaaaa: #REF!
Name aaaaa: #REF!
Name aaaaa: #REF!
Name aaaaa: #REF!
Name aaaaa: #REF!
Name aaaaa: #REF!
Name aaaaa: #REF!
Name ADMINISTRAÇÃO: #REF!
Name ADMINISTRAÇÃO: #REF!
Name ADMINISTRAÇÃO: #REF!
Name ADMINISTRAÇÃO: #REF!
Name ATC: #REF!
Name ATC: #REF!
Name BANCO1: #REF!
Name BANCO1: #REF!
Name BANCO1: #REF!
Name BANCO1: #REF!
Name BANCO1: #REF!
Name BANCO1: #REF!
Name BANCO1: #REF!
Name BANCO2: #REF!
Name BANCO2: #REF!
Name BANCO2: #REF!
Name BANCO2: #REF!
Name BANCO2: #REF!
Name BANCO2: #REF!
Name BANCO2: #REF!
Name BANCO3: #REF!
Name BANCO3: #REF!
Name BANCO3: #REF!
Name BANCO3: #REF!
Name BANCO3: #REF!
Name BANCO3: #REF!
Name BANCO3: #REF!
Name BANCO4: #REF!
Name BANCO4: #REF!
Name BANCO4: #REF!
Name BANCO4: #REF!
Name BANCO4: #REF!
Name BANCO4: #REF!
Name BASE: OFFSET(#REF!,0,0,COUNTA(#REF!)+1,5)
Name BASE: OFFSET(#REF!,0,0,COUNTA(#REF!)+1,5)
Name BASE: OFFSET(#REF!,0,0,COUNTA(#REF!)+1,5)
Name BASE: OFFSET(#REF!,0,0,COUNTA(#REF!)+1,5)
Name BASE: OFFSET(#REF!,0,0,COUNTA(#REF!)+1,5)
Name BASE: OFFSET(#REF!,0,0,COUNTA(#REF!)+1,5)
Name BASE: OFFSET(#REF!,0,0,COUNTA(#REF!)+1,5)
Name CAUX2: OFFSET(#REF!,0,0,COUNTA(#REF!)+1,1)
Name CAUX2: OFFSET(#REF!,0,0,COUNTA(#REF!)+1,1)
Name CAUX2: OFFSET(#REF!,0,0,COUNTA(#REF!)+1,1)
Name CAUX2: OFFSET(#REF!,0,0,COUNTA(#REF!)+1,1)
Name CAUX2: OFFSET(#REF!,0,0,COUNTA(#REF!)+1,1)
Name CAUX2: OFFSET(#REF!,0,0,COUNTA(#REF!)+1,1)

Sheet Quadro de Areas
A2: QUADRO DE AREAS EQUIVALENTES | L2: QUADRO DE AREAS PRIVATIVAS
A3: BLOCO 01 | B3: TERREO | E3: Área Coberta - Fechada | F3: 1 | G3: 1 | H3: =133.91-H4-H5 -> 62.72 | I3: =F3*1*H3 -> 62.72 | J3: =F3*H3*G3 -> 62.72 | L3: 101 | M3: 1 | N3: 62.03 | O3: =N3*M3 -> 62.03
E4: Área Coberta - Fechada - Caixas + DML + Gerador + A. Cam. + Casa de Maq | F4: 1 | G4: 0.5 | H4: =6.4+3.08+4.26 -> 13.74 | I4: =F4*1*H4 -> 13.74 | J4: =F4*H4*G4 -> 6.87 | L4: 102 | M4: 1 | N4: 62.07 | O4: =N4*M4 -> 62.07
E5: Área Coberta - Fechada - Garagem | F5: 1 | G5: 0.5 | H5: 57.45 | I5: =F5*1*H5 -> 57.45 | J5: =F5*H5*G5 -> 28.725 | L5: 201 a 401 | M5: 3 | N5: =45.25+9.78 -> 55.03 | O5: =N5*M5 -> 165.09
E6: Área Descoberta - Aberta | F6: 1 | G6: 0.25 | H6: 8.62 | J6: =F6*H6*G6 -> 2.155 | L6: 202 a 402 | M6: 3 | N6: =45.36+9.79 -> 55.15 | O6: =N6*M6 -> 165.45
B7: 1º PAVIMENTO | E7: Área Coberta - Fechada | F7: 1 | G7: 1 | H7: =131.58-H8 -> 114.67 | I7: =F7*1*H7 -> 114.67 | J7: =F7*H7*G7 -> 114.67 | L7: 501 | M7: 1 | N7: 118.74 | O7: =N7*M7 -> 118.74
E8: Área Coberta - Aberta | F8: 1 | G8: 1 | H8: 16.91 | I8: =F8*1*H8 -> 16.91 | J8: =F8*H8*G8 -> 16.91 | L8: 502 | M8: 1 | N8: 118.08 | O8: =N8*M8 -> 118.08
E9: Área Descoberta - Aberta - Terraço | F9: 1 | G9: 0.5 | H9: 13.33 | J9: =F9*H9*G9 -> 6.665 | L9: TOTAL GERAL: | O9: =SUM(O3:O8) -> 691.46
B10: 2 ao 4º PAVIMENTO | E10: Área Coberta - Fechada | F10: 3 | G10: 1 | H10: =131.58-H11 -> 120.06 | I10: =F10*1*H10 -> 360.18 | J10: =F10*H10*G10 -> 360.18
E11: Área Coberta - Aberta | F11: 3 | G11: 1 | H11: 11.52 | I11: =F11*1*H11 -> 34.56 | J11: =F11*H11*G11 -> 34.56
B12: 5º PAVIMENTO | E12: Área Coberta - Fechada | F12: 1 | G12: 1 | H12: =131.58-H13 -> 114.68 | I12: =F12*1*H12 -> 114.68 | J12: =F12*H12*G12 -> 114.68
E13: Área Coberta - Aberta | F13: 1 | G13: 1 | H13: 16.9 | I13: =F13*1*H13 -> 16.9 | J13: =F13*H13*G13 -> 16.9
B14: 6º PAVIMENTO | E14: Área Coberta - Fechada | F14: 1 | G14: 1 | H14: =87.37-H15 -> 87.37 | I14: =F14*1*H14 -> 87.37 | J14: =F14*H14*G14 -> 87.37
E15: Área Coberta - Aberta | F15: 1 | G15: 1 | I15: =F15*1*H15 -> 0 | J15: =F15*H15*G15 -> 0
B16: COBERTURA | E16: Área Coberta - Fechada | F16: 1 | G16: 1 | H16: =22.94-H17 -> 22.94 | I16: =F16*1*H16 -> 22.94 | J16: =F16*H16*G16 -> 22.94
E17: Área Descoberta - Aberta | F17: 1 | G17: 0.5 | I17: =F17*1*H17 -> 0 | J17: =F17*H17*G17 -> 0
B18: TELHADO | E18: Área Coberta - Fechada | F18: 1 | G18: 0.5 | I18: =F18*1*H18 -> 0 | J18: =F18*H18*G18 -> 0
E19: Área Descoberta - Aberta | F19: 1 | G19: 0.25 | H19: 51.26 | J19: =F19*H19*G19 -> 12.815
A20: TOTAL GERAL: | I20: =SUM(I3:I19) -> 902.12 | J20: =SUM(J3:J19) -> 888.16

Sheet 02. Orçamento RASO
E1: PLANILHA ORÇAMENTÁRIA DETALHADA | K1: formulado | L1: PRAZO (meses)
L2: 8
K4: % DISTR
F5: CATEGORIA | G5: UNIDADE | H5: QTD. | I5: QTD. TOTAL | J5: VALOR | K5: 1 | L5: TOTAL | O5: VALOR SEM % DISTR
B7: CUSTO RASO | L7: =SUM(L9+L177) -> 3655161.1 | M7: =L7/$L$7 -> 1 | N7: =P7=L7 -> FALSE | O7: =SUM(O10:O819) -> 3261117 | P7: =O7*K5 -> 3261117
B8: 0 | C8: 0 | D8: 0 | E8: 0 | G8: 0 | H8: 0 | J8: =IFERROR(IF(K8<>0,K8*$K$5,0),0) -> 0 | M8: =L8/$L$7 -> 0
A9: =LEN(C9) -> 1 | C9: I | D9: DESPESAS INDIRETAS | L9: =SUMIF(A10:A176,3,L10:L176) -> 198955.94 | M9: =L9/$L$7 -> 0.05443151 | O9: =IF(I9<>0,I9*H9*K9,) -> 0 | R9: =IF(J9<>0,J9/1.03-K9,0) -> 0
A10: =LEN(C10) -> 3 | C10: 01. | D10: SERVIÇOS TÉCNICOS E PRELIMINARES | L10: =SUMIF(A11:A24,4,L11:L24) -> 1 | M10: =L10/$L$7 -> 2.7358575e-07 | O10: =IF(I10<>0,I10*H10*K10,) -> 0 | R10: =IF(J10<>0,J10/1.03-K10,0) -> 0
A11: =LEN(C11) -> 0 | J11: =IFERROR(IF(K11<>0,K11*$K$5,0),0) -> 0 | K11: =IF(A11=0,VLOOKUP(D11,'03. Insumos'!A:F,4,0),"") -> #N/A | M11: =L11/$L$7 -> 0 | O11: =IF(I11<>0,I11*H11*K11,) -> 0 | R11: =IF(J11<>0,J11/1.03-K11,0) -> 0
A12: =LEN(C12) -> 4 | C12: 01.1 | D12: Serviços Preliminares | K12: =IF(A12=0,VLOOKUP(D12,'03. Insumos'!A:F,4,0),"") | L12: =SUMIF(A13:A14,6,L13:L14) -> 0 | M12: =L12/$L$7 -> 0 | O12: =IF(I12<>0,I12*H12*K12,) -> 0 | R12: =IF(J12<>0,J12/1.03-K12,0) -> 0
A13: =LEN(C13) -> 6 | C13: 01.1.1 | D13: Placa de Obra | K13: =IF(A13=0,VLOOKUP(D13,'03. Insumos'!A:F,4,0),"") | M13: =L13/$L$7 -> 0 | O13: =IF(I13<>0,I13*H13*K13,) -> 0 | R13: =IF(J13<>0,J13/1.03-K13,0) -> 0
A14: =LEN(C14) -> 0 | D14: 01.01.0001 | E14: =VLOOKUP(D14,'03. Insumos'!A:D,2,0) -> Placa de Obra | G14: =VLOOKUP(D14,'03. Insumos'!A:F,3,0) -> vb | H14: 1 | J14: =IFERROR(IF(K14<>0,K14*$K$5,0),0) -> 1 | K14: =IF(A14=0,VLOOKUP(D14,'03. Insumos'!A:F,4,0),"") -> 1 | L14: =H14*J14*I14 -> 0 | M14: =L14/$L$7 -> 0 | O14: =IF(I14<>0,I14*H14*K14,) -> 0 | R14: =IF(J14<>0,J14/1.03-K14,0) -> -0.029126214
A15: =LEN(C15) -> 4 | C15: 01.2 | D15: Serviços Técnicos | K15: =IF(A15=0,VLOOKUP(D15,'03. Insumos'!A:F,4,0),"") | L15: =SUMIF(A16:A24,6,L16:L24) -> 1 | M15: =L15/$L$7 -> 2.7358575e-07 | O15: =IF(I15<>0,I15*H15*K15,) -> 0 | R15: =IF(J15<>0,J15/1.03-K15,0) -> 0
A16: =LEN(C16) -> 6 | C16: 01.2.1 | D16: Controle Tecnológico | K16: =IF(A16=0,VLOOKUP(D16,'03. Insumos'!A:F,4,0),"") | L16: =SUM(L17:L20) -> 0 | M16: =L16/$L$7 -> 0 | O16: =IF(I16<>0,I16*H16*K16,) -> 0 | R16: =IF(J16<>0,J16/1.03-K16,0) -> 0
A17: =LEN(C17) -> 0 | D17: 01.01.0105 | E17: =VLOOKUP(D17,'03. Insumos'!A:D,2,0) -> Controle Tecnológico - Ensaio compressão simples concreto NBR 7215 | G17: =VLOOKUP(D17,'03. Insumos'!A:F,3,0) -> cp | H17: 1 | J17: =IFERROR(IF(K17<>0,K17*$K$5,0),0) -> 12 | K17: =IF(A17=0,VLOOKUP(D17,'03. Insumos'!A:F,4,0),"") -> 12 | L17: =H17*J17*I17 -> 0 | M17: =L17/$L$7 -> 0 | O17: =IF(I17<>0,I17*H17*K17,) -> 0 | R17: =IF(J17<>0,J17/1.03-K17,0) -> -0.34951456
A18: =LEN(C18) -> 0 | D18: 01.01.0103 | E18: =VLOOKUP(D18,'03. Insumos'!A:D,2,0) -> Controle Tecnológico - Diária Moldador | G18: =VLOOKUP(D18,'03. Insumos'!A:F,3,0) -> dia | H18: 1 | J18: =IFERROR(IF(K18<>0,K18*$K$5,0),0) -> 225 | K18: =IF(A18=0,VLOOKUP(D18,'03. Insumos'!A:F,4,0),"") -> 225 | L18: =H18*J18*I18 -> 0 | M18: =L18/$L$7 -> 0 | O18: =IF(I18<>0,I18*H18*K18,) -> 0 | R18: =IF(J18<>0,J18/1.03-K18,0) -> -6.5533981
A19: =LEN(C19) -> 0 | D19: 01.01.0104 | E19: =VLOOKUP(D19,'03. Insumos'!A:D,2,0) -> Controle Tecnológico - Mobilização | G19: =VLOOKUP(D19,'03. Insumos'!A:F,3,0) -> uni | H19: 1 | J19: =IFERROR(IF(K19<>0,K19*$K$5,0),0) -> 155 | K19: =IF(A19=0,VLOOKUP(D19,'03. Insumos'!A:F,4,0),"") -> 155 | L19: =H19*J19*I19 -> 0 | M19: =L19/$L$7 -> 0 | O19: =IF(I19<>0,I19*H19*K19,) -> 0 | R19: =IF(J19<>0,J19/1.03-K19,0) -> -4.5145631
A20: =LEN(C20) -> 0 | D20: 01.01.0107 | E20: =VLOOKUP(D20,'03. Insumos'!A:D,2,0) -> Controle Tecnológico - Coleta de materiais na obra | G20: =VLOOKUP(D20,'03. Insumos'!A:F,3,0) -> uni | H20: 1 | J20: =IFERROR(IF(K20<>0,K20*$K$5,0),0) -> 155 | K20: =IF(A20=0,VLOOKUP(D20,'03. Insumos'!A:F,4,0),"") -> 155 | L20: =H20*J20*I20 -> 0 | M20: =L20/$L$7 -> 0 | O20: =IF(I20<>0,I20*H20*K20,) -> 0 | R20: =IF(J20<>0,J20/1.03-K20,0) -> -4.5145631
A21: =LEN(C21) -> 6 | C21: 01.2.2 | D21: Consultorias | K21: =IF(A21=0,VLOOKUP(D21,'03. Insumos'!A:F,4,0),"") | L21: =SUM(L22:L22) -> 0 | M21: =L21/$L$7 -> 0 | R21: =IF(J21<>0,J21/1.03-K21,0) -> 0
A22: =LEN(C22) -> 0 | D22: 01.01.0005 | E22: =VLOOKUP(D22,'03. Insumos'!A:D,2,0) -> Consultoria Estrutura | G22: =VLOOKUP(D22,'03. Insumos'!A:F,3,0) -> mês | H22: 1 | J22: =IFERROR(IF(K22<>0,K22*$K$5,0),0) -> 3000 | K22: =IF(A22=0,VLOOKUP(D22,'03. Insumos'!A:F,4,0),"") -> 3000 | L22: =H22*J22*I22 -> 0 | M22: =L22/$L$7 -> 0 | O22: =IF(I22<>0,I22*H22*K22,) -> 0 | R22: =IF(J22<>0,J22/1.03-K22,0) -> -87.378641
A23: =LEN(C23) -> 6 | C23: 01.2.3 | D23: Seguro de Obra | K23: =IF(A23=0,VLOOKUP(D23,'03. Insumos'!A:F,4,0),"") | L23: =SUM(L24:L26) -> 1 | M23: =L23/$L$7 -> 2.7358575e-07 | R23: =IF(J23<>0,J23/1.03-K23,0) -> 0
A24: =LEN(C24) -> 0 | D24: 01.01.0713 | E24: =VLOOKUP(D24,'03. Insumos'!A:D,2,0) -> Seguro responsabilidade civil e cruzada | F24: SERV. ESP. | G24: =VLOOKUP(D24,'03. Insumos'!A:F,3,0) -> vb | H24: 1 | I24: 1 | J24: =IFERROR(IF(K24<>0,K24*$K$5,0),0) -> 1 | K24: =IF(A24=0,VLOOKUP(D24,'03. Insumos'!A:F,4,0),"") -> 1 | L24: =H24*J24*I24 -> 1 | M24: =L24/$L$7 -> 2.7358575e-07 | O24: =IF(I24<>0,I24*H24*K24,) -> 1 | R24: =IF(J24<>0,J24/1.03-K24,0) -> -0.029126214
A25: =LEN(C25) -> 0 | D25: 01.01.0714 | E25: =VLOOKUP(D25,'03. Insumos'!A:D,2,0) -> Seguro Performance Bond | G25: =VLOOKUP(D25,'03. Insumos'!A:F,3,0) -> vb | H25: 12 | J25: =IFERROR(IF(K25<>0,K25*$K$5,0),0) -> 1 | K25: =IF(A25=0,VLOOKUP(D25,'03. Insumos'!A:F,4,0),"") -> 1 | L25: =H25*J25*I25 -> 0 | M25: =L25/$L$7 -> 0
A26: =LEN(C26) -> 0 | D26: 01.01.0773 | E26: =VLOOKUP(D26,'03. Insumos'!A:D,2,0) -> Carta fiança (10% valor) | G26: =VLOOKUP(D26,'03. Insumos'!A:F,3,0) -> vb | H26: 1 | J26: =IFERROR(IF(K26<>0,K26*$K$5,0),0) -> 85135.685 | K26: =0.03*2837856.16 -> 85135.685 | L26: =H26*J26*I26 -> 0 | M26: =L26/$L$7 -> 0
A27: =LEN(C27) -> 3 | C27: 02. | D27: INSTALAÇÕES PROVISÓRIAS E CANTEIRO | L27: =SUMIF(A28:A49,4,L28:L49) -> 2139 | M27: =L27/$L$7 -> 0.00058519992 | O27: =IF(I27<>0,I27*H27*K27,) -> 0 | R27: =IF(J27<>0,J27/1.03-K27,0) -> 0
A28: =LEN(C28) -> 0 | J28: =IFERROR(IF(K28<>0,K28*$K$5,0),0) -> 0 | K28: =IF(A28=0,VLOOKUP(D28,'03. Insumos'!A:F,4,0),"") -> #N/A | M28: =L28/$L$7 -> 0 | O28: =IF(I28<>0,I28*H28*K28,) -> 0 | R28: =IF(J28<>0,J28/1.03-K28,0) -> 0
A29: =LEN(C29) -> 4 | C29: 02.1 | D29: Canteiro de Obras | K29: =IF(A29=0,VLOOKUP(D29,'03. Insumos'!A:F,4,0),"") | L29: =SUMIF(A30:A49,6,L30:L49) -> 2139 | M29: =L29/$L$7 -> 0.00058519992 | O29: =IF(I29<>0,I29*H29*K29,) -> 0 | R29: =IF(J29<>0,J29/1.03-K29,0) -> 0
A30: =LEN(C30) -> 6 | C30: 02.1.1 | D30: Barraco | K30: =IF(A30=0,VLOOKUP(D30,'03. Insumos'!A:F,4,0),"") | L30: =SUM(L31:L36) -> 0 | M30: =L30/$L$7 -> 0 | O30: =IF(I30<>0,I30*H30*K30,) -> 0 | R30: =IF(J30<>0,J30/1.03-K30,0) -> 0
A31: =LEN(C31) -> 0 | D31: 01.01.0717 | E31: =VLOOKUP(D31,'03. Insumos'!A:D,2,0) -> Barraco de Obra | G31: =VLOOKUP(D31,'03. Insumos'!A:F,3,0) -> vb | H31: 1 | J31: =IFERROR(IF(K31<>0,K31*$K$5,0),0) -> 45169.28 | K31: 45169.28 | L31: =H31*J31*I31 -> 0 | M31: =L31/$L$7 -> 0 | O31: =IF(I31<>0,I31*H31*K31,) -> 0 | R31: =IF(J31<>0,J31/1.03-K31,0) -> -1315.6101
A32: =LEN(C32) -> 0 | D32: 01.01.0716 | E32: =VLOOKUP(D32,'03. Insumos'!A:D,2,0) -> Mobiliário para barraco | G32: =VLOOKUP(D32,'03. Insumos'!A:F,3,0) -> vb | H32: 1 | J32: =IFERROR(IF(K32<>0,K32*$K$5,0),0) -> 20143.76 | K32: 20143.76 | L32: =H32*J32*I32 -> 0 | M32: =L32/$L$7 -> 0
A33: =LEN(C33) -> 0 | D33: 01.01.0767 | E33: =VLOOKUP(D33,'03. Insumos'!A:D,2,0) -> Módulo habitacional banheiro | G33: =VLOOKUP(D33,'03. Insumos'!A:F,3,0) -> mês | H33: 1 | J33: =IFERROR(IF(K33<>0,K33*$K$5,0),0) -> 620 | K33: =IF(A33=0,VLOOKUP(D33,'03. Insumos'!A:F,4,0),"") -> 620 | L33: =H33*J33*I33 -> 0 | M33: =L33/$L$7 -> 0
A34: =LEN(C34) -> 0 | D34: 01.01.0768 | E34: =VLOOKUP(D34,'03. Insumos'!A:D,2,0) -> Banheiro químico | G34: =VLOOKUP(D34,'03. Insumos'!A:F,3,0) -> mês | H34: 2 | J34: =IFERROR(IF(K34<>0,K34*$K$5,0),0) -> 700 | K34: =IF(A34=0,VLOOKUP(D34,'03. Insumos'!A:F,4,0),"") -> 700 | L34: =H34*J34*I34 -> 0 | M34: =L34/$L$7 -> 0
A35: =LEN(C35) -> 0 | D35: 01.01.0729 | E35: =VLOOKUP(D35,'03. Insumos'!A:D,2,0) -> Container marítimo 20 pés | G35: =VLOOKUP(D35,'03. Insumos'!A:F,3,0) -> unid | H35: 2 | J35: =IFERROR(IF(K35<>0,K35*$K$5,0),0) -> 500 | K35: =IF(A35=0,VLOOKUP(D35,'03. Insumos'!A:F,4,0),"") -> 500 | L35: =H35*J35*I35 -> 0 | M35: =L35/$L$7 -> 0
A36: =LEN(C36) -> 0 | D36: 01.01.0730 | E36: =VLOOKUP(D36,'03. Insumos'!A:D,2,0) -> Frete container marítimo | G36: =VLOOKUP(D36,'03. Insumos'!A:F,3,0) -> unid | H36: 1 | J36: =IFERROR(IF(K36<>0,K36*$K$5,0),0) -> 800 | K36: =IF(A36=0,VLOOKUP(D36,'03. Insumos'!A:F,4,0),"") -> 800 | L36: =H36*J36*I36 -> 0 | M36: =L36/$L$7 -> 0
A37: =LEN(C37) -> 6 | C37: 02.1.2 | D37: Isolamento área de trabalho | K37: =IF(A37=0,VLOOKUP(D37,'03. Insumos'!A:F,4,0),"") | L37: =SUM(L38:L38) -> 0 | M37: =L37/$L$7 -> 0 | O37: =IF(I37<>0,I37*H37*K37,) -> 0 | R37: =IF(J37<>0,J37/1.03-K37,0) -> 0
A38: =LEN(C38) -> 0 | D38: 01.01.0429 | E38: =VLOOKUP(D38,'03. Insumos'!A:D,2,0) -> Tapume metálico | G38: vb | H38: 1 | J38: =IFERROR(IF(K38<>0,K38*$K$5,0),0) -> 100 | K38: =IF(A38=0,VLOOKUP(D38,'03. Insumos'!A:F,4,0),"") -> 100 | L38: =H38*J38*I38 -> 0 | M38: =L38/$L$7 -> 0 | O38: =IF(I38<>0,I38*H38*K38,) -> 0 | R38: =IF(J38<>0,J38/1.03-K38,0) -> -2.9126214
A39: =LEN(C39) -> 6 | C39: 02.1.3 | D39: Instalações provisórias | K39: =IF(A39=0,VLOOKUP(D39,'03. Insumos'!A:F,4,0),"") | L39: =SUM(L40:L49) -> 2139 | M39: =L39/$L$7 -> 0.00058519992 | O39: =IF(I39<>0,I39*H39*K39,) -> 0 | R39: =IF(J39<>0,J39/1.03-K39,0) -> 0
A40: =LEN(C40) -> 0 | D40: 01.01.0424 | E40: =VLOOKUP(D40,'03. Insumos'!A:D,2,0) -> Cabo PP (2 x 2,5 mm) | F40: MAT CONSUMO | G40: =VLOOKUP(D40,'03. Insumos'!A:F,3,0) -> m | H40: 1 | I40: 200 | J40: =IFERROR(IF(K40<>0,K40*$K$5,0),0) -> 3.22 | K40: =IF(A40=0,VLOOKUP(D40,'03. Insumos'!A:F,4,0),"") -> 3.22 | L40: =H40*J40*I40 -> 644 | M40: =L40/$L$7 -> 0.00017618922 | O40: =IF(I40<>0,I40*H40*K40,) -> 644 | R40: =IF(J40<>0,J40/1.03-K40,0) -> -0.093786408
A41: =LEN(C41) -> 0 | D41: 01.01.0425 | E41: =VLOOKUP(D41,'03. Insumos'!A:D,2,0) -> Bocal para lâmpada | F41: MAT CONSUMO | G41: =VLOOKUP(D41,'03. Insumos'!A:F,3,0) -> unid | H41: 1 | I41: 10 | J41: =IFERROR(IF(K41<>0,K41*$K$5,0),0) -> 3.5 | K41: =IF(A41=0,VLOOKUP(D41,'03. Insumos'!A:F,4,0),"") -> 3.5 | L41: =H41*J41*I41 -> 35 | M41: =L41/$L$7 -> 9.5755012e-06
A42: =LEN(C42) -> 0 | D42: 01.01.0426 | E42: =VLOOKUP(D42,'03. Insumos'!A:D,2,0) -> Lâmpada | F42: MAT CONSUMO | G42: =VLOOKUP(D42,'03. Insumos'!A:F,3,0) -> unid | H42: 1 | I42: 20 | J42: =IFERROR(IF(K42<>0,K42*$K$5,0),0) -> 6 | K42: =IF(A42=0,VLOOKUP(D42,'03. Insumos'!A:F,4,0),"") -> 6 | L42: =H42*J42*I42 -> 120 | M42: =L42/$L$7 -> 3.283029e-05
A43: =LEN(C43) -> 0 | D43: 01.01.0778 | E43: =VLOOKUP(D43,'03. Insumos'!A:D,2,0) -> Refletores 400 W | F43: MAT CONSUMO | G43: =VLOOKUP(D43,'03. Insumos'!A:F,3,0) -> unid | H43: 1 | I43: 2 | J43: =IFERROR(IF(K43<>0,K43*$K$5,0),0) -> 134 | K43: =IF(A43=0,VLOOKUP(D43,'03. Insumos'!A:F,4,0),"") -> 134 | L43: =H43*J43*I43 -> 268 | M43: =L43/$L$7 -> 7.3320981e-05
A44: =LEN(C44) -> 0 | D44: 01.01.0427 | E44: =VLOOKUP(D44,'03. Insumos'!A:D,2,0) -> Plug macho | F44: MAT CONSUMO | G44: =VLOOKUP(D44,'03. Insumos'!A:F,3,0) -> unid | H44: 1 | I44: 10 | J44: =IFERROR(IF(K44<>0,K44*$K$5,0),0) -> 2.75 | K44: =IF(A44=0,VLOOKUP(D44,'03. Insumos'!A:F,4,0),"") -> 2.75 | L44: =H44*J44*I44 -> 27.5 | M44: =L44/$L$7 -> 7.5236081e-06
A45: =LEN(C45) -> 0 | D45: 01.01.0428 | E45: =VLOOKUP(D45,'03. Insumos'!A:D,2,0) -> Plug fêmea | F45: MAT CONSUMO | G45: =VLOOKUP(D45,'03. Insumos'!A:F,3,0) -> unid | H45: 1 | I45: 10 | J45: =IFERROR(IF(K45<>0,K45*$K$5,0),0) -> 4.45 | K45: =IF(A45=0,VLOOKUP(D45,'03. Insumos'!A:F,4,0),"") -> 4.45 | L45: =H45*J45*I45 -> 44.5 | M45: =L45/$L$7 -> 1.2174566e-05
A46: =LEN(C46) -> 0 | D46: 01.01.0589 | E46: =VLOOKUP(D46,'03. Insumos'!A:D,2,0) -> Robozinho para instalação provisória | G46: =VLOOKUP(D46,'03. Insumos'!A:F,3,0) -> unid | H46: 1 | J46: =IFERROR(IF(K46<>0,K46*$K$5,0),0) -> 2700 | K46: =IF(A46=0,VLOOKUP(D46,'03. Insumos'!A:F,4,0),"") -> 2700 | L46: =H46*J46*I46 -> 0 | M46: =L46/$L$7 -> 0
A47: =LEN(C47) -> 0 | D47: 01.01.0787 | E47: =VLOOKUP(D47,'03. Insumos'!A:D,2,0) -> Caixa d' agua 10.000 L | G47: =VLOOKUP(D47,'03. Insumos'!A:F,3,0) -> unid | H47: 1 | J47: =IFERROR(IF(K47<>0,K47*$K$5,0),0) -> 3800 | K47: =IF(A47=0,VLOOKUP(D47,'03. Insumos'!A:F,4,0),"") -> 3800 | L47: =H47*J47*I47 -> 0 | M47: =L47/$L$7 -> 0
A48: =LEN(C48) -> 0 | D48: 01.01.0788 | E48: =VLOOKUP(D48,'03. Insumos'!A:D,2,0) -> Bomba de recalque água | G48: =VLOOKUP(D48,'03. Insumos'!A:F,3,0) -> unid | H48: 1 | J48: =IFERROR(IF(K48<>0,K48*$K$5,0),0) -> 780 | K48: =IF(A48=0,VLOOKUP(D48,'03. Insumos'!A:F,4,0),"") -> 780 | L48: =H48*J48*I48 -> 0 | M48: =L48/$L$7 -> 0
A49: =LEN(C49) -> 0 | D49: 01.01.0718 | E49: =VLOOKUP(D49,'03. Insumos'!A:D,2,0) -> Itens diversos de instalações provisórias | F49: MAT CONSUMO | G49: =VLOOKUP(D49,'03. Insumos'!A:F,3,0) -> vb | H49: 1 | I49: 1 | J49: =IFERROR(IF(K49<>0,K49*$K$5,0),0) -> 1000 | K49: 1000 | L49: =H49*J49*I49 -> 1000 | M49: =L49/$L$7 -> 0.00027358575
A50: =LEN(C50) -> 3 | C50: 03. | D50: SEGURANÇA DO TRABALHO E PROTEÇÕES | L50: =SUMIF(A51:A79,4,L51:L79) -> 36387.12 | M50: =L50/$L$7 -> 0.0099549975 | O50: =IF(I50<>0,I50*H50*K50,) -> 0 | R50: =IF(J50<>0,J50/1.03-K50,0) -> 0
A51: =LEN(C51) -> 0 | K51: =IF(A51=0,VLOOKUP(D51,'03. Insumos'!A:F,4,0),"") -> #N/A | M51: =L51/$L$7 -> 0 | O51: =IF(I51<>0,I51*H51*K51,) -> 0 | R51: =IF(J51<>0,J51/1.03-K51,0) -> 0
A52: =LEN(C52) -> 4 | C52: 03.1 | D52: Sinalização de segurança e combate à incêndio | K52: =IF(A52=0,VLOOKUP(D52,'03. Insumos'!A:F,4,0),"") | L52: =SUMIF(A53:A55,6,L53:L55) -> 910 | M52: =L52/$L$7 -> 0.00024896303 | O52: =IF(I52<>0,I52*H52*K52,) -> 0 | R52: =IF(J52<>0,J52/1.03-K52,0) -> 0
A53: =LEN(C53) -> 6 | C53: 03.1.1 | D53: Equipamentos de combate à incêndio | K53: =IF(A53=0,VLOOKUP(D53,'03. Insumos'!A:F,4,0),"") | L53: =SUM(L54:L55) -> 910 | M53: =L53/$L$7 -> 0.00024896303 | O53: =IF(I53<>0,I53*H53*K53,) -> 0 | R53: =IF(J53<>0,J53/1.03-K53,0) -> 0
A54: =LEN(C54) -> 0 | D54: 01.01.0025 | E54: =VLOOKUP(D54,'03. Insumos'!A:D,2,0) -> Extintor de Pó Químico 4kg | F54: MAT CONSUMO | G54: =VLOOKUP(D54,'03. Insumos'!A:F,3,0) -> uni | H54: 1 | I54: 1 | J54: =IFERROR(IF(K54<>0,K54*$K$5,0),0) -> 540 | K54: =IF(A54=0,VLOOKUP(D54,'03. Insumos'!A:F,4,0),"") -> 540 | L54: =H54*J54*I54 -> 540 | M54: =L54/$L$7 -> 0.0001477363 | O54: =IF(I54<>0,I54*H54*K54,) -> 540 | R54: =IF(J54<>0,J54/1.03-K54,0) -> -15.728155
A55: =LEN(C55) -> 0 | D55: 01.01.0026 | E55: =VLOOKUP(D55,'03. Insumos'!A:D,2,0) -> Extintor CO2 4Kg | F55: MAT CONSUMO | G55: =VLOOKUP(D55,'03. Insumos'!A:F,3,0) -> uni | H55: 1 | I55: 1 | J55: =IFERROR(IF(K55<>0,K55*$K$5,0),0) -> 370 | K55: =IF(A55=0,VLOOKUP(D55,'03. Insumos'!A:F,4,0),"") -> 370 | L55: =H55*J55*I55 -> 370 | M55: =L55/$L$7 -> 0.00010122673 | O55: =IF(I55<>0,I55*H55*K55,) -> 370 | R55: =IF(J55<>0,J55/1.03-K55,0) -> -10.776699
A56: =LEN(C56) -> 4 | C56: 03.2 | D56: Documentação de segurança do trabalho | K56: =IF(A56=0,VLOOKUP(D56,'03. Insumos'!A:F,4,0),"") | L56: =SUMIF(A57:A58,6,L57:L66) -> 0 | M56: =L56/$L$7 -> 0
A57: =LEN(C57) -> 6 | C57: 03.2.1 | D57: Documentação de segurança do trabalho | K57: =IF(A57=0,VLOOKUP(D57,'03. Insumos'!A:F,4,0),"") | L57: =SUM(L58:L66) -> 0 | M57: =L57/$L$7 -> 0
A58: =LEN(C58) -> 0 | D58: 01.01.0789 | E58: =VLOOKUP(D58,'03. Insumos'!A:D,2,0) -> PCMAT por fase da obra | G58: =VLOOKUP(D58,'03. Insumos'!A:F,3,0) -> unid | H58: 1 | J58: =IFERROR(IF(K58<>0,K58*$K$5,0),0) -> 1200 | K58: =IF(A58=0,VLOOKUP(D58,'03. Insumos'!A:F,4,0),"") -> 1200 | L58: =H58*J58*I58 -> 0 | M58: =L58/$L$7 -> 0
A59: =LEN(C59) -> 0 | D59: 01.01.0790 | E59: =VLOOKUP(D59,'03. Insumos'!A:D,2,0) -> Revisão do PCMAT | G59: =VLOOKUP(D59,'03. Insumos'!A:F,3,0) -> unid | H59: 1 | J59: =IFERROR(IF(K59<>0,K59*$K$5,0),0) -> 300 | K59: =IF(A59=0,VLOOKUP(D59,'03. Insumos'!A:F,4,0),"") -> 300 | L59: =H59*J59*I59 -> 0 | M59: =L59/$L$7 -> 0
A60: =LEN(C60) -> 0 | D60: 01.01.0791 | E60: =VLOOKUP(D60,'03. Insumos'!A:D,2,0) -> PGR por fase da obra | G60: =VLOOKUP(D60,'03. Insumos'!A:F,3,0) -> unid | H60: 1 | J60: =IFERROR(IF(K60<>0,K60*$K$5,0),0) -> 1500 | K60: =IF(A60=0,VLOOKUP(D60,'03. Insumos'!A:F,4,0),"") -> 1500 | L60: =H60*J60*I60 -> 0 | M60: =L60/$L$7 -> 0
A61: =LEN(C61) -> 0 | D61: 01.01.0792 | E61: =VLOOKUP(D61,'03. Insumos'!A:D,2,0) -> Revisão PGR | G61: =VLOOKUP(D61,'03. Insumos'!A:F,3,0) -> unid | H61: 1 | J61: =IFERROR(IF(K61<>0,K61*$K$5,0),0) -> 369 | K61: =IF(A61=0,VLOOKUP(D61,'03. Insumos'!A:F,4,0),"") -> 369 | L61: =H61*J61*I61 -> 0 | M61: =L61/$L$7 -> 0
A62: =LEN(C62) -> 0 | D62: 01.01.0793 | E62: =VLOOKUP(D62,'03. Insumos'!A:D,2,0) -> Mapa de risco por fase da obra | G62: =VLOOKUP(D62,'03. Insumos'!A:F,3,0) -> unid | H62: 1 | J62: =IFERROR(IF(K62<>0,K62*$K$5,0),0) -> 180 | K62: =IF(A62=0,VLOOKUP(D62,'03. Insumos'!A:F,4,0),"") -> 180 | L62: =H62*J62*I62 -> 0 | M62: =L62/$L$7 -> 0
A63: =LEN(C63) -> 0 | D63: 01.01.0794 | E63: =VLOOKUP(D63,'03. Insumos'!A:D,2,0) -> PCMAT por fase da obra | G63: =VLOOKUP(D63,'03. Insumos'!A:F,3,0) -> unid | H63: 1 | J63: =IFERROR(IF(K63<>0,K63*$K$5,0),0) -> 1800 | K63: =IF(A63=0,VLOOKUP(D63,'03. Insumos'!A:F,4,0),"") -> 1800 | L63: =H63*J63*I63 -> 0 | M63: =L63/$L$7 -> 0
A64: =LEN(C64) -> 0 | D64: 01.01.0795 | E64: =VLOOKUP(D64,'03. Insumos'!A:D,2,0) -> Revisão do PCMSO | G64: =VLOOKUP(D64,'03. Insumos'!A:F,3,0) -> unid | H64: 1 | J64: =IFERROR(IF(K64<>0,K64*$K$5,0),0) -> 300 | K64: =IF(A64=0,VLOOKUP(D64,'03. Insumos'!A:F,4,0),"") -> 300 | L64: =H64*J64*I64 -> 0 | M64: =L64/$L$7 -> 0
A65: =LEN(C65) -> 0 | D65: 01.01.0796 | E65: =VLOOKUP(D65,'03. Insumos'!A:D,2,0) -> Implantação e gerenciamento da CIPA | G65: =VLOOKUP(D65,'03. Insumos'!A:F,3,0) -> mês | H65: 1 | J65: =IFERROR(IF(K65<>0,K65*$K$5,0),0) -> 300 | K65: =IF(A65=0,VLOOKUP(D65,'03. Insumos'!A:F,4,0),"") -> 300 | L65: =H65*J65*I65 -> 0 | M65: =L65/$L$7 -> 0
A66: =LEN(C66) -> 0 | D66: 01.01.0797 | E66: =VLOOKUP(D66,'03. Insumos'!A:D,2,0) -> Treinamento para CIPA | G66: =VLOOKUP(D66,'03. Insumos'!A:F,3,0) -> unid | H66: 1 | J66: =IFERROR(IF(K66<>0,K66*$K$5,0),0) -> 2000 | K66: =IF(A66=0,VLOOKUP(D66,'03. Insumos'!A:F,4,0),"") -> 2000 | L66: =H66*J66*I66 -> 0 | M66: =L66/$L$7 -> 0
A67: =LEN(C67) -> 4 | C67: 03.3 | D67: Equipamentos de proteção individual | K67: =IF(A67=0,VLOOKUP(D67,'03. Insumos'!A:F,4,0),"") | L67: =SUMIF(A68:A75,6,L68:L75) -> 35477.12 | M67: =L67/$L$7 -> 0.0097060345 | O67: =IF(I67<>0,I67*H67*K67,) -> 0 | R67: =IF(J67<>0,J67/1.03-K67,0) -> 0
A68: =LEN(C68) -> 6 | C68: 03.3.1 | D68: Equipamentos de proteção individual | K68: =IF(A68=0,VLOOKUP(D68,'03. Insumos'!A:F,4,0),"") | L68: =SUM(L69:L75) -> 35477.12 | M68: =L68/$L$7 -> 0.0097060345 | O68: =IF(I68<>0,I68*H68*K68,) -> 0 | R68: =IF(J68<>0,J68/1.03-K68,0) -> 0
A69: =LEN(C69) -> 0 | D69: 01.01.0430 | E69: =VLOOKUP(D69,'03. Insumos'!A:D,2,0) -> Máscara | F69: MAT CONSUMO | G69: =VLOOKUP(D69,'03. Insumos'!A:F,3,0) -> unid | H69: 1 | I69: =6*6*2 -> 72 | J69: =IFERROR(IF(K69<>0,K69*$K$5,0),0) -> 0.47333333 | K69: =IF(A69=0,VLOOKUP(D69,'03. Insumos'!A:F,4,0),"") -> 0.47333333 | L69: =H69*J69*I69 -> 34.08 | M69: =L69/$L$7 -> 9.3238023e-06 | O69: =IF(I69<>0,I69*H69*K69,) -> 34.08 | R69: =IF(J69<>0,J69/1.03-K69,0) -> -0.013786408
A70: =LEN(C70) -> 0 | D70: 01.01.0431 | E70: =VLOOKUP(D70,'03. Insumos'!A:D,2,0) -> Bota | G70: =VLOOKUP(D70,'03. Insumos'!A:F,3,0) -> unid | H70: 1 | J70: =IFERROR(IF(K70<>0,K70*$K$5,0),0) -> 27 | K70: =IF(A70=0,VLOOKUP(D70,'03. Insumos'!A:F,4,0),"") -> 27 | L70: =H70*J70*I70 -> 0 | M70: =L70/$L$7 -> 0
A71: =LEN(C71) -> 0 | D71: 01.01.0432 | E71: =VLOOKUP(D71,'03. Insumos'!A:D,2,0) -> Capacete | G71: =VLOOKUP(D71,'03. Insumos'!A:F,3,0) -> unid | H71: 1 | J71: =IFERROR(IF(K71<>0,K71*$K$5,0),0) -> 9.73 | K71: =IF(A71=0,VLOOKUP(D71,'03. Insumos'!A:F,4,0),"") -> 9.73 | L71: =H71*J71*I71 -> 0 | M71: =L71/$L$7 -> 0
A72: =LEN(C72) -> 0 | D72: 01.01.0433 | E72: =VLOOKUP(D72,'03. Insumos'!A:D,2,0) -> Cinto de segurança | F72: MAT CONSUMO | G72: =VLOOKUP(D72,'03. Insumos'!A:F,3,0) -> unid | H72: 1 | I72: 2 | J72: =IFERROR(IF(K72<>0,K72*$K$5,0),0) -> 46.2 | K72: =IF(A72=0,VLOOKUP(D72,'03. Insumos'!A:F,4,0),"") -> 46.2 | L72: =H72*J72*I72 -> 92.4 | M72: =L72/$L$7 -> 2.5279323e-05
A73: =LEN(C73) -> 0 | D73: 01.01.0434 | E73: =VLOOKUP(D73,'03. Insumos'!A:D,2,0) -> Corda de poliamida (50 m) | F73: MAT CONSUMO | G73: =VLOOKUP(D73,'03. Insumos'!A:F,3,0) -> rolo | H73: 1 | I73: 100 | J73: =IFERROR(IF(K73<>0,K73*$K$5,0),0) -> 350 | K73: =IF(A73=0,VLOOKUP(D73,'03. Insumos'!A:F,4,0),"") -> 350 | L73: =H73*J73*I73 -> 35000 | M73: =L73/$L$7 -> 0.0095755012
A74: =LEN(C74) -> 0 | D74: 01.01.0435 | E74: =VLOOKUP(D74,'03. Insumos'!A:D,2,0) -> Luva | F74: MAT CONSUMO | G74: =VLOOKUP(D74,'03. Insumos'!A:F,3,0) -> unid | H74: 1 | I74: =I69/2 -> 36 | J74: =IFERROR(IF(K74<>0,K74*$K$5,0),0) -> 7.74 | K74: =IF(A74=0,VLOOKUP(D74,'03. Insumos'!A:F,4,0),"") -> 7.74 | L74: =H74*J74*I74 -> 278.64 | M74: =L74/$L$7 -> 7.6231933e-05
A75: =LEN(C75) -> 0 | D75: 01.01.0436 | E75: =VLOOKUP(D75,'03. Insumos'!A:D,2,0) -> Óculos | F75: MAT CONSUMO | G75: =VLOOKUP(D75,'03. Insumos'!A:F,3,0) -> unid | H75: 1 | I75: =I69/2 -> 36 | J75: =IFERROR(IF(K75<>0,K75*$K$5,0),0) -> 2 | K75: =IF(A75=0,VLOOKUP(D75,'03. Insumos'!A:F,4,0),"") -> 2 | L75: =H75*J75*I75 -> 72 | M75: =L75/$L$7 -> 1.9698174e-05
A76: =LEN(C76) -> 4 | C76: 03.3 | D76: Equipamentos de proteção coletiva | K76: =IF(A76=0,VLOOKUP(D76,'03. Insumos'!A:F,4,0),"") | L76: =SUMIF(A77:A79,6,L77:L79) -> 0 | M76: =L76/$L$7 -> 0 | O76: =IF(I76<>0,I76*H76*K76,) -> 0 | R76: =IF(J76<>0,J76/1.03-K76,0) -> 0
A77: =LEN(C77) -> 6 | C77: 03.3.1 | D77: Equipamentos de proteção coletiva | K77: =IF(A77=0,VLOOKUP(D77,'03. Insumos'!A:F,4,0),"") | L77: =SUM(L78:L79) -> 0 | M77: =L77/$L$7 -> 0 | O77: =IF(I77<>0,I77*H77*K77,) -> 0 | R77: =IF(J77<>0,J77/1.03-K77,0) -> 0
A78: =LEN(C78) -> 0 | D78: 01.01.0741 | E78: =VLOOKUP(D78,'03. Insumos'!A:D,2,0) -> Proteção de periferia | G78: =VLOOKUP(D78,'03. Insumos'!A:F,3,0) -> vb | H78: 1 | J78: =IFERROR(IF(K78<>0,K78*$K$5,0),0) -> 1683.2 | K78: =(40*5.58)+(60*16)+(10*50) -> 1683.2 | L78: =H78*J78*I78 -> 0 | M78: =L78/$L$7 -> 0
A79: =LEN(C79) -> 0 | D79: 01.01.0742 | E79: =VLOOKUP(D79,'03. Insumos'!A:D,2,0) -> Linha de vida | G79: =VLOOKUP(D79,'03. Insumos'!A:F,3,0) -> vb | H79: 1 | J79: =IFERROR(IF(K79<>0,K79*$K$5,0),0) -> 11688.62 | K79: =IF(A79=0,VLOOKUP(D79,'03. Insumos'!A:F,4,0),"") -> 11688.62 | L79: =H79*J79*I79 -> 0 | M79: =L79/$L$7 -> 0 | O79: =IF(I79<>0,I79*H79*K79,) -> 0 | R79: =IF(J79<>0,J79/1.03-K79,0) -> -340.44524
A80: =LEN(C80) -> 3 | C80: 04. | D80: MÁQUINAS E EQUIPAMENTOS | L80: =SUMIF(A81:A137,4,L81:L137) -> 15444.82 | M80: =L80/$L$7 -> 0.0042254827 | O80: =IF(I80<>0,I80*H80*K80,) -> 0 | R80: =IF(J80<>0,J80/1.03-K80,0) -> 0
A81: =LEN(C81) -> 0 | J81: =IFERROR(IF(K81<>0,K81*$K$5,0),0) -> 0 | K81: =IF(A81=0,VLOOKUP(D81,'03. Insumos'!A:F,4,0),"") -> #N/A | M81: =L81/$L$7 -> 0 | O81: =IF(I81<>0,I81*H81*K81,) -> 0 | R81: =IF(J81<>0,J81/1.03-K81,0) -> 0
A82: =LEN(C82) -> 4 | C82: 04.1 | D82: Equipamentos | K82: =IF(A82=0,VLOOKUP(D82,'03. Insumos'!A:F,4,0),"") | L82: =SUMIF(A83:A112,6,L83:L112) -> 4737 | M82: =L82/$L$7 -> 0.0012959757 | O82: =IF(I82<>0,I82*H82*K82,) -> 0 | R82: =IF(J82<>0,J82/1.03-K82,0) -> 0
A83: =LEN(C83) -> 6 | C83: 04.1.1 | D83: Locação de equipamentos diversos | K83: =IF(A83=0,VLOOKUP(D83,'03. Insumos'!A:F,4,0),"") | L83: =SUM(L84:L110) -> 4737 | M83: =L83/$L$7 -> 0.0012959757 | O83: =IF(I83<>0,I83*H83*K83,) -> 0 | R83: =IF(J83<>0,J83/1.03-K83,0) -> 0
A84: =LEN(C84) -> 0 | D84: 01.01.0438 | E84: =VLOOKUP(D84,'03. Insumos'!A:D,2,0) -> Serra mármore | F84: MAT CONSUMO | G84: =VLOOKUP(D84,'03. Insumos'!A:F,3,0) -> mês | H84: 6 | I84: 2 | J84: =IFERROR(IF(K84<>0,K84*$K$5,0),0) -> 80 | K84: =IF(A84=0,VLOOKUP(D84,'03. Insumos'!A:F,4,0),"") -> 80 | L84: =H84*J84*I84 -> 960 | M84: =L84/$L$7 -> 0.00026264232
A85: =LEN(C85) -> 0 | D85: 01.01.0757 | E85: =VLOOKUP(D85,'03. Insumos'!A:D,2,0) -> Torre de iluminação | G85: =VLOOKUP(D85,'03. Insumos'!A:F,3,0) -> mês | H85: 1 | J85: =IFERROR(IF(K85<>0,K85*$K$5,0),0) -> 1490 | K85: =IF(A85=0,VLOOKUP(D85,'03. Insumos'!A:F,4,0),"") -> 1490 | L85: =H85*J85*I85 -> 0 | M85: =L85/$L$7 -> 0
A86: =LEN(C86) -> 0 | D86: 01.01.0782 | E86: =VLOOKUP(D86,'03. Insumos'!A:D,2,0) -> Traçador | G86: =VLOOKUP(D86,'03. Insumos'!A:F,3,0) -> mês | H86: 1 | J86: =IFERROR(IF(K86<>0,K86*$K$5,0),0) -> 105 | K86: =IF(A86=0,VLOOKUP(D86,'03. Insumos'!A:F,4,0),"") -> 105 | L86: =H86*J86*I86 -> 0 | M86: =L86/$L$7 -> 0
A87: =LEN(C87) -> 0 | D87: 01.01.0032 | E87: =VLOOKUP(D87,'03. Insumos'!A:D,2,0) -> Velox Locação | G87: =VLOOKUP(D87,'03. Insumos'!A:F,3,0) -> mês | H87: 1 | J87: =IFERROR(IF(K87<>0,K87*$K$5,0),0) -> 290 | K87: =IF(A87=0,VLOOKUP(D87,'03. Insumos'!A:F,4,0),"") -> 290 | L87: =H87*J87*I87 -> 0 | M87: =L87/$L$7 -> 0
A88: =LEN(C88) -> 0 | D88: 01.01.0780 | E88: =VLOOKUP(D88,'03. Insumos'!A:D,2,0) -> Bomba submersa | G88: =VLOOKUP(D88,'03. Insumos'!A:F,3,0) -> mês | H88: 1 | J88: =IFERROR(IF(K88<>0,K88*$K$5,0),0) -> 230 | K88: =IF(A88=0,VLOOKUP(D88,'03. Insumos'!A:F,4,0),"") -> 230 | L88: =H88*J88*I88 -> 0 | M88: =L88/$L$7 -> 0
A89: =LEN(C89) -> 0 | D89: 01.01.0781 | E89: =VLOOKUP(D89,'03. Insumos'!A:D,2,0) -> Mangote para bomba 20 m | G89: =VLOOKUP(D89,'03. Insumos'!A:F,3,0) -> mês | H89: 1 | J89: =IFERROR(IF(K89<>0,K89*$K$5,0),0) -> 96 | K89: =IF(A89=0,VLOOKUP(D89,'03. Insumos'!A:F,4,0),"") -> 96 | L89: =H89*J89*I89 -> 0 | M89: =L89/$L$7 -> 0
A90: =LEN(C90) -> 0 | D90: 01.01.0758 | E90: =VLOOKUP(D90,'03. Insumos'!A:D,2,0) -> Martelete 10 Kg | G90: =VLOOKUP(D90,'03. Insumos'!A:F,3,0) -> mês | H90: 1 | J90: =IFERROR(IF(K90<>0,K90*$K$5,0),0) -> 490 | K90: =IF(A90=0,VLOOKUP(D90,'03. Insumos'!A:F,4,0),"") -> 490 | L90: =H90*J90*I90 -> 0 | M90: =L90/$L$7 -> 0
A91: =LEN(C91) -> 0 | D91: 01.01.0123 | E91: =VLOOKUP(D91,'03. Insumos'!A:D,2,0) -> Martelete de 2,5 Kg | F91: MAT CONSUMO | G91: =VLOOKUP(D91,'03. Insumos'!A:F,3,0) -> mês | H91: 2 | I91: 2 | J91: =IFERROR(IF(K91<>0,K91*$K$5,0),0) -> 185 | K91: =IF(A91=0,VLOOKUP(D91,'03. Insumos'!A:F,4,0),"") -> 185 | L91: =H91*J91*I91 -> 740 | M91: =L91/$L$7 -> 0.00020245345
A92: =LEN(C92) -> 0 | D92: 01.01.0439 | E92: =VLOOKUP(D92,'03. Insumos'!A:D,2,0) -> MARTELETE (SDS PLUS) 220VOLTS BIF | F92: MAT CONSUMO | G92: =VLOOKUP(D92,'03. Insumos'!A:F,3,0) -> mês | H92: 1 | I92: 2 | J92: =IFERROR(IF(K92<>0,K92*$K$5,0),0) -> 125 | K92: =IF(A92=0,VLOOKUP(D92,'03. Insumos'!A:F,4,0),"") -> 125 | L92: =H92*J92*I92 -> 250 | M92: =L92/$L$7 -> 6.8396437e-05
A93: =LEN(C93) -> 0 | D93: 01.01.0760 | E93: =VLOOKUP(D93,'03. Insumos'!A:D,2,0) -> Compressor 185 PCM para 2 marteletes | G93: =VLOOKUP(D93,'03. Insumos'!A:F,3,0) -> mês | H93: 1 | J93: =IFERROR(IF(K93<>0,K93*$K$5,0),0) -> 2100 | K93: =IF(A93=0,VLOOKUP(D93,'03. Insumos'!A:F,4,0),"") -> 2100 | L93: =H93*J93*I93 -> 0 | M93: =L93/$L$7 -> 0
A94: =LEN(C94) -> 0 | D94: 01.01.0761 | E94: =VLOOKUP(D94,'03. Insumos'!A:D,2,0) -> Lance de mangueira c/ 20 m | G94: =VLOOKUP(D94,'03. Insumos'!A:F,3,0) -> mês | H94: 1 | J94: =IFERROR(IF(K94<>0,K94*$K$5,0),0) -> 98 | K94: =IF(A94=0,VLOOKUP(D94,'03. Insumos'!A:F,4,0),"") -> 98 | L94: =H94*J94*I94 -> 0 | M94: =L94/$L$7 -> 0
A95: =LEN(C95) -> 0 | D95: 01.01.0762 | E95: =VLOOKUP(D95,'03. Insumos'!A:D,2,0) -> Mini escavadeira | G95: =VLOOKUP(D95,'03. Insumos'!A:F,3,0) -> mês | H95: 1 | J95: =IFERROR(IF(K95<>0,K95*$K$5,0),0) -> 24000 | K95: =IF(A95=0,VLOOKUP(D95,'03. Insumos'!A:F,4,0),"") -> 24000 | L95: =H95*J95*I95 -> 0 | M95: =L95/$L$7 -> 0
A96: =LEN(C96) -> 0 | D96: 01.01.0779 | E96: =VLOOKUP(D96,'03. Insumos'!A:D,2,0) -> Retroescavadeira com operador | G96: =VLOOKUP(D96,'03. Insumos'!A:F,3,0) -> mês | H96: 1 | J96: =IFERROR(IF(K96<>0,K96*$K$5,0),0) -> 16000 | K96: =IF(A96=0,VLOOKUP(D96,'03. Insumos'!A:F,4,0),"") -> 16000 | L96: =H96*J96*I96 -> 0 | M96: =L96/$L$7 -> 0
A97: =LEN(C97) -> 0 | D97: 01.01.0752 | E97: =VLOOKUP(D97,'03. Insumos'!A:D,2,0) -> Plataforma elevatória de 7 m (tesourinha) | G97: =VLOOKUP(D97,'03. Insumos'!A:F,3,0) -> mês | H97: 1 | J97: =IFERROR(IF(K97<>0,K97*$K$5,0),0) -> 1600 | K97: =IF(A97=0,VLOOKUP(D97,'03. Insumos'!A:F,4,0),"") -> 1600 | L97: =H97*J97*I97 -> 0 | M97: =L97/$L$7 -> 0
A98: =LEN(C98) -> 0 | D98: 01.01.0763 | E98: =VLOOKUP(D98,'03. Insumos'!A:D,2,0) -> Gerador portátil 8 Kva | G98: =VLOOKUP(D98,'03. Insumos'!A:F,3,0) -> mês | H98: 1 | J98: =IFERROR(IF(K98<>0,K98*$K$5,0),0) -> 600 | K98: =IF(A98=0,VLOOKUP(D98,'03. Insumos'!A:F,4,0),"") -> 600 | L98: =H98*J98*I98 -> 0 | M98: =L98/$L$7 -> 0
A99: =LEN(C99) -> 0 | D99: 01.01.0764 | E99: =VLOOKUP(D99,'03. Insumos'!A:D,2,0) -> Cortador de piso | G99: =VLOOKUP(D99,'03. Insumos'!A:F,3,0) -> mês | H99: 1 | J99: =IFERROR(IF(K99<>0,K99*$K$5,0),0) -> 350 | K99: =IF(A99=0,VLOOKUP(D99,'03. Insumos'!A:F,4,0),"") -> 350 | L99: =H99*J99*I99 -> 0 | M99: =L99/$L$7 -> 0
A100: =LEN(C100) -> 0 | D100: 01.01.0765 | E100: =VLOOKUP(D100,'03. Insumos'!A:D,2,0) -> Disco corte | G100: =VLOOKUP(D100,'03. Insumos'!A:F,3,0) -> unid | H100: 1 | J100: =IFERROR(IF(K100<>0,K100*$K$5,0),0) -> 260 | K100: =IF(A100=0,VLOOKUP(D100,'03. Insumos'!A:F,4,0),"") -> 260 | L100: =H100*J100*I100 -> 0 | M100: =L100/$L$7 -> 0
A101: =LEN(C101) -> 0 | D101: 01.01.0771 | E101: =VLOOKUP(D101,'03. Insumos'!A:D,2,0) -> Compactador de solo | F101: MAT CONSUMO | G101: =VLOOKUP(D101,'03. Insumos'!A:F,3,0) -> mês | H101: 1 | I101: 1 | J101: =IFERROR(IF(K101<>0,K101*$K$5,0),0) -> 495 | K101: =IF(A101=0,VLOOKUP(D101,'03. Insumos'!A:F,4,0),"") -> 495 | L101: =H101*J101*I101 -> 495 | M101: =L101/$L$7 -> 0.00013542495
A102: =LEN(C102) -> 0 | D102: 01.01.0772 | E102: =VLOOKUP(D102,'03. Insumos'!A:D,2,0) -> Giranda com 100 metros | G102: =VLOOKUP(D102,'03. Insumos'!A:F,3,0) -> unid | H102: 1 | J102: =IFERROR(IF(K102<>0,K102*$K$5,0),0) -> 1300 | K102: =IF(A102=0,VLOOKUP(D102,'03. Insumos'!A:F,4,0),"") -> 1300 | L102: =H102*J102*I102 -> 0 | M102: =L102/$L$7 -> 0
...

Sheet 02. Orçamento - opção troca pis
E1: PLANILHA ORÇAMENTÁRIA DETALHADA | K1: formulado | L1: PRAZO (meses)
L2: 4
K4: % DISTR
F5: CATEGORIA | G5: UNIDADE | H5: QTD. | I5: QTD. TOTAL | J5: VALOR | K5: 1 | L5: TOTAL | O5: VALOR SEM % DISTR
B7: CUSTO TOTAL | L7: =SUM(L9+L191) -> 563357.81 | M7: =L7/$L$7 -> 1 | N7: =P7=L7 -> #VALUE! | O7: =SUM(O10:O628) -> #VALUE! | P7: =O7*K5 -> #VALUE!
B8: 0 | C8: 0 | D8: 0 | E8: 0 | G8: 0 | H8: 0 | J8: =IFERROR(IF(K8<>0,K8*$K$5,0),0) -> 0 | M8: =L8/$L$7 -> 0
A9: =LEN(C9) -> 1 | C9: I | D9: DESPESAS INDIRETAS | L9: =SUMIF(A10:A190,3,L10:L190) -> 81268.395 | M9: =L9/$L$7 -> 0.14425715 | O9: =IF(I9<>0,I9*H9*K9,) -> 0 | R9: =IF(J9<>0,J9/1.03-K9,0) -> 0
A10: =LEN(C10) -> 3 | C10: 01. | D10: SERVIÇOS TÉCNICOS E PRELIMINARES | L10: =SUMIF(A11:A27,4,L11:L27) -> 10002 | M10: =L10/$L$7 -> 0.017754258 | O10: =IF(I10<>0,I10*H10*K10,) -> 0 | R10: =IF(J10<>0,J10/1.03-K10,0) -> 0
A11: =LEN(C11) -> 4 | C11: 01.1 | D11: Serviços Preliminares | K11: =IF(A11=0,VLOOKUP(D11,'03. Insumos'!A:F,4,0),"") | L11: =SUMIF(A12:A15,6,L12:L15) -> 10002 | M11: =L11/$L$7 -> 0.017754258 | O11: =IF(I11<>0,I11*H11*K11,) -> 0 | R11: =IF(J11<>0,J11/1.03-K11,0) -> 0
A12: =LEN(C12) -> 6 | C12: 01.1.1 | D12: Serviços Preliminares | K12: =IF(A12=0,VLOOKUP(D12,'03. Insumos'!A:F,4,0),"") | L12: =SUM(L13:L15) -> 10002 | M12: =L12/$L$7 -> 0.017754258 | O12: =IF(I12<>0,I12*H12*K12,) -> 0 | R12: =IF(J12<>0,J12/1.03-K12,0) -> 0
A13: 0 | D13: 01.01.0713 | E13: =VLOOKUP(D13,'03. Insumos'!A:D,2,0) -> Seguro responsabilidade civil e cruzada | F13: FAT DIRETO | G13: =VLOOKUP(D13,'03. Insumos'!A:F,3,0) -> vb | H13: 1 | I13: 1 | J13: =IFERROR(IF(K13<>0,K13*$K$5,0),0) -> 1 | K13: =IF(A13=0,VLOOKUP(D13,'03. Insumos'!A:F,4,0),"") -> 1 | L13: =H13*J13*I13 -> 1 | M13: =L13/$L$7 -> 1.7750708e-06
A14: 0 | D14: 01.01.0001 | E14: =VLOOKUP(D14,'03. Insumos'!A:D,2,0) -> Placa de Obra | F14: RASA | G14: =VLOOKUP(D14,'03. Insumos'!A:F,3,0) -> vb | H14: 1 | I14: 1 | J14: =IFERROR(IF(K14<>0,K14*$K$5,0),0) -> 1 | K14: =IF(A14=0,VLOOKUP(D14,'03. Insumos'!A:F,4,0),"") -> 1 | L14: =H14*J14*I14 -> 1 | M14: =L14/$L$7 -> 1.7750708e-06
A15: =LEN(C15) -> 0 | D15: 01.01.1309 | E15: =VLOOKUP(D15,'03. Insumos'!A:D,2,0) -> Mestre De Obra | F15: RASA | G15: =VLOOKUP(D15,'03. Insumos'!A:F,3,0) -> mês | H15: 1 | I15: 1 | J15: =IFERROR(IF(K15<>0,K15*$K$5,0),0) -> 10000 | K15: =IF(A15=0,VLOOKUP(D15,'03. Insumos'!A:F,4,0),"") -> 10000 | L15: =H15*J15*I15 -> 10000 | M15: =L15/$L$7 -> 0.017750708 | O15: =IF(I15<>0,I15*H15*K15,) -> 10000 | R15: =IF(J15<>0,J15/1.03-K15,0) -> -291.26214
A16: =LEN(C16) -> 4 | C16: 01.2 | D16: Serviços Técnicos | K16: =IF(A16=0,VLOOKUP(D16,'03. Insumos'!A:F,4,0),"") | L16: =SUMIF(A17:A25,6,L17:L27) -> 0 | M16: =L16/$L$7 -> 0 | O16: =IF(I16<>0,I16*H16*K16,) -> 0 | R16: =IF(J16<>0,J16/1.03-K16,0) -> 0
A17: =LEN(C17) -> 6 | C17: 01.2.1 | D17: Controle Tecnológico | G17: m³ | K17: =IF(A17=0,VLOOKUP(D17,'03. Insumos'!A:F,4,0),"") | L17: =SUM(L18:L21) -> 0 | M17: =L17/$L$7 -> 0 | O17: =IF(I17<>0,I17*H17*K17,) -> 0 | R17: =IF(J17<>0,J17/1.03-K17,0) -> 0
A18: =LEN(C18) -> 0 | D18: 01.01.0105 | E18: =VLOOKUP(D18,'03. Insumos'!A:D,2,0) -> Controle Tecnológico - Ensaio compressão simples concreto NBR 7215 | F18: FAT DIRETO | G18: =VLOOKUP(D18,'03. Insumos'!A:F,3,0) -> cp | I18: 5 | J18: =IFERROR(IF(K18<>0,K18*$K$5,0),0) -> 12 | K18: =IF(A18=0,VLOOKUP(D18,'03. Insumos'!A:F,4,0),"") -> 12 | L18: =H18*J18*I18 -> 0 | M18: =L18/$L$7 -> 0 | O18: =IF(I18<>0,I18*H18*K18,) -> 0 | R18: =IF(J18<>0,J18/1.03-K18,0) -> -0.34951456
A19: =LEN(C19) -> 0 | D19: 01.01.0103 | E19: =VLOOKUP(D19,'03. Insumos'!A:D,2,0) -> Controle Tecnológico - Diária Moldador | F19: FAT DIRETO | G19: =VLOOKUP(D19,'03. Insumos'!A:F,3,0) -> dia | I19: 5 | J19: =IFERROR(IF(K19<>0,K19*$K$5,0),0) -> 225 | K19: =IF(A19=0,VLOOKUP(D19,'03. Insumos'!A:F,4,0),"") -> 225 | L19: =H19*J19*I19 -> 0 | M19: =L19/$L$7 -> 0 | O19: =IF(I19<>0,I19*H19*K19,) -> 0 | R19: =IF(J19<>0,J19/1.03-K19,0) -> -6.5533981
A20: =LEN(C20) -> 0 | D20: 01.01.0104 | E20: =VLOOKUP(D20,'03. Insumos'!A:D,2,0) -> Controle Tecnológico - Mobilização | F20: FAT DIRETO | G20: =VLOOKUP(D20,'03. Insumos'!A:F,3,0) -> uni | I20: 5 | J20: =IFERROR(IF(K20<>0,K20*$K$5,0),0) -> 155 | K20: =IF(A20=0,VLOOKUP(D20,'03. Insumos'!A:F,4,0),"") -> 155 | L20: =H20*J20*I20 -> 0 | M20: =L20/$L$7 -> 0 | O20: =IF(I20<>0,I20*H20*K20,) -> 0 | R20: =IF(J20<>0,J20/1.03-K20,0) -> -4.5145631
A21: =LEN(C21) -> 0 | D21: 01.01.0107 | E21: =VLOOKUP(D21,'03. Insumos'!A:D,2,0) -> Controle Tecnológico - Coleta de materiais na obra | F21: FAT DIRETO | G21: =VLOOKUP(D21,'03. Insumos'!A:F,3,0) -> uni | I21: 5 | J21: =IFERROR(IF(K21<>0,K21*$K$5,0),0) -> 155 | K21: =IF(A21=0,VLOOKUP(D21,'03. Insumos'!A:F,4,0),"") -> 155 | L21: =H21*J21*I21 -> 0 | M21: =L21/$L$7 -> 0 | O21: =IF(I21<>0,I21*H21*K21,) -> 0 | R21: =IF(J21<>0,J21/1.03-K21,0) -> -4.5145631
A22: =LEN(C22) -> 6 | C22: 01.2.2 | D22: Consultorias | K22: =IF(A22=0,VLOOKUP(D22,'03. Insumos'!A:F,4,0),"") | L22: =SUM(L23:L23) -> 0 | M22: =L22/$L$7 -> 0 | R22: =IF(J22<>0,J22/1.03-K22,0) -> 0
A23: =LEN(C23) -> 0 | D23: 01.01.0005 | E23: =VLOOKUP(D23,'03. Insumos'!A:D,2,0) -> Consultoria Estrutura | G23: =VLOOKUP(D23,'03. Insumos'!A:F,3,0) -> mês | J23: =IFERROR(IF(K23<>0,K23*$K$5,0),0) -> 3000 | K23: =IF(A23=0,VLOOKUP(D23,'03. Insumos'!A:F,4,0),"") -> 3000 | L23: =H23*J23*I23 -> 0 | M23: =L23/$L$7 -> 0 | O23: =IF(I23<>0,I23*H23*K23,) -> 0 | R23: =IF(J23<>0,J23/1.03-K23,0) -> -87.378641
A24: =LEN(C24) -> 6 | C24: 01.2.3 | D24: Seguro de Obra | K24: =IF(A24=0,VLOOKUP(D24,'03. Insumos'!A:F,4,0),"") | L24: =SUM(L25:L27) -> 0 | M24: =L24/$L$7 -> 0 | R24: =IF(J24<>0,J24/1.03-K24,0) -> 0
A25: =LEN(C25) -> 0 | D25: 01.01.0713 | E25: =VLOOKUP(D25,'03. Insumos'!A:D,2,0) -> Seguro responsabilidade civil e cruzada | F25: SERV. ESP. | G25: =VLOOKUP(D25,'03. Insumos'!A:F,3,0) -> vb | J25: =IFERROR(IF(K25<>0,K25*$K$5,0),0) -> 1 | K25: =IF(A25=0,VLOOKUP(D25,'03. Insumos'!A:F,4,0),"") -> 1 | L25: =H25*J25*I25 -> 0 | M25: =L25/$L$7 -> 0 | O25: =IF(I25<>0,I25*H25*K25,) -> 0 | R25: =IF(J25<>0,J25/1.03-K25,0) -> -0.029126214
A26: =LEN(C26) -> 0 | D26: 01.01.0714 | E26: =VLOOKUP(D26,'03. Insumos'!A:D,2,0) -> Seguro Performance Bond | G26: =VLOOKUP(D26,'03. Insumos'!A:F,3,0) -> vb | J26: =IFERROR(IF(K26<>0,K26*$K$5,0),0) -> 1 | K26: =IF(A26=0,VLOOKUP(D26,'03. Insumos'!A:F,4,0),"") -> 1 | L26: =H26*J26*I26 -> 0 | M26: =L26/$L$7 -> 0
A27: =LEN(C27) -> 0 | D27: 01.01.0773 | E27: =VLOOKUP(D27,'03. Insumos'!A:D,2,0) -> Carta fiança (10% valor) | G27: =VLOOKUP(D27,'03. Insumos'!A:F,3,0) -> vb | J27: =IFERROR(IF(K27<>0,K27*$K$5,0),0) -> 85135.685 | K27: =0.03*2837856.16 -> 85135.685 | L27: =H27*J27*I27 -> 0 | M27: =L27/$L$7 -> 0
A28: =LEN(C28) -> 3 | C28: 02. | D28: INSTALAÇÕES PROVISÓRIAS E CANTEIRO | L28: =SUMIF(A29:A53,4,L29:L53) -> 4 | M28: =L28/$L$7 -> 7.1002831e-06 | O28: =IF(I28<>0,I28*H28*K28,) -> 0 | R28: =IF(J28<>0,J28/1.03-K28,0) -> 0
A29: =LEN(C29) -> 0 | K29: =IF(A29=0,VLOOKUP(D29,'03. Insumos'!A:F,4,0),"") -> #N/A | M29: =L29/$L$7 -> 0 | O29: =IF(I29<>0,I29*H29*K29,) -> 0 | R29: =IF(J29<>0,J29/1.03-K29,0) -> 0
A30: =LEN(C30) -> 4 | C30: 02.1 | D30: Canteiro de Obras | K30: =IF(A30=0,VLOOKUP(D30,'03. Insumos'!A:F,4,0),"") | L30: =SUMIF(A31:A53,6,L31:L53) -> 4 | M30: =L30/$L$7 -> 7.1002831e-06 | O30: =IF(I30<>0,I30*H30*K30,) -> 0 | R30: =IF(J30<>0,J30/1.03-K30,0) -> 0
A31: =LEN(C31) -> 6 | C31: 02.1.1 | D31: Barraco | K31: =IF(A31=0,VLOOKUP(D31,'03. Insumos'!A:F,4,0),"") | L31: =SUM(L32:L37) -> 0 | M31: =L31/$L$7 -> 0 | O31: =IF(I31<>0,I31*H31*K31,) -> 0 | R31: =IF(J31<>0,J31/1.03-K31,0) -> 0
A32: =LEN(C32) -> 0 | D32: 01.01.0302 | E32: =VLOOKUP(D32,'03. Insumos'!A:D,2,0) -> Mudança do Barraco de Obra | F32: FAT DIRETO | G32: =VLOOKUP(D32,'03. Insumos'!A:F,3,0) -> vb | I32: 1 | J32: =IFERROR(IF(K32<>0,K32*$K$5,0),0) -> 3000 | K32: =IF(A32=0,VLOOKUP(D32,'03. Insumos'!A:F,4,0),"") -> 3000 | L32: =H32*J32*I32 -> 0 | M32: =L32/$L$7 -> 0 | O32: =IF(I32<>0,I32*H32*K32,) -> 0 | R32: =IF(J32<>0,J32/1.03-K32,0) -> -87.378641
A33: =LEN(C33) -> 0 | D33: 01.01.0716 | E33: =VLOOKUP(D33,'03. Insumos'!A:D,2,0) -> Mobiliário para barraco | F33: FAT DIRETO | G33: =VLOOKUP(D33,'03. Insumos'!A:F,3,0) -> vb | I33: 1 | J33: =IFERROR(IF(K33<>0,K33*$K$5,0),0) -> 1 | K33: =IF(A33=0,VLOOKUP(D33,'03. Insumos'!A:F,4,0),"") -> 1 | L33: =H33*J33*I33 -> 0 | M33: =L33/$L$7 -> 0
A34: =LEN(C34) -> 0 | D34: 01.01.0116 | E34: =VLOOKUP(D34,'03. Insumos'!A:D,2,0) -> Container - Refeitório | F34: FAT DIRETO | G34: =VLOOKUP(D34,'03. Insumos'!A:F,3,0) -> mês | I34: 4 | J34: =IFERROR(IF(K34<>0,K34*$K$5,0),0) -> 500 | K34: =IF(A34=0,VLOOKUP(D34,'03. Insumos'!A:F,4,0),"") -> 500 | L34: =H34*J34*I34 -> 0 | M34: =L34/$L$7 -> 0
A35: =LEN(C35) -> 0 | D35: 01.01.0110 | E35: =VLOOKUP(D35,'03. Insumos'!A:D,2,0) -> Container Almoxarifado | F35: FAT DIRETO | G35: =VLOOKUP(D35,'03. Insumos'!A:F,3,0) -> mês | I35: 4 | J35: =IFERROR(IF(K35<>0,K35*$K$5,0),0) -> 900 | K35: =IF(A35=0,VLOOKUP(D35,'03. Insumos'!A:F,4,0),"") -> 900 | L35: =H35*J35*I35 -> 0 | M35: =L35/$L$7 -> 0
A36: =LEN(C36) -> 0 | D36: 01.01.0112 | E36: =VLOOKUP(D36,'03. Insumos'!A:D,2,0) -> Container Banheiro | F36: FAT DIRETO | G36: =VLOOKUP(D36,'03. Insumos'!A:F,3,0) -> mês | I36: 4 | J36: =IFERROR(IF(K36<>0,K36*$K$5,0),0) -> 400 | K36: =IF(A36=0,VLOOKUP(D36,'03. Insumos'!A:F,4,0),"") -> 400 | L36: =H36*J36*I36 -> 0 | M36: =L36/$L$7 -> 0
A37: =LEN(C37) -> 0 | D37: 01.01.0115 | E37: =VLOOKUP(D37,'03. Insumos'!A:D,2,0) -> Container - Frete ida / volta | F37: FAT DIRETO | G37: =VLOOKUP(D37,'03. Insumos'!A:F,3,0) -> viagem | I37: =3*2 -> 6 | J37: =IFERROR(IF(K37<>0,K37*$K$5,0),0) -> 920 | K37: =IF(A37=0,VLOOKUP(D37,'03. Insumos'!A:F,4,0),"") -> 920 | L37: =H37*J37*I37 -> 0 | M37: =L37/$L$7 -> 0
A38: =LEN(C38) -> 6 | C38: 02.1.2 | D38: Tapume | K38: =IF(A38=0,VLOOKUP(D38,'03. Insumos'!A:F,4,0),"") | L38: =SUM(L39:L39) -> 0 | M38: =L38/$L$7 -> 0 | O38: =IF(I38<>0,I38*H38*K38,) -> 0 | R38: =IF(J38<>0,J38/1.03-K38,0) -> 0
A39: =LEN(C39) -> 0 | D39: 01.01.0121 | E39: =VLOOKUP(D39,'03. Insumos'!A:D,2,0) -> Tapume com telha metálica (h=2,20m) - material e mão de obra | F39: MAT CONSUMO | G39: =VLOOKUP(D39,'03. Insumos'!A:F,3,0) -> m | I39: 1 | J39: =IFERROR(IF(K39<>0,K39*$K$5,0),0) -> 530 | K39: =IF(A39=0,VLOOKUP(D39,'03. Insumos'!A:F,4,0),"") -> 530 | L39: =H39*J39*I39 -> 0 | M39: =L39/$L$7 -> 0
A40: =LEN(C40) -> 6 | C40: 02.1.3 | D40: Gabarito | K40: =IF(A40=0,VLOOKUP(D40,'03. Insumos'!A:F,4,0),"") | L40: =SUM(L41:L41) -> 0 | M40: =L40/$L$7 -> 0 | O40: =IF(I40<>0,I40*H40*K40,) -> 0 | R40: =IF(J40<>0,J40/1.03-K40,0) -> 0
A41: =LEN(C41) -> 0 | D41: 01.01.0126 | E41: =VLOOKUP(D41,'03. Insumos'!A:D,2,0) -> Gabarito - Material + Mão de Obra | F41: MAT CONSUMO | G41: =VLOOKUP(D41,'03. Insumos'!A:F,3,0) -> m | I41: =(25*2)+(34*2) -> 118 | J41: =IFERROR(IF(K41<>0,K41*$K$5,0),0) -> 120 | K41: =IF(A41=0,VLOOKUP(D41,'03. Insumos'!A:F,4,0),"") -> 120 | L41: =H41*J41*I41 -> 0 | M41: =L41/$L$7 -> 0
A42: =LEN(C42) -> 6 | C42: 02.1.1 | D42: Instalações provisórias | K42: =IF(A42=0,VLOOKUP(D42,'03. Insumos'!A:F,4,0),"") | L42: =SUM(L43:L53) -> 4 | M42: =L42/$L$7 -> 7.1002831e-06 | O42: =IF(I42<>0,I42*H42*K42,) -> 0 | R42: =IF(J42<>0,J42/1.03-K42,0) -> 0
A43: =LEN(C43) -> 0 | D43: 01.01.0718 | E43: =VLOOKUP(D43,'03. Insumos'!A:D,2,0) -> Itens diversos de instalações provisórias | F43: RASA | G43: =VLOOKUP(D43,'03. Insumos'!A:F,3,0) -> vb | H43: 4 | I43: 1 | J43: =IFERROR(IF(K43<>0,K43*$K$5,0),0) -> 1 | K43: =IF(A43=0,VLOOKUP(D43,'03. Insumos'!A:F,4,0),"") -> 1 | L43: =H43*J43*I43 -> 4 | M43: =L43/$L$7 -> 7.1002831e-06 | O43: =IF(I43<>0,I43*H43*K43,) -> 4 | R43: =IF(J43<>0,J43/1.03-K43,0) -> -0.029126214
A44: =LEN(C44) -> 0 | D44: 01.01.0425 | E44: =VLOOKUP(D44,'03. Insumos'!A:D,2,0) -> Bocal para lâmpada | F44: MAT CONSUMO | G44: =VLOOKUP(D44,'03. Insumos'!A:F,3,0) -> unid | I44: 10 | J44: =IFERROR(IF(K44<>0,K44*$K$5,0),0) -> 3.5 | K44: =IF(A44=0,VLOOKUP(D44,'03. Insumos'!A:F,4,0),"") -> 3.5 | L44: =H44*J44*I44 -> 0 | M44: =L44/$L$7 -> 0
A45: =LEN(C45) -> 0 | D45: 01.01.0426 | E45: =VLOOKUP(D45,'03. Insumos'!A:D,2,0) -> Lâmpada | F45: MAT CONSUMO | G45: =VLOOKUP(D45,'03. Insumos'!A:F,3,0) -> unid | I45: 10 | J45: =IFERROR(IF(K45<>0,K45*$K$5,0),0) -> 6 | K45: =IF(A45=0,VLOOKUP(D45,'03. Insumos'!A:F,4,0),"") -> 6 | L45: =H45*J45*I45 -> 0 | M45: =L45/$L$7 -> 0
A46: =LEN(C46) -> 0 | D46: 01.01.0778 | E46: =VLOOKUP(D46,'03. Insumos'!A:D,2,0) -> Refletores 400 W | F46: MAT CONSUMO | G46: =VLOOKUP(D46,'03. Insumos'!A:F,3,0) -> unid | I46: 2 | J46: =IFERROR(IF(K46<>0,K46*$K$5,0),0) -> 134 | K46: =IF(A46=0,VLOOKUP(D46,'03. Insumos'!A:F,4,0),"") -> 134 | L46: =H46*J46*I46 -> 0 | M46: =L46/$L$7 -> 0
A47: =LEN(C47) -> 0 | D47: 01.01.0427 | E47: =VLOOKUP(D47,'03. Insumos'!A:D,2,0) -> Plug macho | F47: MAT CONSUMO | G47: =VLOOKUP(D47,'03. Insumos'!A:F,3,0) -> unid | I47: 10 | J47: =IFERROR(IF(K47<>0,K47*$K$5,0),0) -> 2.75 | K47: =IF(A47=0,VLOOKUP(D47,'03. Insumos'!A:F,4,0),"") -> 2.75 | L47: =H47*J47*I47 -> 0 | M47: =L47/$L$7 -> 0
A48: =LEN(C48) -> 0 | D48: 01.01.0428 | E48: =VLOOKUP(D48,'03. Insumos'!A:D,2,0) -> Plug fêmea | F48: MAT CONSUMO | G48: =VLOOKUP(D48,'03. Insumos'!A:F,3,0) -> unid | I48: 10 | J48: =IFERROR(IF(K48<>0,K48*$K$5,0),0) -> 4.45 | K48: =IF(A48=0,VLOOKUP(D48,'03. Insumos'!A:F,4,0),"") -> 4.45 | L48: =H48*J48*I48 -> 0 | M48: =L48/$L$7 -> 0
A49: =LEN(C49) -> 0 | D49: 01.01.0589 | E49: =VLOOKUP(D49,'03. Insumos'!A:D,2,0) -> Robozinho para instalação provisória | F49: MAT CONSUMO | G49: =VLOOKUP(D49,'03. Insumos'!A:F,3,0) -> unid | I49: 1 | J49: =IFERROR(IF(K49<>0,K49*$K$5,0),0) -> 2700 | K49: =IF(A49=0,VLOOKUP(D49,'03. Insumos'!A:F,4,0),"") -> 2700 | L49: =H49*J49*I49 -> 0 | M49: =L49/$L$7 -> 0
A50: =LEN(C50) -> 0 | D50: 01.01.1321 | E50: =VLOOKUP(D50,'03. Insumos'!A:D,2,0) -> Servente | F50: MAT CONSUMO | G50: =VLOOKUP(D50,'03. Insumos'!A:F,3,0) -> mês | I50: 1 | J50: =IFERROR(IF(K50<>0,K50*$K$5,0),0) -> 2091.232 | K50: =IF(A50=0,VLOOKUP(D50,'03. Insumos'!A:F,4,0),"") -> 2091.232 | L50: =H50*J50*I50 -> 0 | M50: =L50/$L$7 -> 0
A51: =LEN(C51) -> 0 | D51: 01.01.1322 | E51: =VLOOKUP(D51,'03. Insumos'!A:D,2,0) -> Refeição (almoço + café) | F51: MAT CONSUMO | G51: =VLOOKUP(D51,'03. Insumos'!A:F,3,0) -> VB | I51: 1 | J51: =IFERROR(IF(K51<>0,K51*$K$5,0),0) -> 1 | K51: =IF(A51=0,VLOOKUP(D51,'03. Insumos'!A:F,4,0),"") -> 1 | L51: =H51*J51*I51 -> 0 | M51: =L51/$L$7 -> 0
A52: =LEN(C52) -> 0 | D52: 01.01.0788 | E52: =VLOOKUP(D52,'03. Insumos'!A:D,2,0) -> Bomba de recalque água | F52: MAT CONSUMO | G52: =VLOOKUP(D52,'03. Insumos'!A:F,3,0) -> unid | I52: 1 | J52: =IFERROR(IF(K52<>0,K52*$K$5,0),0) -> 780 | K52: =IF(A52=0,VLOOKUP(D52,'03. Insumos'!A:F,4,0),"") -> 780 | L52: =H52*J52*I52 -> 0 | M52: =L52/$L$7 -> 0
A53: =LEN(C53) -> 0 | D53: 01.01.0718 | E53: =VLOOKUP(D53,'03. Insumos'!A:D,2,0) -> Itens diversos de instalações provisórias | F53: MAT CONSUMO | G53: =VLOOKUP(D53,'03. Insumos'!A:F,3,0) -> vb | I53: 1 | J53: =IFERROR(IF(K53<>0,K53*$K$5,0),0) -> 1000 | K53: 1000 | L53: =H53*J53*I53 -> 0 | M53: =L53/$L$7 -> 0
A54: =LEN(C54) -> 3 | C54: 03. | D54: SEGURANÇA DO TRABALHO E PROTEÇÕES | L54: =SUMIF(A55:A84,4,L55:L84) -> 3099.9833 | M54: =L54/$L$7 -> 0.0055026899 | O54: =IF(I54<>0,I54*H54*K54,) -> 0 | R54: =IF(J54<>0,J54/1.03-K54,0) -> 0
A55: =LEN(C55) -> 4 | C55: 03.1 | D55: Sinalização de segurança e combate à incêndio | K55: =IF(A55=0,VLOOKUP(D55,'03. Insumos'!A:F,4,0),"") | L55: =SUMIF(A56:A58,6,L56:L58) -> 0 | M55: =L55/$L$7 -> 0 | O55: =IF(I55<>0,I55*H55*K55,) -> 0 | R55: =IF(J55<>0,J55/1.03-K55,0) -> 0
A56: =LEN(C56) -> 6 | C56: 03.1.1 | D56: Equipamentos de combate à incêndio | K56: =IF(A56=0,VLOOKUP(D56,'03. Insumos'!A:F,4,0),"") | L56: =SUM(L57:L58) -> 0 | M56: =L56/$L$7 -> 0 | O56: =IF(I56<>0,I56*H56*K56,) -> 0 | R56: =IF(J56<>0,J56/1.03-K56,0) -> 0
A57: =LEN(C57) -> 0 | D57: 01.01.0025 | E57: =VLOOKUP(D57,'03. Insumos'!A:D,2,0) -> Extintor de Pó Químico 4kg | F57: MAT CONSUMO | G57: =VLOOKUP(D57,'03. Insumos'!A:F,3,0) -> uni | J57: =IFERROR(IF(K57<>0,K57*$K$5,0),0) -> 540 | K57: =IF(A57=0,VLOOKUP(D57,'03. Insumos'!A:F,4,0),"") -> 540 | L57: =H57*J57*I57 -> 0 | M57: =L57/$L$7 -> 0 | O57: =IF(I57<>0,I57*H57*K57,) -> 0 | R57: =IF(J57<>0,J57/1.03-K57,0) -> -15.728155
A58: =LEN(C58) -> 0 | D58: 01.01.0026 | E58: =VLOOKUP(D58,'03. Insumos'!A:D,2,0) -> Extintor CO2 4Kg | F58: MAT CONSUMO | G58: =VLOOKUP(D58,'03. Insumos'!A:F,3,0) -> uni | J58: =IFERROR(IF(K58<>0,K58*$K$5,0),0) -> 370 | K58: =IF(A58=0,VLOOKUP(D58,'03. Insumos'!A:F,4,0),"") -> 370 | L58: =H58*J58*I58 -> 0 | M58: =L58/$L$7 -> 0 | O58: =IF(I58<>0,I58*H58*K58,) -> 0 | R58: =IF(J58<>0,J58/1.03-K58,0) -> -10.776699
A59: =LEN(C59) -> 4 | C59: 03.2 | D59: Documentação de segurança do trabalho | K59: =IF(A59=0,VLOOKUP(D59,'03. Insumos'!A:F,4,0),"") | L59: =SUMIF(A60:A61,6,L60:L69) -> 0 | M59: =L59/$L$7 -> 0
A60: =LEN(C60) -> 6 | C60: 03.2.1 | D60: Documentação de segurança do trabalho | K60: =IF(A60=0,VLOOKUP(D60,'03. Insumos'!A:F,4,0),"") | L60: =SUM(L61:L69) -> 0 | M60: =L60/$L$7 -> 0
A61: =LEN(C61) -> 0 | D61: 01.01.0789 | E61: =VLOOKUP(D61,'03. Insumos'!A:D,2,0) -> PCMAT por fase da obra | F61: FAT DIRETO | G61: =VLOOKUP(D61,'03. Insumos'!A:F,3,0) -> unid | I61: 1 | J61: =IFERROR(IF(K61<>0,K61*$K$5,0),0) -> 1200 | K61: =IF(A61=0,VLOOKUP(D61,'03. Insumos'!A:F,4,0),"") -> 1200 | L61: =H61*J61*I61 -> 0 | M61: =L61/$L$7 -> 0
A62: =LEN(C62) -> 0 | D62: 01.01.0790 | E62: =VLOOKUP(D62,'03. Insumos'!A:D,2,0) -> Revisão do PCMAT | F62: FAT DIRETO | G62: =VLOOKUP(D62,'03. Insumos'!A:F,3,0) -> unid | J62: =IFERROR(IF(K62<>0,K62*$K$5,0),0) -> 300 | K62: =IF(A62=0,VLOOKUP(D62,'03. Insumos'!A:F,4,0),"") -> 300 | L62: =H62*J62*I62 -> 0 | M62: =L62/$L$7 -> 0
A63: =LEN(C63) -> 0 | D63: 01.01.0791 | E63: =VLOOKUP(D63,'03. Insumos'!A:D,2,0) -> PGR por fase da obra | F63: FAT DIRETO | G63: =VLOOKUP(D63,'03. Insumos'!A:F,3,0) -> unid | I63: 1 | J63: =IFERROR(IF(K63<>0,K63*$K$5,0),0) -> 1500 | K63: =IF(A63=0,VLOOKUP(D63,'03. Insumos'!A:F,4,0),"") -> 1500 | L63: =H63*J63*I63 -> 0 | M63: =L63/$L$7 -> 0
A64: =LEN(C64) -> 0 | D64: 01.01.0792 | E64: =VLOOKUP(D64,'03. Insumos'!A:D,2,0) -> Revisão PGR | F64: FAT DIRETO | G64: =VLOOKUP(D64,'03. Insumos'!A:F,3,0) -> unid | J64: =IFERROR(IF(K64<>0,K64*$K$5,0),0) -> 369 | K64: =IF(A64=0,VLOOKUP(D64,'03. Insumos'!A:F,4,0),"") -> 369 | L64: =H64*J64*I64 -> 0 | M64: =L64/$L$7 -> 0
A65: =LEN(C65) -> 0 | D65: 01.01.0793 | E65: =VLOOKUP(D65,'03. Insumos'!A:D,2,0) -> Mapa de risco por fase da obra | F65: FAT DIRETO | G65: =VLOOKUP(D65,'03. Insumos'!A:F,3,0) -> unid | I65: 1 | J65: =IFERROR(IF(K65<>0,K65*$K$5,0),0) -> 180 | K65: =IF(A65=0,VLOOKUP(D65,'03. Insumos'!A:F,4,0),"") -> 180 | L65: =H65*J65*I65 -> 0 | M65: =L65/$L$7 -> 0
A66: =LEN(C66) -> 0 | D66: 01.01.0794 | E66: =VLOOKUP(D66,'03. Insumos'!A:D,2,0) -> PCMAT por fase da obra | F66: FAT DIRETO | G66: =VLOOKUP(D66,'03. Insumos'!A:F,3,0) -> unid | I66: 1 | J66: =IFERROR(IF(K66<>0,K66*$K$5,0),0) -> 1800 | K66: =IF(A66=0,VLOOKUP(D66,'03. Insumos'!A:F,4,0),"") -> 1800 | L66: =H66*J66*I66 -> 0 | M66: =L66/$L$7 -> 0
A67: =LEN(C67) -> 0 | D67: 01.01.1323 | E67: =VLOOKUP(D67,'03. Insumos'!A:D,2,0) -> Exame admissional / demissional / períodico | F67: FAT DIRETO | G67: =VLOOKUP(D67,'03. Insumos'!A:F,3,0) -> unid | I67: 10 | J67: =IFERROR(IF(K67<>0,K67*$K$5,0),0) -> 50 | K67: =IF(A67=0,VLOOKUP(D67,'03. Insumos'!A:F,4,0),"") -> 50 | L67: =H67*J67*I67 -> 0 | M67: =L67/$L$7 -> 0
A68: =LEN(C68) -> 0 | D68: 01.01.0796 | E68: =VLOOKUP(D68,'03. Insumos'!A:D,2,0) -> Implantação e gerenciamento da CIPA | F68: FAT DIRETO | G68: =VLOOKUP(D68,'03. Insumos'!A:F,3,0) -> mês | J68: =IFERROR(IF(K68<>0,K68*$K$5,0),0) -> 300 | K68: =IF(A68=0,VLOOKUP(D68,'03. Insumos'!A:F,4,0),"") -> 300 | L68: =H68*J68*I68 -> 0 | M68: =L68/$L$7 -> 0
A69: =LEN(C69) -> 0 | D69: 01.01.0797 | E69: =VLOOKUP(D69,'03. Insumos'!A:D,2,0) -> Treinamento para CIPA | F69: FAT DIRETO | G69: =VLOOKUP(D69,'03. Insumos'!A:F,3,0) -> unid | J69: =IFERROR(IF(K69<>0,K69*$K$5,0),0) -> 2000 | K69: =IF(A69=0,VLOOKUP(D69,'03. Insumos'!A:F,4,0),"") -> 2000 | L69: =H69*J69*I69 -> 0 | M69: =L69/$L$7 -> 0
A70: =LEN(C70) -> 4 | C70: 03.3 | D70: Equipamentos de proteção individual | K70: =IF(A70=0,VLOOKUP(D70,'03. Insumos'!A:F,4,0),"") | L70: =SUMIF(A71:A80,6,L71:L80) -> 3099.9833 | M70: =L70/$L$7 -> 0.0055026899 | O70: =IF(I70<>0,I70*H70*K70,) -> 0 | R70: =IF(J70<>0,J70/1.03-K70,0) -> 0
A71: =LEN(C71) -> 6 | C71: 03.3.1 | D71: Equipamentos de proteção individual | H71: 5 | K71: =IF(A71=0,VLOOKUP(D71,'03. Insumos'!A:F,4,0),"") | L71: =SUM(L72:L80) -> 3099.9833 | M71: =L71/$L$7 -> 0.0055026899 | O71: =IF(I71<>0,I71*#REF!*K71,) -> 0 | R71: =IF(J71<>0,J71/1.03-K71,0) -> 0
A72: =LEN(C72) -> 0 | D72: 01.01.0430 | E72: =VLOOKUP(D72,'03. Insumos'!A:D,2,0) -> Máscara | F72: RASA | G72: =VLOOKUP(D72,'03. Insumos'!A:F,3,0) -> unid | H72: 1 | I72: =H71*L2*2*4 -> 160 | J72: =IFERROR(IF(K72<>0,K72*$K$5,0),0) -> 0.47333333 | K72: =IF(A72=0,VLOOKUP(D72,'03. Insumos'!A:F,4,0),"") -> 0.47333333 | L72: =H72*J72*I72 -> 75.733333 | M72: =L72/$L$7 -> 0.00013443203 | O72: =IF(I72<>0,I72*H72*K72,) -> 75.733333 | R72: =IF(J72<>0,J72/1.03-K72,0) -> -0.013786408
A73: =LEN(C73) -> 0 | D73: 01.01.0431 | E73: =VLOOKUP(D73,'03. Insumos'!A:D,2,0) -> Bota | F73: RASA | G73: =VLOOKUP(D73,'03. Insumos'!A:F,3,0) -> unid | H73: 1 | I73: 5 | J73: =IFERROR(IF(K73<>0,K73*$K$5,0),0) -> 27 | K73: =IF(A73=0,VLOOKUP(D73,'03. Insumos'!A:F,4,0),"") -> 27 | L73: =H73*J73*I73 -> 135 | M73: =L73/$L$7 -> 0.00023963456
A74: =LEN(C74) -> 0 | D74: 01.01.1164 | E74: =VLOOKUP(D74,'03. Insumos'!A:D,2,0) -> Uniforme - Calça | F74: RASA | G74: =VLOOKUP(D74,'03. Insumos'!A:F,3,0) -> unid | H74: 1 | I74: =I73*2 -> 10 | J74: =IFERROR(IF(K74<>0,K74*$K$5,0),0) -> 30 | K74: =IF(A74=0,VLOOKUP(D74,'03. Insumos'!A:F,4,0),"") -> 30 | L74: =H74*J74*I74 -> 300 | M74: =L74/$L$7 -> 0.00053252124
A75: =LEN(C75) -> 0 | D75: 01.01.1165 | E75: =VLOOKUP(D75,'03. Insumos'!A:D,2,0) -> Uniforme - Camisa | F75: RASA | G75: =VLOOKUP(D75,'03. Insumos'!A:F,3,0) -> unid | H75: 1 | I75: =I74*3 -> 30 | J75: =IFERROR(IF(K75<>0,K75*$K$5,0),0) -> 43 | K75: =IF(A75=0,VLOOKUP(D75,'03. Insumos'!A:F,4,0),"") -> 43 | L75: =H75*J75*I75 -> 1290 | M75: =L75/$L$7 -> 0.0022898413
A76: =LEN(C76) -> 0 | D76: 01.01.0432 | E76: =VLOOKUP(D76,'03. Insumos'!A:D,2,0) -> Capacete | F76: RASA | G76: =VLOOKUP(D76,'03. Insumos'!A:F,3,0) -> unid | H76: 1 | I76: =I73 -> 5 | J76: =IFERROR(IF(K76<>0,K76*$K$5,0),0) -> 9.73 | K76: =IF(A76=0,VLOOKUP(D76,'03. Insumos'!A:F,4,0),"") -> 9.73 | L76: =H76*J76*I76 -> 48.65 | M76: =L76/$L$7 -> 8.6357194e-05
A77: =LEN(C77) -> 0 | D77: 01.01.0433 | E77: =VLOOKUP(D77,'03. Insumos'!A:D,2,0) -> Cinto de segurança | F77: RASA | G77: =VLOOKUP(D77,'03. Insumos'!A:F,3,0) -> unid | H77: 1 | I77: =I73 -> 5 | J77: =IFERROR(IF(K77<>0,K77*$K$5,0),0) -> 46.2 | K77: =IF(A77=0,VLOOKUP(D77,'03. Insumos'!A:F,4,0),"") -> 46.2 | L77: =H77*J77*I77 -> 231 | M77: =L77/$L$7 -> 0.00041004135
A78: =LEN(C78) -> 0 | D78: 01.01.0434 | E78: =VLOOKUP(D78,'03. Insumos'!A:D,2,0) -> Corda de poliamida (50 m) | F78: RASA | G78: =VLOOKUP(D78,'03. Insumos'!A:F,3,0) -> rolo | H78: 1 | I78: 2 | J78: =IFERROR(IF(K78<>0,K78*$K$5,0),0) -> 350 | K78: =IF(A78=0,VLOOKUP(D78,'03. Insumos'!A:F,4,0),"") -> 350 | L78: =H78*J78*I78 -> 700 | M78: =L78/$L$7 -> 0.0012425496
A79: =LEN(C79) -> 0 | D79: 01.01.0435 | E79: =VLOOKUP(D79,'03. Insumos'!A:D,2,0) -> Luva | F79: RASA | G79: =VLOOKUP(D79,'03. Insumos'!A:F,3,0) -> unid | H79: 1 | I79: =H71*L2*2 -> 40 | J79: =IFERROR(IF(K79<>0,K79*$K$5,0),0) -> 7.74 | K79: =IF(A79=0,VLOOKUP(D79,'03. Insumos'!A:F,4,0),"") -> 7.74 | L79: =H79*J79*I79 -> 309.6 | M79: =L79/$L$7 -> 0.00054956192
A80: =LEN(C80) -> 0 | D80: 01.01.0436 | E80: =VLOOKUP(D80,'03. Insumos'!A:D,2,0) -> Óculos | F80: RASA | G80: =VLOOKUP(D80,'03. Insumos'!A:F,3,0) -> unid | H80: 1 | I80: =H71 -> 5 | J80: =IFERROR(IF(K80<>0,K80*$K$5,0),0) -> 2 | K80: =IF(A80=0,VLOOKUP(D80,'03. Insumos'!A:F,4,0),"") -> 2 | L80: =H80*J80*I80 -> 10 | M80: =L80/$L$7 -> 1.7750708e-05
A81: =LEN(C81) -> 4 | C81: 03.3 | D81: Equipamentos de proteção coletiva | K81: =IF(A81=0,VLOOKUP(D81,'03. Insumos'!A:F,4,0),"") | L81: =SUMIF(A82:A84,6,L82:L84) -> 0 | M81: =L81/$L$7 -> 0 | O81: =IF(I81<>0,I81*H81*K81,) -> 0 | R81: =IF(J81<>0,J81/1.03-K81,0) -> 0
A82: =LEN(C82) -> 6 | C82: 03.3.1 | D82: Equipamentos de proteção coletiva | K82: =IF(A82=0,VLOOKUP(D82,'03. Insumos'!A:F,4,0),"") | L82: =SUM(L83:L84) -> 0 | M82: =L82/$L$7 -> 0 | O82: =IF(I82<>0,I82*H82*K82,) -> 0 | R82: =IF(J82<>0,J82/1.03-K82,0) -> 0
A83: =LEN(C83) -> 0 | D83: 01.01.0741 | E83: =VLOOKUP(D83,'03. Insumos'!A:D,2,0) -> Proteção de periferia | F83: FAT DIRETO | G83: =VLOOKUP(D83,'03. Insumos'!A:F,3,0) -> vb | J83: =IFERROR(IF(K83<>0,K83*$K$5,0),0) -> 1683.2 | K83: =(40*5.58)+(60*16)+(10*50) -> 1683.2 | L83: =H83*J83*I83 -> 0 | M83: =L83/$L$7 -> 0
A84: =LEN(C84) -> 0 | D84: 01.01.0742 | E84: =VLOOKUP(D84,'03. Insumos'!A:D,2,0) -> Linha de vida | F84: FAT DIRETO | G84: =VLOOKUP(D84,'03. Insumos'!A:F,3,0) -> vb | J84: =IFERROR(IF(K84<>0,K84*$K$5,0),0) -> 11688.62 | K84: =IF(A84=0,VLOOKUP(D84,'03. Insumos'!A:F,4,0),"") -> 11688.62 | L84: =H84*J84*I84 -> 0 | M84: =L84/$L$7 -> 0 | O84: =IF(I84<>0,I84*H84*K84,) -> 0 | R84: =IF(J84<>0,J84/1.03-K84,0) -> -340.44524
A85: =LEN(C85) -> 3 | C85: 04. | D85: MÁQUINAS E EQUIPAMENTOS | L85: =SUMIF(A86:A143,4,L86:L143) -> 10179.5 | M85: =L85/$L$7 -> 0.018069333 | O85: =IF(I85<>0,I85*H85*K85,) -> 0 | R85: =IF(J85<>0,J85/1.03-K85,0) -> 0
A86: =LEN(C86) -> 0 | J86: =IFERROR(IF(K86<>0,K86*$K$5,0),0) -> 0 | K86: =IF(A86=0,VLOOKUP(D86,'03. Insumos'!A:F,4,0),"") -> #N/A | M86: =L86/$L$7 -> 0 | O86: =IF(I86<>0,I86*H86*K86,) -> 0 | R86: =IF(J86<>0,J86/1.03-K86,0) -> 0
A87: =LEN(C87) -> 4 | C87: 04.1 | D87: Equipamentos | K87: =IF(A87=0,VLOOKUP(D87,'03. Insumos'!A:F,4,0),"") | L87: =SUMIF(A88:A117,6,L88:L117) -> 820 | M87: =L87/$L$7 -> 0.001455558 | O87: =IF(I87<>0,I87*H87*K87,) -> 0 | R87: =IF(J87<>0,J87/1.03-K87,0) -> 0
A88: =LEN(C88) -> 6 | C88: 04.1.1 | D88: Locação de equipamentos diversos | K88: =IF(A88=0,VLOOKUP(D88,'03. Insumos'!A:F,4,0),"") | L88: =SUM(L89:L115) -> 820 | M88: =L88/$L$7 -> 0.001455558 | O88: =IF(I88<>0,I88*H88*K88,) -> 0 | R88: =IF(J88<>0,J88/1.03-K88,0) -> 0
A89: =LEN(C89) -> 0 | D89: 01.01.0438 | E89: =VLOOKUP(D89,'03. Insumos'!A:D,2,0) -> Serra mármore | F89: FAT DIRETO | G89: =VLOOKUP(D89,'03. Insumos'!A:F,3,0) -> mês | H89: 1 | I89: =L2 -> 4 | J89: =IFERROR(IF(K89<>0,K89*$K$5,0),0) -> 80 | K89: =IF(A89=0,VLOOKUP(D89,'03. Insumos'!A:F,4,0),"") -> 80 | L89: =H89*J89*I89 -> 320 | M89: =L89/$L$7 -> 0.00056802265
A90: =LEN(C90) -> 0 | D90: 01.01.0757 | E90: =VLOOKUP(D90,'03. Insumos'!A:D,2,0) -> Torre de iluminação | F90: FAT DIRETO | G90: =VLOOKUP(D90,'03. Insumos'!A:F,3,0) -> mês | J90: =IFERROR(IF(K90<>0,K90*$K$5,0),0) -> 1490 | K90: =IF(A90=0,VLOOKUP(D90,'03. Insumos'!A:F,4,0),"") -> 1490 | L90: =H90*J90*I90 -> 0 | M90: =L90/$L$7 -> 0
A91: =LEN(C91) -> 0 | D91: 01.01.0782 | E91: =VLOOKUP(D91,'03. Insumos'!A:D,2,0) -> Traçador | F91: FAT DIRETO | G91: =VLOOKUP(D91,'03. Insumos'!A:F,3,0) -> mês | J91: =IFERROR(IF(K91<>0,K91*$K$5,0),0) -> 105 | K91: =IF(A91=0,VLOOKUP(D91,'03. Insumos'!A:F,4,0),"") -> 105 | L91: =H91*J91*I91 -> 0 | M91: =L91/$L$7 -> 0
A92: =LEN(C92) -> 0 | D92: 01.01.0032 | E92: =VLOOKUP(D92,'03. Insumos'!A:D,2,0) -> Velox Locação | F92: FAT DIRETO | G92: =VLOOKUP(D92,'03. Insumos'!A:F,3,0) -> mês | J92: =IFERROR(IF(K92<>0,K92*$K$5,0),0) -> 290 | K92: =IF(A92=0,VLOOKUP(D92,'03. Insumos'!A:F,4,0),"") -> 290 | L92: =H92*J92*I92 -> 0 | M92: =L92/$L$7 -> 0
A93: =LEN(C93) -> 0 | D93: 01.01.0780 | E93: =VLOOKUP(D93,'03. Insumos'!A:D,2,0) -> Bomba submersa | F93: FAT DIRETO | G93: =VLOOKUP(D93,'03. Insumos'!A:F,3,0) -> mês | J93: =IFERROR(IF(K93<>0,K93*$K$5,0),0) -> 230 | K93: =IF(A93=0,VLOOKUP(D93,'03. Insumos'!A:F,4,0),"") -> 230 | L93: =H93*J93*I93 -> 0 | M93: =L93/$L$7 -> 0
A94: =LEN(C94) -> 0 | D94: 01.01.0781 | E94: =VLOOKUP(D94,'03. Insumos'!A:D,2,0) -> Mangote para bomba 20 m | F94: FAT DIRETO | G94: =VLOOKUP(D94,'03. Insumos'!A:F,3,0) -> mês | J94: =IFERROR(IF(K94<>0,K94*$K$5,0),0) -> 96 | K94: =IF(A94=0,VLOOKUP(D94,'03. Insumos'!A:F,4,0),"") -> 96 | L94: =H94*J94*I94 -> 0 | M94: =L94/$L$7 -> 0
A95: =LEN(C95) -> 0 | D95: 01.01.0758 | E95: =VLOOKUP(D95,'03. Insumos'!A:D,2,0) -> Martelete 10 Kg | F95: FAT DIRETO | G95: =VLOOKUP(D95,'03. Insumos'!A:F,3,0) -> mês | I95: 1 | J95: =IFERROR(IF(K95<>0,K95*$K$5,0),0) -> 490 | K95: =IF(A95=0,VLOOKUP(D95,'03. Insumos'!A:F,4,0),"") -> 490 | L95: =H95*J95*I95 -> 0 | M95: =L95/$L$7 -> 0
A96: =LEN(C96) -> 0 | D96: 01.01.0439 | E96: =VLOOKUP(D96,'03. Insumos'!A:D,2,0) -> MARTELETE (SDS PLUS) 220VOLTS BIF | F96: FAT DIRETO | G96: =VLOOKUP(D96,'03. Insumos'!A:F,3,0) -> mês | H96: 1 | I96: =L2 -> 4 | J96: =IFERROR(IF(K96<>0,K96*$K$5,0),0) -> 125 | K96: =IF(A96=0,VLOOKUP(D96,'03. Insumos'!A:F,4,0),"") -> 125 | L96: =H96*J96*I96 -> 500 | M96: =L96/$L$7 -> 0.00088753539
A97: =LEN(C97) -> 0 | D97: 01.01.0439 | E97: =VLOOKUP(D97,'03. Insumos'!A:D,2,0) -> MARTELETE (SDS PLUS) 220VOLTS BIF | F97: FAT DIRETO | G97: =VLOOKUP(D97,'03. Insumos'!A:F,3,0) -> mês | I97: =L2 -> 4 | J97: =IFERROR(IF(K97<>0,K97*$K$5,0),0) -> 125 | K97: =IF(A97=0,VLOOKUP(D97,'03. Insumos'!A:F,4,0),"") -> 125 | L97: =H97*J97*I97 -> 0 | M97: =L97/$L$7 -> 0
A98: =LEN(C98) -> 0 | D98: 01.01.0760 | E98: =VLOOKUP(D98,'03. Insumos'!A:D,2,0) -> Compressor 185 PCM para 2 marteletes | F98: FAT DIRETO | G98: =VLOOKUP(D98,'03. Insumos'!A:F,3,0) -> mês | J98: =IFERROR(IF(K98<>0,K98*$K$5,0),0) -> 2100 | K98: =IF(A98=0,VLOOKUP(D98,'03. Insumos'!A:F,4,0),"") -> 2100 | L98: =H98*J98*I98 -> 0 | M98: =L98/$L$7 -> 0
A99: =LEN(C99) -> 0 | D99: 01.01.0761 | E99: =VLOOKUP(D99,'03. Insumos'!A:D,2,0) -> Lance de mangueira c/ 20 m | F99: FAT DIRETO | G99: =VLOOKUP(D99,'03. Insumos'!A:F,3,0) -> mês | J99: =IFERROR(IF(K99<>0,K99*$K$5,0),0) -> 98 | K99: =IF(A99=0,VLOOKUP(D99,'03. Insumos'!A:F,4,0),"") -> 98 | L99: =H99*J99*I99 -> 0 | M99: =L99/$L$7 -> 0
A100: =LEN(C100) -> 0 | D100: 01.01.0762 | E100: =VLOOKUP(D100,'03. Insumos'!A:D,2,0) -> Mini escavadeira | F100: FAT DIRETO | G100: =VLOOKUP(D100,'03. Insumos'!A:F,3,0) -> mês | J100: =IFERROR(IF(K100<>0,K100*$K$5,0),0) -> 24000 | K100: =IF(A100=0,VLOOKUP(D100,'03. Insumos'!A:F,4,0),"") -> 24000 | L100: =H100*J100*I100 -> 0 | M100: =L100/$L$7 -> 0
A101: =LEN(C101) -> 0 | D101: 01.01.0779 | E101: =VLOOKUP(D101,'03. Insumos'!A:D,2,0) -> Retroescavadeira com operador | F101: FAT DIRETO | G101: =VLOOKUP(D101,'03. Insumos'!A:F,3,0) -> mês | J101: =IFERROR(IF(K101<>0,K101*$K$5,0),0) -> 16000 | K101: =IF(A101=0,VLOOKUP(D101,'03. Insumos'!A:F,4,0),"") -> 16000 | L101: =H101*J101*I101 -> 0 | M101: =L101/$L$7 -> 0
A102: =LEN(C102) -> 0 | D102: 01.01.0752 | E102: =VLOOKUP(D102,'03. Insumos'!A:D,2,0) -> Plataforma elevatória de 7 m (tesourinha) | F102: FAT DIRETO | G102: =VLOOKUP(D102,'03. Insumos'!A:F,3,0) -> mês | J102: =IFERROR(IF(K102<>0,K102*$K$5,0),0) -> 1600 | K102: =IF(A102=0,VLOOKUP(D102,'03. Insumos'!A:F,4,0),"") -> 1600 | L102: =H102*J102*I102 -> 0 | M102: =L102/$L$7 -> 0
...

Sheet 01. Resumo Final
I1: VERIFICAÇÃO GERAL
B2: RESUMO DE ORÇAMENTO PRÉ EXECUTIVO - R04 - 10/03/2025 | I2: =I20=I27=I53=#REF! -> #REF!
E4: Data de Atualização:
B5: Projeto: | C5: Ana Silva | E5: Data Base:
B6: Cidade: | C6: Rio de Janeiro | E6: 45992
B7: Bairro: | C7: Pechincha | E7: INCC (n-1):
B8: Uso: | C8: Multifamiliar | E8: 1218.747
D12: ATC: | E12: 4002.24
B13: Prazo: | C13: ='02. Orçamento'!L2 -> 36 | D13: A. PRIVATIVA: | E13: 2561.21
D14: UNIDADES | E14: 37
C16: DESCRIÇÃO | D16: TOTAL (R$) | E16: TOTAL (INCC) | F16: Perc. (%)
B18: VALOR TOTAL | D18: =D20+D27 -> 16469381 | E18: =IF($E$8=0,0,D18/$E$8) -> 13513.372 | F18: =F20+F27 -> 1
B20: CUSTO INDIRETO | D20: =SUM(D21:D26) -> 4421734.1 | E20: =IF($E$8=0,0,D20/$E$8) -> 3628.0985 | F20: =SUM(F21:F26) -> 0.2684821 | I20: =D20=#REF! -> #REF!
B21: 01 | C21: ='02. Orçamento'!D10 -> SERVIÇOS TÉCNICOS E PRELIMINARES | D21: ='02. Orçamento'!L10 -> 245350 | E21: =IF($E$8=0,0,D21/$E$8) -> 201.31332 | F21: =IF(D21<>0,D21/$D$18,) -> 0.014897341 | I21: =SUM(D21:D26)/D18 -> 0.2684821 | J21: SERVIÇOS TÉCNICOS E PRELIMINARES | K21: 516512.39 | L21: =K21=D21 -> FALSE
B22: 02 | C22: ='02. Orçamento'!D49 -> INSTALAÇÕES PROVISÓRIAS E CANTEIRO | D22: ='02. Orçamento'!L49 -> 288861.24 | E22: =IF($E$8=0,0,D22/$E$8) -> 237.01493 | F22: =IF(D22<>0,D22/$D$18,) -> 0.017539289 | J22: INSTALAÇÕES PROVISÓRIAS E CANTEIRO | K22: 366211.25 | L22: =K22=D22 -> FALSE
B23: 03 | C23: ='02. Orçamento'!D72 -> SEGURANÇA DO TRABALHO E PROTEÇÕES | D23: ='02. Orçamento'!L72 -> 215613.63 | E23: =IF($E$8=0,0,D23/$E$8) -> 176.91418 | F23: =IF(D23<>0,D23/$D$18,) -> 0.013091787 | J23: SEGURANÇA DO TRABALHO E PROTEÇÕES | K23: 238669.84 | L23: =K23=D23 -> FALSE
B24: 04 | C24: ='02. Orçamento'!D124 -> MÁQUINAS E EQUIPAMENTOS | D24: ='02. Orçamento'!L124 -> 426714.53 | E24: =IF($E$8=0,0,D24/$E$8) -> 350.1256 | F24: =IF(D24<>0,D24/$D$18,) -> 0.025909566 | J24: MÁQUINAS E EQUIPAMENTOS | K24: 282257.69 | L24: =K24=D24 -> FALSE
B25: 05 | C25: ='02. Orçamento'!D205 -> MÃO DE OBRA DE APOIO / ENGENHARIA | D25: ='02. Orçamento'!L205 -> 2895074.7 | E25: =IF($E$8=0,0,D25/$E$8) -> 2375.4518 | F25: =IF(D25<>0,D25/$D$18,) -> 0.17578527 | J25: MÃO DE OBRA DE APOIO / ENGENHARIA | K25: 1105068.2 | L25: =K25=D25 -> FALSE
B26: 06 | C26: ='02. Orçamento'!D270 -> DESPESAS OPERACIONAIS | D26: ='02. Orçamento'!L270 -> 350120 | E26: =IF($E$8=0,0,D26/$E$8) -> 287.27866 | F26: =IF(D26<>0,D26/$D$18,) -> 0.021258843 | J26: DESPESAS OPERACIONAIS | K26: 419700 | L26: =K26=D26 -> FALSE
B27: CUSTO DIRETO | D27: =SUM(D28:D49) -> 12047647 | E27: =IF($E$8=0,0,D27/$E$8) -> 9885.2735 | F27: =SUM(F28:F49) -> 0.7315179 | I27: =D27=#REF! -> #REF! | L27: =K27=D27 -> FALSE
B28: 07 | C28: ='02. Orçamento'!D298 -> MOVIMENTAÇÃO DE TERRA / DEMOLIÇÃO | D28: ='02. Orçamento'!L298 -> 255846.5 | E28: =IF($E$8=0,0,D28/$E$8) -> 209.92585 | F28: =IF(D28<>0,D28/$D$18,) -> 0.015534676 | J28: DEMOLIÇÃO E ACERTOS | K28: 106481.39 | L28: =K28=D28 -> FALSE
B29: 08 | C29: ='02. Orçamento'!D328 -> INFRAESTRUTURA | D29: ='02. Orçamento'!L328 -> 970337.51 | E29: =IF($E$8=0,0,D29/$E$8) -> 796.17633 | F29: =IF(D29<>0,D29/$D$18,) -> 0.058917665 | J29: INFRAESTRUTURA | K29: 526061.97 | L29: =K29=D29 -> FALSE
B30: 09 | C30: ='02. Orçamento'!D516 -> SUPRAESTRUTURA | D30: ='02. Orçamento'!L516 -> 2724364.1 | E30: =IF($E$8=0,0,D30/$E$8) -> 2235.3812 | F30: =IF(D30<>0,D30/$D$18,) -> 0.16541994 | J30: SUPRAESTRUTURA | K30: 2956692.1 | L30: =K30=D30 -> FALSE
B31: 10 | C31: ='02. Orçamento'!D571 -> PAREDES E PAINÉIS | D31: ='02. Orçamento'!L571 -> 651943.64 | E31: =IF($E$8=0,0,D31/$E$8) -> 534.92943 | F31: =IF(D31<>0,D31/$D$18,) -> 0.039585192 | J31: PAREDES E PAINÉIS | K31: 829933.93 | L31: =K31=D31 -> FALSE
B32: 11 | C32: ='02. Orçamento'!D700 -> INSTALAÇÕES | D32: ='02. Orçamento'!L700 -> 2424709 | E32: =IF($E$8=0,0,D32/$E$8) -> 1989.5097 | F32: =IF(D32<>0,D32/$D$18,) -> 0.14722526 | J32: INSTALAÇÕES | K32: 3332378.2 | L32: =K32=D32 -> FALSE
B33: 12 | C33: ='02. Orçamento'!D736 -> IMPERMEABILIZAÇÃO | D33: ='02. Orçamento'!L736 -> 241413.07 | E33: =IF($E$8=0,0,D33/$E$8) -> 198.08301 | F33: =IF(D33<>0,D33/$D$18,) -> 0.014658296 | J33: IMPERMEABILIZAÇÃO | K33: 374231.47 | L33: =K33=D33 -> FALSE
B34: 13 | C34: ='02. Orçamento'!D771 -> MASSA | D34: ='02. Orçamento'!L771 -> 904246.01 | E34: =IF($E$8=0,0,D34/$E$8) -> 741.94727 | F34: =IF(D34<>0,D34/$D$18,) -> 0.054904673 | J34: MASSA | K34: 1132893.3 | L34: =K34=D34 -> FALSE
B35: 14 | C35: ='02. Orçamento'!D802 -> FORRO | D35: ='02. Orçamento'!L802 -> 34872.39 | E35: =IF($E$8=0,0,D35/$E$8) -> 28.613314 | F35: =IF(D35<>0,D35/$D$18,) -> 0.0021174074 | J35: FORRO | K35: 200048.28 | L35: =K35=D35 -> FALSE
B36: 15 | C36: ='02. Orçamento'!D810 -> REVESTIMENTOS INTERNOS | D36: ='02. Orçamento'!L810 -> 829026.71 | E36: =IF($E$8=0,0,D36/$E$8) -> 680.22872 | F36: =IF(D36<>0,D36/$D$18,) -> 0.050337453 | J36: REVESTIMENTOS INTERNOS E EXTERNOS | K36: 1298586.2 | L36: =K36=D36 -> FALSE
B37: 16 | C37: ='02. Orçamento'!D921 -> PEDRAS NATURAIS E SINTÉTICAS | D37: ='02. Orçamento'!L921 -> 203956.92 | E37: =IF($E$8=0,0,D37/$E$8) -> 167.34968 | F37: =IF(D37<>0,D37/$D$18,) -> 0.012384006 | J37: PEDRAS NATURAIS E SINTÉTICAS | K37: 315285.35 | L37: =K37=D37 -> FALSE
B38: 17 | C38: ='02. Orçamento'!D987 -> ESQUADRIAS EM ALUMÍNIO, FERRO E MADEIRA | D38: ='02. Orçamento'!L987 -> 875132.39 | E38: =IF($E$8=0,0,D38/$E$8) -> 718.05911 | F38: =IF(D38<>0,D38/$D$18,) -> 0.053136931 | J38: ESQUADRIAS EM ALUMÍNIO E MADEIRA | K38: 2043561.7 | L38: =K38=D38 -> FALSE
B39: 18 | C39: ='02. Orçamento'!D1079 -> FACHADA | D39: ='02. Orçamento'!L1079 -> 580194.62 | E39: =IF($E$8=0,0,D39/$E$8) -> 476.05829 | F39: =IF(D39<>0,D39/$D$18,) -> 0.035228683 | J39: FACHADA | K39: 563518.38 | L39: =K39=D39 -> FALSE
B40: 19 | C40: ='02. Orçamento'!D1124 -> ELEVADORES | D40: ='02. Orçamento'!L1124 -> 178000 | E40: =IF($E$8=0,0,D40/$E$8) -> 146.05164 | F40: =IF(D40<>0,D40/$D$18,) -> 0.010807935 | J40: ELEVADORES | K40: 290000 | L40: =K40=D40 -> FALSE
B41: 20 | C41: ='02. Orçamento'!D1130 -> PINTURA | D41: ='02. Orçamento'!L1130 -> 417699.28 | E41: =IF($E$8=0,0,D41/$E$8) -> 342.72846 | F41: =IF(D41<>0,D41/$D$18,) -> 0.025362172 | J41: PINTURA | K41: 446866.2 | L41: =K41=D41 -> FALSE
B42: 21 | C42: ='02. Orçamento'!D1164 -> LOUÇAS E METAIS | D42: ='02. Orçamento'!L1164 -> 161044.31 | E42: =IF($E$8=0,0,D42/$E$8) -> 132.13924 | F42: =IF(D42<>0,D42/$D$18,) -> 0.0097784066 | J42: LOUÇAS E METAIS | K42: 145944.21 | L42: =K42=D42 -> FALSE
B43: 22 | C43: ='02. Orçamento'!D1196 -> AR CONDICIONADO E EXAUSTÃO | D43: ='02. Orçamento'!L1196 -> 357846.29 | E43: =IF($E$8=0,0,D43/$E$8) -> 293.61819 | F43: =IF(D43<>0,D43/$D$18,) -> 0.021727974 | J43: ITENS DIVEROS | K43: 0 | L43: =K43=D43 -> FALSE
B44: 23 | C44: ='02. Orçamento'!D1205 -> EQUIPAMENTOS ESPECIAIS | D44: ='02. Orçamento'!L1205 -> 64065.424 | E44: =IF($E$8=0,0,D44/$E$8) -> 52.566631 | F44: =IF(D44<>0,D44/$D$18,) -> 0.0038899715 | J44: ITENS DIVEROS | K44: 0 | L44: =K44=D44 -> FALSE
B45: 24 | C45: ='02. Orçamento'!D1234 -> LIMPEZA DE OBRA | D45: ='02. Orçamento'!L1234 -> 57871.36 | E45: =IF($E$8=0,0,D45/$E$8) -> 47.48431 | F45: =IF(D45<>0,D45/$D$18,) -> 0.0035138757 | J45: LIMPEZA DE OBRA | K45: 86087.383 | L45: =K45=D45 -> FALSE
B46: 25 | C46: ='02. Orçamento'!D1245 -> ÁREA COMUM | D46: ='02. Orçamento'!L1245 -> 115077.84 | E46: =IF($E$8=0,0,D46/$E$8) -> 94.423073 | F46: =IF(D46<>0,D46/$D$18,) -> 0.0069873806 | J46: EVENTUAIS | K46: 527309.68 | L46: =K46=D46 -> FALSE
B47: 25 | C47: =#REF! -> #REF! | D47: =IFERROR(#REF!,0) -> 0 | F47: =IF(D47<>0,D47/$D$18,) -> 0
B48: 26 | C48: =#REF! -> #REF! | D48: =IFERROR(#REF!,0) -> 0 | E48: =IF($E$7=0,0,D48/$E$7) -> #VALUE! | F48: =IF(D48<>0,D48/$D$18,) -> 0
B49: 27 | C49: =#REF! -> #REF! | D49: =IFERROR(#REF!,0) -> 0 | E49: =IF($E$7=0,0,D49/$E$7) -> #VALUE! | F49: =IF(D49<>0,D49/$D$18,) -> 0
E52: CUSTO ATC | F52: CUSTO A PRIV
C53: CUSTO RASO | D53: =D27+D20 -> 16469381 | E53: =D53/$E$12 -> 4115.0409 | F53: =D53/$E$13 -> 6430.3128 | I53: =#REF!=D53 -> #REF!
C54: BDI | D54: ='02. Orçamento'!L1346 -> 0 | E54: =D54/$E$12 -> 0 | F54: =D54/$E$13 -> 0
C55: CUSTO TOTAL | D55: =SUM(D53:D54) -> 16469381 | E55: =D55/$E$12 -> 4115.0409 | F55: =D55/$E$13 -> 6430.3128
I56: =D53/545 -> 30219.049
C59: ASSISTÊNCIA TÉCNICA - 1% CUSTO RASO | D59: =D53*0.01 -> 164693.81 | E59: =D59/$E$12 -> 41.150409 | F59: =D59/$E$13 -> 64.303128
I60: =#REF!/545 -> #REF!
C63: Área ùtil (m²) | D63: =#REF! -> #REF! | E63: =SUM('Quadro de áreas'!#REF!,'Quadro de áreas'!#REF!,'Quadro de áreas'!#REF!,'Quadro de áreas'!#REF!,'Quadro de áreas'!#REF!) -> #REF!
C64: Custo p/ m² | D64: =D53/D63 -> #REF! | E64: =#REF!/E63 -> #REF!

Sheet 02. Dados Gerais
A1: DADOS GERAIS
A4: =CONCATENATE('01. Resumo Final'!B5," ",'01. Resumo Final'!C5) -> Projeto: Ana Silva
A5: =CONCATENATE('01. Resumo Final'!B6," ",'01. Resumo Final'!C6) -> Cidade: Rio de Janeiro
A6: =CONCATENATE('01. Resumo Final'!B7," ",'01. Resumo Final'!C7) -> Bairro: Pechincha
I8: uso
A9: USO: | B9: Residencial | F9: PADRÃO : | G9: Residencial | I9: Comercial
I10: Residencial
I11: Misto
A12: ÍNICIO DO ORÇAMENTO: | B12: 45950 | F12: QUANT. DE BLOCOS: | G12: 1
A14: MÊS BASE: | B14: 45962 | F14: QUANT. DE APARTAMENTOS: | G14: 105
A16: INCC (MÊS BASE-2): | B16: 1218.747 | F16: QUANT. DE QUARTOS:
A18: ÁREA DE CONSTRUÇÃO: | B18: ='01. Resumo Final'!E12 -> 4002.24 | F18: QUANT. DE SALAS COMERCIAIS:
A20: ÁREA PRIVATIVA | B20: 3512.2 | F20: QUANT. DE SALAS CORPORATIVAS:
A22: ÁREA EQUIVALENTE: | B22: =B18*1.2 -> 4802.688 | F22: QUANT. DE LOJAS
A24: PRAZO (MESES): | B24: 16 | F24: TOTAL DE UNIDADES: | G24: =G22+G20+G18+G14 -> 105
A26: TIPOLOGIA
A28: DESCRIÇÃO: | B28: Prédio residencial com 1 bloco, térreo e 7 pavimentos tipos e cobertura rooftop
A30: TIPOLOGIA:
A32: Subsolo | B32: não | F32: Pavimento Tipo 1 | G32: sim
A33: Térreo | B33: sim | F33: Pavimento Tipo 2 | G33: não
A34: Embasamento | B34: não | F34: Cobertura | G34: sim
A35: Jirau no térreo | B35: não | F35: Casa de Máquinas | G35: não
A36: Pavimento garagem elevada | B36: não | F36: Telhado | G36: sim
A38: TIPO DE FUNDAÇÃO: | B38: Estaca Hélice Contínua | F38: TIPO DE ESTRUTURA: | G38: Pilotis + Alvenaria Estrutural
A40: LATERAIS COM VIZINHO: | B40: Não | F40: TIPO DE FACHADA: | G40: Pintura Acrílica Externa

Sheet 03. Quadro de Áreas
E2: Data: | H2: 41648
E3: Código: | H3: 002.14 - Monumental Niemeyer
E4: Revisão: | H4: 00
B5: Quadro de Áreas
B7: ÁREA TOTAL DO TERRENO | E7: 3847.6
A9: FILTRO | B9: Pavimento | C9: Área Existente | D9: Qtde | E9: TOTAL | F9: Índice | G9: Área Equivalente | H9: Área Privativa | I9: Área Privativa Total
A11: =IF(E11>0,1,"X") -> 1 | B11: BLOCO 1 | E11: =SUM(E12:E61) -> 33721.51 | G11: =SUM(G12:G61) -> 31467.523 | I11: =SUM(I12:I61) -> 11533.8
A12: =IF(E12>0,1,"X") -> 1 | B12: 1º SUBSOLO ENTERRADO COM ÁGUA | C12: 3811.09 | D12: 1 | E12: =C12*D12 -> 3811.09 | F12: 1 | G12: =E12*F12 -> 3811.09 | I12: =+H12*D12 -> 0
A13: =IF(E13>0,1,"X") -> 1 | B13: 2º SUBSOLO ENTERRADO COM ÁGUA | C13: 3712.11 | D13: 1 | E13: =C13*D13 -> 3712.11 | F13: 1 | G13: =E13*F13 -> 3712.11 | I13: =+H13*D13 -> 0
A14: =IF(E14>0,1,"X") -> 1 | B14: 3º SUBSOLO ENTERRADO COM ÁGUA | C14: 3742.8 | D14: 1 | E14: =C14*D14 -> 3742.8 | F14: 1 | G14: =E14*F14 -> 3742.8 | I14: =+H14*D14 -> 0
A15: =IF(E15>0,1,"X") -> 1 | B15: RESERVATÓRIO ENTERRADO COM ÁGUA | C15: =181.49+52.5+52.5 -> 286.49 | D15: 1 | E15: =C15*D15 -> 286.49 | F15: 1 | G15: =E15*F15 -> 286.49 | H15: 0 | I15: =+H15*D15 -> 0
A16: =IF(E16>0,1,"X") -> X | B16: RESERVATÓRIO SEMI-ENTERRADO COM ÁGUA | E16: =C16*D16 -> 0 | F16: 0.9 | G16: =E16*F16 -> 0 | I16: =+H16*D16 -> 0
A17: =IF(E17>0,1,"X") -> X | B17: SEMI-ENTERRADO COM ÁGUA | E17: =C17*D17 -> 0 | F17: 0.9 | G17: =E17*F17 -> 0 | I17: =+H17*D17 -> 0
A18: =IF(E18>0,1,"X") -> X | B18: SEMI-ENTERRADO SEM ÁGUA | E18: =C18*D18 -> 0 | F18: 0.7 | G18: =E18*F18 -> 0 | I18: =+H18*D18 -> 0
A19: =IF(E19>0,1,"X") -> 1 | B19: LOJAS (TÉRREO) | C19: =336.89 -> 336.89 | D19: 1 | E19: =C19*D19 -> 336.89 | F19: 0.75 | G19: =E19*F19 -> 252.6675 | H19: =C19 -> 336.89 | I19: =+H19*D19 -> 336.89
A20: =IF(E20>0,1,"X") -> 1 | B20: LOJAS (2º PAVIMENTO) | C20: =509.6 -> 509.6 | D20: 1 | E20: =C20*D20 -> 509.6 | F20: 0.75 | G20: =E20*F20 -> 382.2 | H20: =C20 -> 509.6 | I20: =+H20*D20 -> 509.6
A21: =IF(E21>0,1,"X") -> 1 | B21: TÉRREO COBERTO FECHADO | C21: 144.29 | D21: 1 | E21: =C21*D21 -> 144.29 | F21: 1 | G21: =E21*F21 -> 144.29 | H21: 0 | I21: =+H21*D21 -> 0
A22: =IF(E22>0,1,"X") -> 1 | B22: TÉRREO COBERTO ABERTO | C22: 1420.48 | D22: 1 | E22: =C22*D22 -> 1420.48 | F22: 0.75 | G22: =E22*F22 -> 1065.36 | I22: =+H22*D22 -> 0
A23: =IF(E23>0,1,"X") -> X | B23: TÉRREO COBERTO FECHADO (GARAGEM) | E23: =C23*D23 -> 0 | F23: 0.6 | G23: =E23*F23 -> 0 | H23: 0 | I23: =+H23*D23 -> 0
A24: =IF(E24>0,1,"X") -> 1 | B24: TÉRREO DESCOBERTO SOBRE LAJE COM OU SEM GARAGEM | C24: 1258.9 | D24: 1 | E24: =C24*D24 -> 1258.9 | F24: 0.5 | G24: =E24*F24 -> 629.45 | I24: =+H24*D24 -> 0
A25: =IF(E25>0,1,"X") -> X | B25: TÉRREO DESCOBERTO SOBRE SOLO | E25: =C25*D25 -> 0 | F25: 0.25 | G25: =E25*F25 -> 0 | I25: =+H25*D25 -> 0
A26: =IF(E26>0,1,"X") -> X | B26: VIAS INTERNAS | E26: =C26*D26 -> 0 | F26: 0.3 | G26: =E26*F26 -> 0 | I26: =+H26*D26 -> 0
A27: =IF(E27>0,1,"X") -> X | B27: VIAS INTERNAS (CALÇADAS) | E27: =C27*D27 -> 0 | F27: 0.25 | G27: =E27*F27 -> 0 | I27: =+H27*D27 -> 0
A28: =IF(E28>0,1,"X") -> X | B28: LAZER COBERTO | E28: =C28*D28 -> 0 | F28: 1 | G28: =E28*F28 -> 0 | I28: =+H28*D28 -> 0
A29: =IF(E29>0,1,"X") -> X | B29: LAZER DESCOBERTO | E29: =C29*D29 -> 0 | F29: 0.5 | G29: =E29*F29 -> 0 | I29: =+H29*D29 -> 0
A30: =IF(E30>0,1,"X") -> X | B30: CONEXÃO BLOCOS FECHADO | E30: =C30*D30 -> 0 | F30: 1 | G30: =E30*F30 -> 0 | I30: =+H30*D30 -> 0
A31: =IF(E31>0,1,"X") -> 1 | B31: CONEXÃO BLOCOS (TERRAÇO 3º PAVIMENTO) | C31: 531.71 | D31: 1 | E31: =C31*D31 -> 531.71 | F31: 0.5 | G31: =E31*F31 -> 265.855 | I31: =+H31*D31 -> 0
A32: =IF(E32>0,1,"X") -> 1 | B32: CONEXÃO BLOCOS (TERRAÇO 12º PAVIMENTO) | C32: 536.34 | D32: 1 | E32: =C32*D32 -> 536.34 | F32: 0.5 | G32: =E32*F32 -> 268.17 | I32: =+H32*D32 -> 0
A33: =IF(E33>0,1,"X") -> X | B33: PISCINA | E33: =C33*D33 -> 0 | F33: 1 | G33: =E33*F33 -> 0 | H33: 0 | I33: =+H33*D33 -> 0
A34: =IF(E34>0,1,"X") -> X | B34: JIRAU VAZIO (VAZIO 1° PAV.) | E34: =C34*D34 -> 0 | F34: 0.35 | G34: =E34*F34 -> 0 | H34: 0 | I34: =+H34*D34 -> 0
A35: =IF(E35>0,1,"X") -> X | B35: JIRAU COMO DEPENDÊNCIA | E35: =C35*D35 -> 0 | F35: 0.75 | G35: =E35*F35 -> 0 | I35: =+H35*D35 -> 0
A36: =IF(E36>0,1,"X") -> X | B36: JIRAU FECHADO COMO GARAGEM | E36: =C36*D36 -> 0 | F36: 0.6 | G36: =E36*F36 -> 0 | I36: =+H36*D36 -> 0
A37: =IF(E37>0,1,"X") -> X | B37: JIRAU ABERTO COMO GARAGEM | E37: =C37*D37 -> 0 | F37: 0.5 | G37: =E37*F37 -> 0 | I37: =+H37*D37 -> 0
A38: =IF(E38>0,1,"X") -> X | B38: JIRAU COBERTO FECHADO | E38: =C38*D38 -> 0 | F38: 1 | G38: =E38*F38 -> 0 | I38: =+H38*D38 -> 0
A39: =IF(E39>0,1,"X") -> X | B39: GARAGEM ELEVADA FECHADA COBERTA | E39: =C39*D39 -> 0 | F39: 0.6 | G39: =E39*F39 -> 0 | I39: =+H39*D39 -> 0
A40: =IF(E40>0,1,"X") -> X | B40: GARAGEM ELEVADA ABERTA COBERTA | E40: =C40*D40 -> 0 | F40: 0.5 | G40: =E40*F40 -> 0 | H40: 0 | I40: =+H40*D40 -> 0
A41: =IF(E41>0,1,"X") -> X | B41: GARAGEM ELEVADA DESCOBERTA | E41: =C41*D41 -> 0 | F41: 0.5 | G41: =E41*F41 -> 0 | H41: 0 | I41: =+H41*D41 -> 0
A42: =IF(E42>0,1,"X") -> X | B42: PUC GARAGEM SOBRE SOLO | E42: =C42*D42 -> 0 | F42: 0.25 | G42: =E42*F42 -> 0 | I42: =+H42*D42 -> 0
A43: =IF(E43>0,1,"X") -> X | B43: PUC GARAGEM ELEVADA DESCOBERTA | E43: =C43*D43 -> 0 | F43: 0.5 | G43: =E43*F43 -> 0 | I43: =+H43*D43 -> 0
A44: =IF(E44>0,1,"X") -> X | B44: GARAGEM SOB TRANSIÇÃO | E44: =C44*D44 -> 0 | F44: 0.7 | G44: =E44*F44 -> 0 | I44: =+H44*D44 -> 0
A45: =IF(E45>0,1,"X") -> X | B45: PUC COBERTO FECHADO | E45: =C45*D45 -> 0 | F45: 1 | G45: =E45*F45 -> 0 | H45: 0 | I45: =+H45*D45 -> 0
A46: =IF(E46>0,1,"X") -> X | B46: PUC COBERTO ABERTO | E46: =C46*D46 -> 0 | F46: 0.75 | G46: =E46*F46 -> 0 | H46: 0 | I46: =+H46*D46 -> 0
A47: =IF(E47>0,1,"X") -> X | B47: PUC DESCOBERTO | E47: =C47*D47 -> 0 | F47: 0.5 | G47: =E47*F47 -> 0 | H47: 0 | I47: =+H47*D47 -> 0
A48: =IF(E48>0,1,"X") -> 1 | B48: PAVIMENTOS TIPO 1 (CIRCULAÇÃO 2º PAVIMENTO) | C48: 934.98 | D48: 1 | E48: =C48*D48 -> 934.98 | F48: 1 | G48: =E48*F48 -> 934.98 | I48: =+H48*D48 -> 0
A49: =IF(E49>0,1,"X") -> 1 | B49: PAVIMENTOS TIPO 2 (3º PAVIMENTO) | C49: 578.52 | D49: 1 | E49: =C49*D49 -> 578.52 | F49: 1 | G49: =E49*F49 -> 578.52 | H49: 347.21 | I49: =+H49*D49 -> 347.21
A50: =IF(E50>0,1,"X") -> 1 | B50: PAVIMENTOS TIPO 3 (4º ao 10º PAVIMENTO) | C50: 628.6 | D50: 7 | E50: =C50*D50 -> 4400.2 | F50: 1 | G50: =E50*F50 -> 4400.2 | H50: 455.08 | I50: =+H50*D50 -> 3185.56
A51: =IF(E51>0,1,"X") -> 1 | B51: PAVIMENTOS TIPO 4 (11º PAVIMENTO) | C51: 630.05 | D51: 1 | E51: =C51*D51 -> 630.05 | F51: 1 | G51: =E51*F51 -> 630.05 | H51: 455.55 | I51: =+H51*D51 -> 455.55
A52: =IF(E52>0,1,"X") -> 1 | B52: PAVIMENTOS TIPO 5 (12º PAVIMENTO) | C52: 630.24 | D52: 1 | E52: =C52*D52 -> 630.24 | F52: 1 | G52: =E52*F52 -> 630.24 | H52: 332.34 | I52: =+H52*D52 -> 332.34
A53: =IF(E53>0,1,"X") -> 1 | B53: PAVIMENTOS TIPO 6 (13º PAVIMENTO) | C53: 630.24 | D53: 1 | E53: =C53*D53 -> 630.24 | F53: 1 | G53: =E53*F53 -> 630.24 | H53: 455.52 | I53: =+H53*D53 -> 455.52
A54: =IF(E54>0,1,"X") -> 1 | B54: PAVIMENTOS TIPO 7 (14º ao 25º PAVIMENTO) | C54: 630.29 | D54: 12 | E54: =C54*D54 -> 7563.48 | F54: 1 | G54: =E54*F54 -> 7563.48 | H54: 454.64 | I54: =+H54*D54 -> 5455.68
A55: =IF(E55>0,1,"X") -> 1 | B55: LAJE DESCOBERTA (JARDIM 3º PAVIMENTO) | C55: 191.52 | D55: 1 | E55: =C55*D55 -> 191.52 | F55: 0.25 | G55: =E55*F55 -> 47.88 | I55: =+H55*D55 -> 0
A56: =IF(E56>0,1,"X") -> 1 | B56: ÚLTIMO TIPO (26º PAVIMENTO) | C56: 630.25 | D56: 1 | E56: =C56*D56 -> 630.25 | F56: 1 | G56: =E56*F56 -> 630.25 | H56: 455.45 | I56: =+H56*D56 -> 455.45
A57: =IF(E57>0,1,"X") -> X | B57: COBERTURA COBERTA | E57: =C57*D57 -> 0 | F57: 1 | G57: =E57*F57 -> 0 | I57: =+H57*D57 -> 0
A58: =IF(E58>0,1,"X") -> X | B58: COBERTURA DESCOBERTA | E58: =C58*D58 -> 0 | F58: 0.5 | G58: =E58*F58 -> 0 | I58: =+H58*D58 -> 0
A59: =IF(E59>0,1,"X") -> 1 | B59: PAVIMENTO TÉCNICO | C59: 611.12 | D59: 1 | E59: =C59*D59 -> 611.12 | F59: 1 | G59: =E59*F59 -> 611.12 | I59: =+H59*D59 -> 0
A60: =IF(E60>0,1,"X") -> 1 | B60: TELHADO COBERTO | C60: 123.37 | D60: 1 | E60: =C60*D60 -> 123.37 | F60: 1 | G60: =E60*F60 -> 123.37 | I60: =+H60*D60 -> 0
A61: =IF(E61>0,1,"X") -> 1 | B61: TELHADO DESCOBERTO | C61: 506.84 | D61: 1 | E61: =C61*D61 -> 506.84 | F61: 0.25 | G61: =E61*F61 -> 126.71 | I61: =+H61*D61 -> 0
A62: =IF(E62>0,1,"X") -> 1 | B62: SUBTOTAL 1 (m²) | E62: =SUM(E12:E61) -> 33721.51 | G62: =SUM(G12:G61) -> 31467.523 | I62: =SUM(I12:I61) -> 11533.8
A64: =IF(E64>0,1,"X") -> 1 | B64: BLOCO 2 | E64: =SUM(E65:E114) -> 18247.21 | G64: =SUM(G65:G114) -> 17478.993 | I64: =SUM(I65:I114) -> 10345.09
A65: =IF(E65>0,1,"X") -> X | B65: 1º SUBSOLO ENTERRADO COM ÁGUA | E65: =C65*D65 -> 0 | F65: 1 | G65: =E65*F65 -> 0 | I65: =+H65*D65 -> 0
A66: =IF(E66>0,1,"X") -> X | B66: 2º SUBSOLO ENTERRADO COM ÁGUA | E66: =C66*D66 -> 0 | F66: 1 | G66: =E66*F66 -> 0 | I66: =+H66*D66 -> 0
A67: =IF(E67>0,1,"X") -> X | B67: 3º SUBSOLO ENTERRADO COM ÁGUA | E67: =C67*D67 -> 0 | F67: 1 | G67: =E67*F67 -> 0 | I67: =+H67*D67 -> 0
A68: =IF(E68>0,1,"X") -> X | B68: RESERVATÓRIO ENTERRADO COM ÁGUA | E68: =C68*D68 -> 0 | F68: 1 | G68: =E68*F68 -> 0 | I68: =+H68*D68 -> 0
A69: =IF(E69>0,1,"X") -> X | B69: RESERVATÓRIO SEMI-ENTERRADO COM ÁGUA | E69: =C69*D69 -> 0 | F69: 0.9 | G69: =E69*F69 -> 0 | I69: =+H69*D69 -> 0
A70: =IF(E70>0,1,"X") -> X | B70: SEMI-ENTERRADO COM ÁGUA | E70: =C70*D70 -> 0 | F70: 0.9 | G70: =E70*F70 -> 0 | I70: =+H70*D70 -> 0
A71: =IF(E71>0,1,"X") -> X | B71: SEMI-ENTERRADO SEM ÁGUA | E71: =C71*D71 -> 0 | F71: 0.7 | G71: =E71*F71 -> 0 | I71: =+H71*D71 -> 0
A72: =IF(E72>0,1,"X") -> X | B72: LOJAS (TÉRREO) | E72: =C72*D72 -> 0 | F72: 0.75 | G72: =E72*F72 -> 0 | I72: =+H72*D72 -> 0
A73: =IF(E73>0,1,"X") -> X | B73: LOJAS (2º PAVIMENTO) | E73: =C73*D73 -> 0 | F73: 0.75 | G73: =E73*F73 -> 0 | I73: =+H73*D73 -> 0
A74: =IF(E74>0,1,"X") -> 1 | B74: TÉRREO COBERTO FECHADO | C74: =558.61+8.47 -> 567.08 | D74: 1 | E74: =C74*D74 -> 567.08 | F74: 1 | G74: =E74*F74 -> 567.08 | I74: =+H74*D74 -> 0
A75: =IF(E75>0,1,"X") -> X | B75: TÉRREO COBERTO ABERTO | E75: =C75*D75 -> 0 | F75: 0.75 | G75: =E75*F75 -> 0 | I75: =+H75*D75 -> 0
A76: =IF(E76>0,1,"X") -> X | B76: TÉRREO COBERTO FECHADO (GARAGEM) | E76: =C76*D76 -> 0 | F76: 0.6 | G76: =E76*F76 -> 0 | I76: =+H76*D76 -> 0
A77: =IF(E77>0,1,"X") -> X | B77: TÉRREO DESCOBERTO SOBRE LAJE COM OU SEM GARAGEM | E77: =C77*D77 -> 0 | F77: 0.5 | G77: =E77*F77 -> 0 | I77: =+H77*D77 -> 0
A78: =IF(E78>0,1,"X") -> X | B78: TÉRREO DESCOBERTO SOBRE SOLO | E78: =C78*D78 -> 0 | F78: 0.25 | G78: =E78*F78 -> 0 | I78: =+H78*D78 -> 0
A79: =IF(E79>0,1,"X") -> X | B79: VIAS INTERNAS | E79: =C79*D79 -> 0 | F79: 0.3 | G79: =E79*F79 -> 0 | I79: =+H79*D79 -> 0
A80: =IF(E80>0,1,"X") -> X | B80: VIAS INTERNAS (CALÇADAS) | E80: =C80*D80 -> 0 | F80: 0.25 | G80: =E80*F80 -> 0 | I80: =+H80*D80 -> 0
A81: =IF(E81>0,1,"X") -> X | B81: LAZER COBERTO | E81: =C81*D81 -> 0 | F81: 1 | G81: =E81*F81 -> 0 | I81: =+H81*D81 -> 0
A82: =IF(E82>0,1,"X") -> X | B82: LAZER DESCOBERTO | E82: =C82*D82 -> 0 | F82: 0.5 | G82: =E82*F82 -> 0 | I82: =+H82*D82 -> 0
A83: =IF(E83>0,1,"X") -> X | B83: CONEXÃO BLOCOS FECHADO | E83: =C83*D83 -> 0 | F83: 1 | G83: =E83*F83 -> 0 | I83: =+H83*D83 -> 0
A84: =IF(E84>0,1,"X") -> X | B84: CONEXÃO BLOCOS (TERRAÇO 3º PAVIMENTO) | E84: =C84*D84 -> 0 | F84: 0.5 | G84: =E84*F84 -> 0 | I84: =+H84*D84 -> 0
A85: =IF(E85>0,1,"X") -> X | B85: CONEXÃO BLOCOS (TERRAÇO 12º PAVIMENTO) | E85: =C85*D85 -> 0 | F85: 0.5 | G85: =E85*F85 -> 0 | I85: =+H85*D85 -> 0
A86: =IF(E86>0,1,"X") -> X | B86: PISCINA | E86: =C86*D86 -> 0 | F86: 1 | G86: =E86*F86 -> 0 | H86: 0 | I86: =+H86*D86 -> 0
A87: =IF(E87>0,1,"X") -> X | B87: JIRAU VAZIO (VAZIO 1° PAV.) | E87: =C87*D87 -> 0 | F87: 0.35 | G87: =E87*F87 -> 0 | H87: 0 | I87: =+H87*D87 -> 0
A88: =IF(E88>0,1,"X") -> X | B88: JIRAU COMO DEPENDÊNCIA | E88: =C88*D88 -> 0 | F88: 0.75 | G88: =E88*F88 -> 0 | I88: =+H88*D88 -> 0
A89: =IF(E89>0,1,"X") -> X | B89: JIRAU FECHADO COMO GARAGEM | E89: =C89*D89 -> 0 | F89: 0.6 | G89: =E89*F89 -> 0 | I89: =+H89*D89 -> 0
A90: =IF(E90>0,1,"X") -> X | B90: JIRAU ABERTO COMO GARAGEM | E90: =C90*D90 -> 0 | F90: 0.5 | G90: =E90*F90 -> 0 | I90: =+H90*D90 -> 0
A91: =IF(E91>0,1,"X") -> X | B91: JIRAU COBERTO FECHADO | E91: =C91*D91 -> 0 | F91: 1 | G91: =E91*F91 -> 0 | I91: =+H91*D91 -> 0
A92: =IF(E92>0,1,"X") -> X | B92: GARAGEM ELEVADA FECHADA COBERTA | E92: =C92*D92 -> 0 | F92: 0.6 | G92: =E92*F92 -> 0 | I92: =+H92*D92 -> 0
A93: =IF(E93>0,1,"X") -> X | B93: GARAGEM ELEVADA ABERTA COBERTA | E93: =C93*D93 -> 0 | F93: 0.5 | G93: =E93*F93 -> 0 | H93: 0 | I93: =+H93*D93 -> 0
A94: =IF(E94>0,1,"X") -> X | B94: GARAGEM ELEVADA DESCOBERTA | E94: =C94*D94 -> 0 | F94: 0.5 | G94: =E94*F94 -> 0 | H94: 0 | I94: =+H94*D94 -> 0
A95: =IF(E95>0,1,"X") -> X | B95: PUC GARAGEM SOBRE SOLO | E95: =C95*D95 -> 0 | F95: 0.25 | G95: =E95*F95 -> 0 | I95: =+H95*D95 -> 0
A96: =IF(E96>0,1,"X") -> X | B96: PUC GARAGEM ELEVADA DESCOBERTA | E96: =C96*D96 -> 0 | F96: 0.5 | G96: =E96*F96 -> 0 | I96: =+H96*D96 -> 0
A97: =IF(E97>0,1,"X") -> X | B97: GARAGEM SOB TRANSIÇÃO | E97: =C97*D97 -> 0 | F97: 0.7 | G97: =E97*F97 -> 0 | I97: =+H97*D97 -> 0
A98: =IF(E98>0,1,"X") -> X | B98: PUC COBERTO FECHADO | E98: =C98*D98 -> 0 | F98: 1 | G98: =E98*F98 -> 0 | H98: 0 | I98: =+H98*D98 -> 0
A99: =IF(E99>0,1,"X") -> X | B99: PUC COBERTO ABERTO | E99: =C99*D99 -> 0 | F99: 0.75 | G99: =E99*F99 -> 0 | H99: 0 | I99: =+H99*D99 -> 0
A100: =IF(E100>0,1,"X") -> X | B100: PUC DESCOBERTO | E100: =C100*D100 -> 0 | F100: 0.5 | G100: =E100*F100 -> 0 | H100: 0 | I100: =+H100*D100 -> 0
A101: =IF(E101>0,1,"X") -> 1 | B101: PAVIMENTOS TIPO 1 (2º PAVIMENTO) | C101: 916.88 | D101: 1 | E101: =C101*D101 -> 916.88 | F101: 1 | G101: =E101*F101 -> 916.88 | H101: 587.17 | I101: =+H101*D101 -> 587.17
A102: =IF(E102>0,1,"X") -> 1 | B102: PAVIMENTOS TIPO 2 (3º PAVIMENTO) | C102: 542.59 | D102: 1 | E102: =C102*D102 -> 542.59 | F102: 1 | G102: =E102*F102 -> 542.59 | I102: =+H102*D102 -> 0
A103: =IF(E103>0,1,"X") -> 1 | B103: PAVIMENTOS TIPO 3 (4º ao 10º PAVIMENTO) | C103: 630.22 | D103: 7 | E103: =C103*D103 -> 4411.54 | F103: 1 | G103: =E103*F103 -> 4411.54 | H103: 412.16 | I103: =+H103*D103 -> 2885.12
A104: =IF(E104>0,1,"X") -> 1 | B104: PAVIMENTOS TIPO 4 (11º PAVIMENTO) | C104: 630.22 | D104: 1 | E104: =C104*D104 -> 630.22 | F104: 1 | G104: =E104*F104 -> 630.22 | H104: 412.44 | I104: =+H104*D104 -> 412.44
A105: =IF(E105>0,1,"X") -> 1 | B105: PAVIMENTOS TIPO 5 (12º PAVIMENTO) | C105: 630.22 | D105: 1 | E105: =C105*D105 -> 630.22 | F105: 1 | G105: =E105*F105 -> 630.22 | I105: =+H105*D105 -> 0
...

Sheet 02. Orçamento
E1: PLANILHA ORÇAMENTÁRIA DETALHADA | K1: formulado | L1: PRAZO (meses)
L2: 36
I3: =L2 -> 36
K4: % DISTR
F5: CATEGORIA | G5: UNIDADE | H5: QTD. | I5: QTD. TOTAL | J5: VALOR | K5: 1 | L5: TOTAL | O5: VALOR SEM % DISTR
B7: CUSTO TOTAL | L7: =SUM(L9+L297) -> 16469381 | M7: =L7/$L$7 -> 1 | N7: =P7=L7 -> #VALUE! | O7: =SUM(O10:O1246) -> #VALUE! | P7: =O7*K5 -> #VALUE!
B8: 0 | C8: 0 | D8: 0 | E8: 0 | G8: 0 | H8: 0 | J8: =IFERROR(IF(K8<>0,K8*$K$5,0),0) -> 0 | M8: =L8/$L$7 -> 0
A9: =LEN(C9) -> 1 | C9: I | D9: DESPESAS INDIRETAS | L9: =SUMIF(A10:A296,3,L10:L296) -> 4421734.1 | M9: =L9/$L$7 -> 0.2684821 | O9: =IF(I9<>0,I9*H9*K9,) -> 0 | R9: =IF(J9<>0,J9/1.03-K9,0) -> 0
A10: =LEN(C10) -> 3 | C10: 01. | D10: SERVIÇOS TÉCNICOS E PRELIMINARES | L10: =SUMIF(A11:A48,4,L11:L48) -> 245350 | M10: =L10/$L$7 -> 0.014897341 | O10: =IF(I10<>0,I10*H10*K10,) -> 0 | R10: =IF(J10<>0,J10/1.03-K10,0) -> 0
A11: =LEN(C11) -> 4 | C11: 01.1 | D11: Serviços Preliminares | K11: =IF(A11=0,VLOOKUP(D11,'03. Insumos'!A:F,4,0),"") | L11: =SUMIF(A12:A18,6,L12:L18) -> 18050 | M11: =L11/$L$7 -> 0.0010959732 | O11: =IF(I11<>0,I11*H11*K11,) -> 0 | R11: =IF(J11<>0,J11/1.03-K11,0) -> 0
A12: =LEN(C12) -> 6 | C12: 01.1.1 | D12: Serviços Preliminares | H12: 1 | K12: =IF(A12=0,VLOOKUP(D12,'03. Insumos'!A:F,4,0),"") | L12: =SUM(L13:L18) -> 18050 | M12: =L12/$L$7 -> 0.0010959732 | O12: =IF(I12<>0,I12*H12*K12,) -> 0 | R12: =IF(J12<>0,J12/1.03-K12,0) -> 0
A13: 0 | D13: 01.01.0713 | E13: =VLOOKUP(D13,'03. Insumos'!A:D,2,0) -> Seguro responsabilidade civil e cruzada | F13: RASA | G13: =VLOOKUP(D13,'03. Insumos'!A:F,3,0) -> vb | I13: 1 | J13: =IFERROR(IF(K13<>0,K13*$K$5,0),0) -> 1 | K13: =IF(A13=0,VLOOKUP(D13,'03. Insumos'!A:F,4,0),"") -> 1 | L13: =H13*J13*I13 -> 0 | M13: =L13/$L$7 -> 0
A14: 0 | D14: 01.01.0001 | E14: =VLOOKUP(D14,'03. Insumos'!A:D,2,0) -> Placa de Obra | F14: RASA | G14: =VLOOKUP(D14,'03. Insumos'!A:F,3,0) -> vb | H14: 8700 | I14: 1 | J14: 1 | K14: =IF(A14=0,VLOOKUP(D14,'03. Insumos'!A:F,4,0),"") -> 1 | L14: =H14*J14*I14 -> 8700 | M14: =L14/$L$7 -> 0.00052825299
A15: =LEN(C15) -> 0 | D15: 01.01.3143 | E15: =VLOOKUP(D15,'03. Insumos'!A:D,2,0) -> Licença CET-RIO | F15: RASA | G15: =VLOOKUP(D15,'03. Insumos'!A:F,3,0) -> vb | I15: 1 | J15: 1 | K15: =IF(A15=0,VLOOKUP(D15,'03. Insumos'!A:F,4,0),"") -> 1 | L15: =H15*J15*I15 -> 0 | M15: =L15/$L$7 -> 0 | O15: =IF(I15<>0,I15*H15*K15,) -> 0 | R15: =IF(J15<>0,J15/1.03-K15,0) -> -0.029126214
A16: =LEN(C16) -> 0 | D16: 01.01.3175 | E16: =VLOOKUP(D16,'03. Insumos'!A:D,2,0) -> Licença Água e Esgoto | F16: RASA | G16: =VLOOKUP(D16,'03. Insumos'!A:F,3,0) -> vb | H16: 9000 | I16: 1 | J16: 1 | K16: =IF(A16=0,VLOOKUP(D16,'03. Insumos'!A:F,4,0),"") -> 1 | L16: =H16*J16*I16 -> 9000 | M16: =L16/$L$7 -> 0.00054646861 | O16: =IF(I16<>0,I16*H16*K16,) -> 9000 | R16: =IF(J16<>0,J16/1.03-K16,0) -> -0.029126214
A17: =LEN(C17) -> 0 | D17: 01.01.3174 | E17: =VLOOKUP(D17,'03. Insumos'!A:D,2,0) -> Licença Tapume | F17: RASA | G17: =VLOOKUP(D17,'03. Insumos'!A:F,3,0) -> vb | I17: 1 | J17: 1 | K17: =IF(A17=0,VLOOKUP(D17,'03. Insumos'!A:F,4,0),"") -> 1 | L17: =H17*J17*I17 -> 0 | M17: =L17/$L$7 -> 0 | O17: =IF(I17<>0,I17*H17*K17,) -> 0 | R17: =IF(J17<>0,J17/1.03-K17,0) -> -0.029126214
A18: =LEN(C18) -> 0 | D18: 01.01.1305 | E18: =VLOOKUP(D18,'03. Insumos'!A:D,2,0) -> ART | F18: RASA | G18: =VLOOKUP(D18,'03. Insumos'!A:F,3,0) -> vb | H18: 350 | I18: 1 | J18: 1 | K18: =IF(A18=0,VLOOKUP(D18,'03. Insumos'!A:F,4,0),"") -> 1 | L18: =H18*J18*I18 -> 350 | M18: =L18/$L$7 -> 2.1251557e-05 | O18: =IF(I18<>0,I18*H18*K18,) -> 350 | R18: =IF(J18<>0,J18/1.03-K18,0) -> -0.029126214
A19: =LEN(C19) -> 4 | C19: 01.2 | D19: Serviços Técnicos | K19: =IF(A19=0,VLOOKUP(D19,'03. Insumos'!A:F,4,0),"") | L19: =SUMIF(A20:A46,6,L20:L48) -> 227300 | M19: =L19/$L$7 -> 0.013801368 | O19: =IF(I19<>0,I19*H19*K19,) -> 0 | R19: =IF(J19<>0,J19/1.03-K19,0) -> 0
A20: =LEN(C20) -> 6 | C20: 01.2.2 | D20: Projetos - Custo Incorporação | K20: =IF(A20=0,VLOOKUP(D20,'03. Insumos'!A:F,4,0),"") | L20: =SUM(L21:L26) -> 0 | M20: =L20/$L$7 -> 0 | R20: =IF(J20<>0,J20/1.03-K20,0) -> 0
A21: =LEN(C21) -> 0 | D21: 01.01.2595 | E21: =VLOOKUP(D21,'03. Insumos'!A:D,2,0) -> Projeto de Instalações e Combate a Incêndio | F21: FAT DIRETO | G21: =VLOOKUP(D21,'03. Insumos'!A:F,3,0) -> vb | I21: 1 | J21: =IFERROR(IF(K21<>0,K21*$K$5,0),0) -> 1 | K21: =IF(A21=0,VLOOKUP(D21,'03. Insumos'!A:F,4,0),"") -> 1 | L21: =H21*J21*I21 -> 0 | M21: =L21/$L$7 -> 0 | O21: =IF(I21<>0,I21*H21*K21,) -> 0 | R21: =IF(J21<>0,J21/1.03-K21,0) -> -0.029126214
A22: =LEN(C22) -> 0 | D22: 01.01.2596 | E22: =VLOOKUP(D22,'03. Insumos'!A:D,2,0) -> Projeto de Exaustão Mecânica e Ar Condicionado | F22: FAT DIRETO | G22: =VLOOKUP(D22,'03. Insumos'!A:F,3,0) -> vb | I22: 1 | J22: =IFERROR(IF(K22<>0,K22*$K$5,0),0) -> 1 | K22: =IF(A22=0,VLOOKUP(D22,'03. Insumos'!A:F,4,0),"") -> 1 | L22: =H22*J22*I22 -> 0 | M22: =L22/$L$7 -> 0 | O22: =IF(I22<>0,I22*H22*K22,) -> 0 | R22: =IF(J22<>0,J22/1.03-K22,0) -> -0.029126214
A23: =LEN(C23) -> 0 | D23: 01.01.2597 | E23: =VLOOKUP(D23,'03. Insumos'!A:D,2,0) -> Projeto de Estrutura | F23: FAT DIRETO | G23: =VLOOKUP(D23,'03. Insumos'!A:F,3,0) -> vb | I23: 1 | J23: =IFERROR(IF(K23<>0,K23*$K$5,0),0) -> 1 | K23: =IF(A23=0,VLOOKUP(D23,'03. Insumos'!A:F,4,0),"") -> 1 | L23: =H23*J23*I23 -> 0 | M23: =L23/$L$7 -> 0 | O23: =IF(I23<>0,I23*H23*K23,) -> 0 | R23: =IF(J23<>0,J23/1.03-K23,0) -> -0.029126214
A24: =LEN(C24) -> 0 | D24: 01.01.2598 | E24: =VLOOKUP(D24,'03. Insumos'!A:D,2,0) -> Projeto de Fundações | F24: FAT DIRETO | G24: =VLOOKUP(D24,'03. Insumos'!A:F,3,0) -> vb | I24: 1 | J24: =IFERROR(IF(K24<>0,K24*$K$5,0),0) -> 1 | K24: =IF(A24=0,VLOOKUP(D24,'03. Insumos'!A:F,4,0),"") -> 1 | L24: =H24*J24*I24 -> 0 | M24: =L24/$L$7 -> 0 | O24: =IF(I24<>0,I24*H24*K24,) -> 0 | R24: =IF(J24<>0,J24/1.03-K24,0) -> -0.029126214
A25: =LEN(C25) -> 0 | D25: 01.01.2599 | E25: =VLOOKUP(D25,'03. Insumos'!A:D,2,0) -> Projeto Executivo de Arquitetura | F25: FAT DIRETO | G25: =VLOOKUP(D25,'03. Insumos'!A:F,3,0) -> vb | I25: 1 | J25: =IFERROR(IF(K25<>0,K25*$K$5,0),0) -> 1 | K25: =IF(A25=0,VLOOKUP(D25,'03. Insumos'!A:F,4,0),"") -> 1 | L25: =H25*J25*I25 -> 0 | M25: =L25/$L$7 -> 0 | O25: =IF(I25<>0,I25*H25*K25,) -> 0 | R25: =IF(J25<>0,J25/1.03-K25,0) -> -0.029126214
A26: =LEN(C26) -> 0 | D26: 01.01.2600 | E26: =VLOOKUP(D26,'03. Insumos'!A:D,2,0) -> Projeto de Instalações | F26: FAT DIRETO | G26: =VLOOKUP(D26,'03. Insumos'!A:F,3,0) -> vb | I26: 1 | J26: =IFERROR(IF(K26<>0,K26*$K$5,0),0) -> 1 | K26: =IF(A26=0,VLOOKUP(D26,'03. Insumos'!A:F,4,0),"") -> 1 | L26: =H26*J26*I26 -> 0 | M26: =L26/$L$7 -> 0 | O26: =IF(I26<>0,I26*H26*K26,) -> 0 | R26: =IF(J26<>0,J26/1.03-K26,0) -> -0.029126214
A27: =LEN(C27) -> 6 | C27: 01.2.3 | D27: Consultorias | K27: =IF(A27=0,VLOOKUP(D27,'03. Insumos'!A:F,4,0),"") | L27: =SUM(L28:L35) -> 182400 | M27: =L27/$L$7 -> 0.011075097 | R27: =IF(J27<>0,J27/1.03-K27,0) -> 0
A28: =LEN(C28) -> 0 | D28: 01.01.2456 | E28: =VLOOKUP(D28,'03. Insumos'!A:D,2,0) -> Consultoria de Fundação | F28: FAT DIRETO | G28: =VLOOKUP(D28,'03. Insumos'!A:F,3,0) -> vb | H28: 8000 | I28: 3 | J28: =IFERROR(IF(K28<>0,K28*$K$5,0),0) -> 1 | K28: =IF(A28=0,VLOOKUP(D28,'03. Insumos'!A:F,4,0),"") -> 1 | L28: =H28*J28*I28 -> 24000 | M28: =L28/$L$7 -> 0.0014572496 | O28: =IF(I28<>0,I28*H28*K28,) -> 24000 | R28: =IF(J28<>0,J28/1.03-K28,0) -> -0.029126214
A29: =LEN(C29) -> 0 | D29: 01.01.2602 | E29: =VLOOKUP(D29,'03. Insumos'!A:D,2,0) -> Consultoria de Estrutura | F29: FAT DIRETO | G29: =VLOOKUP(D29,'03. Insumos'!A:F,3,0) -> vb | H29: 9000 | J29: 1 | K29: =IF(A29=0,VLOOKUP(D29,'03. Insumos'!A:F,4,0),"") -> 1 | L29: =H29*J29*I29 -> 0 | M29: =L29/$L$7 -> 0 | O29: =IF(I29<>0,I29*H29*K29,) -> 0 | R29: =IF(J29<>0,J29/1.03-K29,0) -> -0.029126214
A30: =LEN(C30) -> 0 | D30: 01.01.2603 | E30: =VLOOKUP(D30,'03. Insumos'!A:D,2,0) -> Consultoria de Fachada | F30: FAT DIRETO | G30: =VLOOKUP(D30,'03. Insumos'!A:F,3,0) -> vb | H30: 4000 | J30: =IFERROR(IF(K30<>0,K30*$K$5,0),0) -> 1 | K30: =IF(A30=0,VLOOKUP(D30,'03. Insumos'!A:F,4,0),"") -> 1 | L30: =H30*J30*I30 -> 0 | M30: =L30/$L$7 -> 0 | O30: =IF(I30<>0,I30*H30*K30,) -> 0 | R30: =IF(J30<>0,J30/1.03-K30,0) -> -0.029126214
A31: =LEN(C31) -> 0 | D31: 01.01.2604 | E31: =VLOOKUP(D31,'03. Insumos'!A:D,2,0) -> Consultoria Saúde e Segurança do Trabalho | F31: FAT DIRETO | G31: =VLOOKUP(D31,'03. Insumos'!A:F,3,0) -> vb | H31: 2200 | I31: =L2 -> 36 | J31: =IFERROR(IF(K31<>0,K31*$K$5,0),0) -> 1 | K31: =IF(A31=0,VLOOKUP(D31,'03. Insumos'!A:F,4,0),"") -> 1 | L31: =H31*J31*I31 -> 79200 | M31: =L31/$L$7 -> 0.0048089238 | O31: =IF(I31<>0,I31*H31*K31,) -> 79200 | R31: =IF(J31<>0,J31/1.03-K31,0) -> -0.029126214
A32: =LEN(C32) -> 0 | D32: 01.01.2605 | E32: =VLOOKUP(D32,'03. Insumos'!A:D,2,0) -> Consultoria de Impermeabilização | F32: FAT DIRETO | G32: =VLOOKUP(D32,'03. Insumos'!A:F,3,0) -> vb | H32: 980 | J32: =IFERROR(IF(K32<>0,K32*$K$5,0),0) -> 1 | K32: =IF(A32=0,VLOOKUP(D32,'03. Insumos'!A:F,4,0),"") -> 1 | L32: =H32*J32*I32 -> 0 | M32: =L32/$L$7 -> 0 | O32: =IF(I32<>0,I32*H32*K32,) -> 0 | R32: =IF(J32<>0,J32/1.03-K32,0) -> -0.029126214
A33: =LEN(C33) -> 0 | D33: 01.01.3322 | E33: =VLOOKUP(D33,'03. Insumos'!A:D,2,0) -> Consultoria de Instalações | F33: FAT DIRETO | G33: =VLOOKUP(D33,'03. Insumos'!A:F,3,0) -> vb | H33: 6000 | J33: =IFERROR(IF(K33<>0,K33*$K$5,0),0) -> 1 | K33: =IF(A33=0,VLOOKUP(D33,'03. Insumos'!A:F,4,0),"") -> 1 | L33: =H33*J33*I33 -> 0 | M33: =L33/$L$7 -> 0 | O33: =IF(I33<>0,I33*H33*K33,) -> 0 | R33: =IF(J33<>0,J33/1.03-K33,0) -> -0.029126214
A34: =LEN(C34) -> 0 | D34: 01.01.3207 | E34: =VLOOKUP(D34,'03. Insumos'!A:D,2,0) -> Consultoria Fiscal | F34: FAT DIRETO | G34: =VLOOKUP(D34,'03. Insumos'!A:F,3,0) -> mês | I34: 1 | J34: =IFERROR(IF(K34<>0,K34*$K$5,0),0) -> 3500 | K34: =IF(A34=0,VLOOKUP(D34,'03. Insumos'!A:F,4,0),"") -> 3500 | L34: =H34*J34*I34 -> 0 | M34: =L34/$L$7 -> 0 | O34: =IF(I34<>0,I34*H34*K34,) -> 0 | R34: =IF(J34<>0,J34/1.03-K34,0) -> -101.94175
A35: =LEN(C35) -> 0 | D35: 01.01.3010 | E35: =VLOOKUP(D35,'03. Insumos'!A:D,2,0) -> Consultoria de Planejamento e Orçamento da Obra | F35: FAT DIRETO | G35: =VLOOKUP(D35,'03. Insumos'!A:F,3,0) -> mês | H35: 1 | I35: =L2 -> 36 | J35: =IFERROR(IF(K35<>0,K35*$K$5,0),0) -> 2200 | K35: =IF(A35=0,VLOOKUP(D35,'03. Insumos'!A:F,4,0),"") -> 2200 | L35: =H35*J35*I35 -> 79200 | M35: =L35/$L$7 -> 0.0048089238 | O35: =IF(I35<>0,I35*H35*K35,) -> 79200 | R35: =IF(J35<>0,J35/1.03-K35,0) -> -64.07767
A36: =LEN(C36) -> 6 | C36: 01.2.3 | D36: Consultoria de Planejamento e Orçamento da Obra | K36: =IF(A36=0,VLOOKUP(D36,'03. Insumos'!A:F,4,0),"") | L36: =SUM(L37) -> 0 | M36: =L36/$L$7 -> 0 | R36: =IF(J36<>0,J36/1.03-K36,0) -> 0
A37: =LEN(C37) -> 0 | D37: 01.01.3010 | E37: =VLOOKUP(D37,'03. Insumos'!A:D,2,0) -> Consultoria de Planejamento e Orçamento da Obra | F37: FAT DIRETO | G37: =VLOOKUP(D37,'03. Insumos'!A:F,3,0) -> mês | H37: 1 | J37: 3500 | K37: =IF(A37=0,VLOOKUP(D37,'03. Insumos'!A:F,4,0),"") -> 2200 | L37: =H37*J37*I37 -> 0 | M37: =L37/$L$7 -> 0 | O37: =IF(I37<>0,I37*H37*K37,) -> 0 | R37: =IF(J37<>0,J37/1.03-K37,0) -> 1198.0583
A38: =LEN(C38) -> 6 | C38: 01.2.4 | D38: Sondagem - Custo Incorporação | K38: =IF(A38=0,VLOOKUP(D38,'03. Insumos'!A:F,4,0),"") | L38: =SUM(L39:L39) -> 0 | M38: =L38/$L$7 -> 0 | R38: =IF(J38<>0,J38/1.03-K38,0) -> 0
A39: =LEN(C39) -> 0 | D39: 01.01.2613 | E39: =VLOOKUP(D39,'03. Insumos'!A:D,2,0) -> Execução de Sondagem | F39: FAT DIRETO | G39: =VLOOKUP(D39,'03. Insumos'!A:F,3,0) -> vb | J39: =IFERROR(IF(K39<>0,K39*$K$5,0),0) -> 1 | K39: =IF(A39=0,VLOOKUP(D39,'03. Insumos'!A:F,4,0),"") -> 1 | L39: =H39*J39*I39 -> 0 | M39: =L39/$L$7 -> 0 | O39: =IF(I39<>0,I39*H39*K39,) -> 0 | R39: =IF(J39<>0,J39/1.03-K39,0) -> -0.029126214
A40: =LEN(C40) -> 6 | C40: 01.2.5 | D40: Manual do Proprietário | K40: =IF(A40=0,VLOOKUP(D40,'03. Insumos'!A:F,4,0),"") | L40: =SUM(L41:L41) -> 15000 | M40: =L40/$L$7 -> 0.00091078102 | R40: =IF(J40<>0,J40/1.03-K40,0) -> 0
A41: =LEN(C41) -> 0 | D41: 01.01.3048 | E41: =VLOOKUP(D41,'03. Insumos'!A:D,2,0) -> Manual do Proprietário | F41: FAT DIRETO | G41: =VLOOKUP(D41,'03. Insumos'!A:F,3,0) -> vb | H41: 15000 | I41: 1 | J41: 1 | K41: =IF(A41=0,VLOOKUP(D41,'03. Insumos'!A:F,4,0),"") -> 1 | L41: =H41*J41*I41 -> 15000 | M41: =L41/$L$7 -> 0.00091078102 | O41: =IF(I41<>0,I41*H41*K41,) -> 15000 | R41: =IF(J41<>0,J41/1.03-K41,0) -> -0.029126214
A42: =LEN(C42) -> 6 | C42: 01.2.6 | D42: Laudos | K42: =IF(A42=0,VLOOKUP(D42,'03. Insumos'!A:F,4,0),"") | L42: =SUM(L43:L44) -> 12000 | M42: =L42/$L$7 -> 0.00072862481 | R42: =IF(J42<>0,J42/1.03-K42,0) -> 0
A43: =LEN(C43) -> 0 | D43: 01.01.2617 | E43: =VLOOKUP(D43,'03. Insumos'!A:D,2,0) -> Laudo de Vistoria de Vizinhos | F43: FAT DIRETO | G43: =VLOOKUP(D43,'03. Insumos'!A:F,3,0) -> vb | H43: 12000 | I43: 1 | J43: =IFERROR(IF(K43<>0,K43*$K$5,0),0) -> 1 | K43: =IF(A43=0,VLOOKUP(D43,'03. Insumos'!A:F,4,0),"") -> 1 | L43: =H43*J43*I43 -> 12000 | M43: =L43/$L$7 -> 0.00072862481 | O43: =IF(I43<>0,I43*H43*K43,) -> 12000 | R43: =IF(J43<>0,J43/1.03-K43,0) -> -0.029126214
A44: =LEN(C44) -> 0 | D44: 01.01.2618 | E44: =VLOOKUP(D44,'03. Insumos'!A:D,2,0) -> Laudo de Aterramento | F44: FAT DIRETO | G44: =VLOOKUP(D44,'03. Insumos'!A:F,3,0) -> vb | I44: 1 | J44: =IFERROR(IF(K44<>0,K44*$K$5,0),0) -> 1 | K44: =IF(A44=0,VLOOKUP(D44,'03. Insumos'!A:F,4,0),"") -> 1 | L44: =H44*J44*I44 -> 0 | M44: =L44/$L$7 -> 0 | O44: =IF(I44<>0,I44*H44*K44,) -> 0 | R44: =IF(J44<>0,J44/1.03-K44,0) -> -0.029126214
A45: =LEN(C45) -> 6 | C45: 01.2.7 | D45: Seguro de Obra | K45: =IF(A45=0,VLOOKUP(D45,'03. Insumos'!A:F,4,0),"") | L45: =SUM(L46:L48) -> 17900 | M45: =L45/$L$7 -> 0.0010868653 | R45: =IF(J45<>0,J45/1.03-K45,0) -> 0
A46: =LEN(C46) -> 0 | D46: 01.01.0713 | E46: =VLOOKUP(D46,'03. Insumos'!A:D,2,0) -> Seguro responsabilidade civil e cruzada | F46: SERV. ESP. | G46: =VLOOKUP(D46,'03. Insumos'!A:F,3,0) -> vb | H46: 17900 | I46: 1 | J46: 1 | K46: =IF(A46=0,VLOOKUP(D46,'03. Insumos'!A:F,4,0),"") -> 1 | L46: =H46*J46*I46 -> 17900 | M46: =L46/$L$7 -> 0.0010868653 | O46: =IF(I46<>0,I46*H46*K46,) -> 17900 | R46: =IF(J46<>0,J46/1.03-K46,0) -> -0.029126214
A47: =LEN(C47) -> 0 | D47: 01.01.0714 | E47: =VLOOKUP(D47,'03. Insumos'!A:D,2,0) -> Seguro Performance Bond | G47: =VLOOKUP(D47,'03. Insumos'!A:F,3,0) -> vb | H47: 44000 | J47: =IFERROR(IF(K47<>0,K47*$K$5,0),0) -> 1 | K47: =IF(A47=0,VLOOKUP(D47,'03. Insumos'!A:F,4,0),"") -> 1 | L47: =H47*J47*I47 -> 0 | M47: =L47/$L$7 -> 0
A48: =LEN(C48) -> 0 | D48: 01.01.0773 | E48: =VLOOKUP(D48,'03. Insumos'!A:D,2,0) -> Carta fiança (10% valor) | G48: =VLOOKUP(D48,'03. Insumos'!A:F,3,0) -> vb | J48: =IFERROR(IF(K48<>0,K48*$K$5,0),0) -> 85135.685 | K48: =0.03*2837856.16 -> 85135.685 | L48: =H48*J48*I48 -> 0 | M48: =L48/$L$7 -> 0
A49: =LEN(C49) -> 3 | C49: 02. | D49: INSTALAÇÕES PROVISÓRIAS E CANTEIRO | L49: =SUMIF(A50:A71,4,L50:L71) -> 288861.24 | M49: =L49/$L$7 -> 0.017539289 | O49: =IF(I49<>0,I49*H49*K49,) -> 0 | R49: =IF(J49<>0,J49/1.03-K49,0) -> 0
A50: =LEN(C50) -> 4 | C50: 02.1 | D50: Canteiro de Obras | K50: =IF(A50=0,VLOOKUP(D50,'03. Insumos'!A:F,4,0),"") | L50: =SUMIF(A51:A71,6,L51:L71) -> 288861.24 | M50: =L50/$L$7 -> 0.017539289 | O50: =IF(I50<>0,I50*H50*K50,) -> 0 | R50: =IF(J50<>0,J50/1.03-K50,0) -> 0
A51: =LEN(C51) -> 6 | C51: 02.1.1 | D51: Barracão | K51: =IF(A51=0,VLOOKUP(D51,'03. Insumos'!A:F,4,0),"") | L51: =SUM(L52:L56) -> 180010 | M51: =L51/$L$7 -> 0.010929979 | O51: =IF(I51<>0,I51*H51*K51,) -> 0 | R51: =IF(J51<>0,J51/1.03-K51,0) -> 0
A52: =LEN(C52) -> 0 | D52: 01.01.2619 | E52: =VLOOKUP(D52,'03. Insumos'!A:D,2,0) -> Confecção de Barracão - MAT + MO | F52: FAT DIRETO | G52: =VLOOKUP(D52,'03. Insumos'!A:F,3,0) -> m² | H52: 65 | I52: 1 | J52: 1950 | K52: =IF(A52=0,VLOOKUP(D52,'03. Insumos'!A:F,4,0),"") -> 1950 | L52: =H52*J52*I52 -> 126750 | M52: =L52/$L$7 -> 0.0076960996 | O52: =IF(I52<>0,I52*H52*K52,) -> 126750 | R52: =IF(J52<>0,J52/1.03-K52,0) -> -56.796117
A53: =LEN(C53) -> 0 | D53: 01.01.2620 | E53: =VLOOKUP(D53,'03. Insumos'!A:D,2,0) -> Mobiliário para Áreas de Vivência | F53: RASA | G53: =VLOOKUP(D53,'03. Insumos'!A:F,3,0) -> vb | H53: 29600 | I53: 1 | J53: 1 | K53: =IF(A53=0,VLOOKUP(D53,'03. Insumos'!A:F,4,0),"") -> 1 | L53: =H53*J53*I53 -> 29600 | M53: =L53/$L$7 -> 0.0017972745
A54: =LEN(C54) -> 0 | D54: 01.01.2621 | E54: =VLOOKUP(D54,'03. Insumos'!A:D,2,0) -> Desmobilização Barracão | F54: FAT DIRETO | G54: =VLOOKUP(D54,'03. Insumos'!A:F,3,0) -> vb | H54: 5000 | I54: 1 | J54: 1 | K54: =IF(A54=0,VLOOKUP(D54,'03. Insumos'!A:F,4,0),"") -> 1 | L54: =H54*J54*I54 -> 5000 | M54: =L54/$L$7 -> 0.00030359367
A55: =LEN(C55) -> 0 | D55: 01.01.3050 | E55: =VLOOKUP(D55,'03. Insumos'!A:D,2,0) -> Banheiro Químico | F55: FAT DIRETO | G55: =VLOOKUP(D55,'03. Insumos'!A:F,3,0) -> mês | H55: 2 | I55: 1 | J55: =IFERROR(IF(K55<>0,K55*$K$5,0),0) -> 1050 | K55: =IF(A55=0,VLOOKUP(D55,'03. Insumos'!A:F,4,0),"") -> 1050 | L55: =H55*J55*I55 -> 2100 | M55: =L55/$L$7 -> 0.00012750934
A56: =LEN(C56) -> 0 | D56: 01.01.2677 | E56: =VLOOKUP(D56,'03. Insumos'!A:D,2,0) -> Dedetização, Desintização e Desratização | F56: FAT DIRETO | G56: =VLOOKUP(D56,'03. Insumos'!A:F,3,0) -> mês | H56: 1 | I56: =L2 -> 36 | J56: =IFERROR(IF(K56<>0,K56*$K$5,0),0) -> 460 | K56: =IF(A56=0,VLOOKUP(D56,'03. Insumos'!A:F,4,0),"") -> 460 | L56: =H56*J56*I56 -> 16560 | M56: =L56/$L$7 -> 0.0010055022
A57: =LEN(C57) -> 6 | C57: 02.1.2 | D57: Tapume | G57: m | H57: 29.77 | K57: =IF(A57=0,VLOOKUP(D57,'03. Insumos'!A:F,4,0),"") | L57: =SUM(L58:L58) -> 15778.1 | M57: =L57/$L$7 -> 0.00095802626 | O57: =IF(I57<>0,I57*H57*K57,) -> 0 | R57: =IF(J57<>0,J57/1.03-K57,0) -> 0
A58: =LEN(C58) -> 0 | D58: 01.01.0121 | E58: =VLOOKUP(D58,'03. Insumos'!A:D,2,0) -> Tapume com telha metálica (h=2,20m) - material e mão de obra | F58: FAT DIRETO | G58: =VLOOKUP(D58,'03. Insumos'!A:F,3,0) -> m | H58: 1 | I58: =H57 -> 29.77 | J58: =IFERROR(IF(K58<>0,K58*$K$5,0),0) -> 530 | K58: =IF(A58=0,VLOOKUP(D58,'03. Insumos'!A:F,4,0),"") -> 530 | L58: =H58*J58*I58 -> 15778.1 | M58: =L58/$L$7 -> 0.00095802626
A59: =LEN(C59) -> 6 | C59: 02.1.3 | D59: Gabarito | G59: m | H59: 140.37 | K59: =IF(A59=0,VLOOKUP(D59,'03. Insumos'!A:F,4,0),"") | L59: =SUM(L60:L60) -> 16844.4 | M59: =L59/$L$7 -> 0.0010227706 | O59: =IF(I59<>0,I59*H59*K59,) -> 0 | R59: =IF(J59<>0,J59/1.03-K59,0) -> 0
A60: =LEN(C60) -> 0 | D60: 01.01.0126 | E60: =VLOOKUP(D60,'03. Insumos'!A:D,2,0) -> Gabarito - Material + Mão de Obra | F60: RASA | G60: =VLOOKUP(D60,'03. Insumos'!A:F,3,0) -> m | H60: 1 | I60: =H59 -> 140.37 | J60: =IFERROR(IF(K60<>0,K60*$K$5,0),0) -> 120 | K60: =IF(A60=0,VLOOKUP(D60,'03. Insumos'!A:F,4,0),"") -> 120 | L60: =H60*J60*I60 -> 16844.4 | M60: =L60/$L$7 -> 0.0010227706
A61: =LEN(C61) -> 6 | C61: 02.1.4 | D61: Instalações provisórias | G61: vb | H61: 72200 | K61: =IF(A61=0,VLOOKUP(D61,'03. Insumos'!A:F,4,0),"") | L61: =SUM(L62:L64) -> 72200 | M61: =L61/$L$7 -> 0.0043838926 | O61: =IF(I61<>0,I61*H61*K61,) -> 0 | R61: =IF(J61<>0,J61/1.03-K61,0) -> 0
A62: =LEN(C62) -> 0 | D62: 01.01.2614 | E62: =VLOOKUP(D62,'03. Insumos'!A:D,2,0) -> Instalações Provisórias - MAT + MO | F62: FAT DIRETO | G62: vb | H62: 1 | I62: =H61 -> 72200 | J62: 1 | K62: =IF(A62=0,VLOOKUP(D62,'03. Insumos'!A:F,4,0),"") -> 1 | L62: =H62*J62*I62 -> 72200 | M62: =L62/$L$7 -> 0.0043838926 | O62: =IF(I62<>0,I62*H62*K62,) -> 72200 | R62: =IF(J62<>0,J62/1.03-K62,0) -> -0.029126214
A63: =LEN(C63) -> 0 | D63: 01.01.2615 | E63: =VLOOKUP(D63,'03. Insumos'!A:D,2,0) -> Serviços de ligações provisórias de energia | F63: FAT DIRETO | G63: =VLOOKUP(D63,'03. Insumos'!A:F,3,0) -> vb | I63: 1 | J63: =IFERROR(IF(K63<>0,K63*$K$5,0),0) -> 1 | K63: =IF(A63=0,VLOOKUP(D63,'03. Insumos'!A:F,4,0),"") -> 1 | L63: =H63*J63*I63 -> 0 | M63: =L63/$L$7 -> 0
A64: =LEN(C64) -> 0 | D64: 01.01.2616 | E64: =VLOOKUP(D64,'03. Insumos'!A:D,2,0) -> Instalações - Aprovação de Esgoto Provisório | F64: FAT DIRETO | G64: =VLOOKUP(D64,'03. Insumos'!A:F,3,0) -> vb | I64: 1 | J64: =IFERROR(IF(K64<>0,K64*$K$5,0),0) -> 1 | K64: =IF(A64=0,VLOOKUP(D64,'03. Insumos'!A:F,4,0),"") -> 1 | L64: =H64*J64*I64 -> 0 | M64: =L64/$L$7 -> 0
A65: =LEN(C65) -> 6 | C65: 02.1.5 | D65: Material para instalações provisórias | G65: m | H65: =2.6*3 -> 7.8 | K65: =IF(A65=0,VLOOKUP(D65,'03. Insumos'!A:F,4,0),"") | L65: =SUM(L66:L69) -> 4028.74 | M65: =L65/$L$7 -> 0.00024461999 | O65: =IF(I65<>0,I65*H65*K65,) -> 0 | R65: =IF(J65<>0,J65/1.03-K65,0) -> 0
A66: =LEN(C66) -> 0 | D66: 01.01.2628 | E66: =VLOOKUP(D66,'03. Insumos'!A:D,2,0) -> Tubo Coletor de Entulho Intermediário | F66: FAT DIRETO | G66: =VLOOKUP(D66,'03. Insumos'!A:F,3,0) -> unid | H66: 2 | I66: 3 | J66: =IFERROR(IF(K66<>0,K66*$K$5,0),0) -> 167.85 | K66: =IF(A66=0,VLOOKUP(D66,'03. Insumos'!A:F,4,0),"") -> 167.85 | L66: =H66*J66*I66 -> 1007.1 | M66: =L66/$L$7 -> 6.1149837e-05 | O66: =IF(I66<>0,I66*H66*K66,) -> 1007.1 | R66: =IF(J66<>0,J66/1.03-K66,0) -> -4.888835
A67: =LEN(C67) -> 0 | D67: 01.01.2629 | E67: =VLOOKUP(D67,'03. Insumos'!A:D,2,0) -> Tubo Coletor de Etulho Superior | F67: FAT DIRETO | G67: =VLOOKUP(D67,'03. Insumos'!A:F,3,0) -> unid | H67: 2 | I67: 1 | J67: =IFERROR(IF(K67<>0,K67*$K$5,0),0) -> 215 | K67: =IF(A67=0,VLOOKUP(D67,'03. Insumos'!A:F,4,0),"") -> 215 | L67: =H67*J67*I67 -> 430 | M67: =L67/$L$7 -> 2.6109056e-05
A68: =LEN(C68) -> 0 | D68: 01.01.2630 | E68: =VLOOKUP(D68,'03. Insumos'!A:D,2,0) -> Tubo Coletor de Entulho Reto | F68: FAT DIRETO | G68: =VLOOKUP(D68,'03. Insumos'!A:F,3,0) -> unid | H68: 2 | I68: =I66*2 -> 6 | J68: =IFERROR(IF(K68<>0,K68*$K$5,0),0) -> 153 | K68: =IF(A68=0,VLOOKUP(D68,'03. Insumos'!A:F,4,0),"") -> 153 | L68: =H68*J68*I68 -> 1836 | M68: =L68/$L$7 -> 0.0001114796
A69: =LEN(C69) -> 0 | D69: 01.01.2631 | E69: =VLOOKUP(D69,'03. Insumos'!A:D,2,0) -> Estrutura de Apoio (EA) | F69: FAT DIRETO | G69: =VLOOKUP(D69,'03. Insumos'!A:F,3,0) -> unid | H69: 2 | I69: =ROUNDDOWN(0.3*H65,0) -> 2 | J69: =IFERROR(IF(K69<>0,K69*$K$5,0),0) -> 188.91 | K69: =IF(A69=0,VLOOKUP(D69,'03. Insumos'!A:F,4,0),"") -> 188.91 | L69: =H69*J69*I69 -> 755.64 | M69: =L69/$L$7 -> 4.5881504e-05
A70: =LEN(C70) -> 6 | C70: 02.1.6 | D70: Proteção de Piso | G70: m | K70: =IF(A70=0,VLOOKUP(D70,'03. Insumos'!A:F,4,0),"") | L70: =SUM(L71:L71) -> 0 | M70: =L70/$L$7 -> 0 | O70: =IF(I70<>0,I70*H70*K70,) -> 0 | R70: =IF(J70<>0,J70/1.03-K70,0) -> 0
A71: =LEN(C71) -> 0 | D71: 01.01.2639 | E71: =VLOOKUP(D71,'03. Insumos'!A:D,2,0) -> Proteção de Piso de Poliet. Audo Ades RL625 x 200MM | F71: FAT DIRETO | G71: =VLOOKUP(D71,'03. Insumos'!A:F,3,0) -> m² | H71: 1 | I71: =H70 -> 0 | J71: =IFERROR(IF(K71<>0,K71*$K$5,0),0) -> 5.066076 | K71: =IF(A71=0,VLOOKUP(D71,'03. Insumos'!A:F,4,0),"") -> 5.066076 | L71: =H71*J71*I71 -> 0 | M71: =L71/$L$7 -> 0 | O71: =IF(I71<>0,I71*H71*K71,) -> 0 | R71: =IF(J71<>0,J71/1.03-K71,0) -> -0.14755561
A72: =LEN(C72) -> 3 | C72: 03. | D72: SEGURANÇA DO TRABALHO E PROTEÇÕES | L72: =SUMIF(A73:A123,4,L73:L123) -> 215613.63 | M72: =L72/$L$7 -> 0.013091787 | O72: =IF(I72<>0,I72*H72*K72,) -> 0 | R72: =IF(J72<>0,J72/1.03-K72,0) -> 0
A73: =LEN(C73) -> 4 | C73: 03.1 | D73: Sinalização de segurança e combate à incêndio | K73: =IF(A73=0,VLOOKUP(D73,'03. Insumos'!A:F,4,0),"") | L73: =SUMIF(A74:A77,6,L74:L77) -> 13480 | M73: =L73/$L$7 -> 0.00081848854 | O73: =IF(I73<>0,I73*H73*K73,) -> 0 | R73: =IF(J73<>0,J73/1.03-K73,0) -> 0
A74: =LEN(C74) -> 6 | C74: 03.1.1 | D74: Equipamentos de combate à incêndio | K74: =IF(A74=0,VLOOKUP(D74,'03. Insumos'!A:F,4,0),"") | L74: =SUM(L75:L77) -> 13480 | M74: =L74/$L$7 -> 0.00081848854 | O74: =IF(I74<>0,I74*H74*K74,) -> 0 | R74: =IF(J74<>0,J74/1.03-K74,0) -> 0
A75: =LEN(C75) -> 0 | D75: 01.01.0025 | E75: =VLOOKUP(D75,'03. Insumos'!A:D,2,0) -> Extintor de Pó Químico 4kg | F75: MAT CONSUMO | G75: =VLOOKUP(D75,'03. Insumos'!A:F,3,0) -> uni | H75: 1 | I75: 12 | J75: =IFERROR(IF(K75<>0,K75*$K$5,0),0) -> 540 | K75: =IF(A75=0,VLOOKUP(D75,'03. Insumos'!A:F,4,0),"") -> 540 | L75: =H75*J75*I75 -> 6480 | M75: =L75/$L$7 -> 0.0003934574 | O75: =IF(I75<>0,I75*H75*K75,) -> 6480 | R75: =IF(J75<>0,J75/1.03-K75,0) -> -15.728155
A76: =LEN(C76) -> 0 | D76: 01.01.0026 | E76: =VLOOKUP(D76,'03. Insumos'!A:D,2,0) -> Extintor CO2 4Kg | F76: MAT CONSUMO | G76: =VLOOKUP(D76,'03. Insumos'!A:F,3,0) -> uni | H76: 1 | I76: 10 | J76: =IFERROR(IF(K76<>0,K76*$K$5,0),0) -> 370 | K76: =IF(A76=0,VLOOKUP(D76,'03. Insumos'!A:F,4,0),"") -> 370 | L76: =H76*J76*I76 -> 3700 | M76: =L76/$L$7 -> 0.00022465932 | O76: =IF(I76<>0,I76*H76*K76,) -> 3700 | R76: =IF(J76<>0,J76/1.03-K76,0) -> -10.776699
A77: =LEN(C77) -> 0 | D77: 01.01.3208 | E77: =VLOOKUP(D77,'03. Insumos'!A:D,2,0) -> Recarga de Extintores | F77: MAT CONSUMO | G77: =VLOOKUP(D77,'03. Insumos'!A:F,3,0) -> unid | H77: 1 | I77: =(I75+I76)*2 -> 44 | J77: =IFERROR(IF(K77<>0,K77*$K$5,0),0) -> 75 | K77: =IF(A77=0,VLOOKUP(D77,'03. Insumos'!A:F,4,0),"") -> 75 | L77: =H77*J77*I77 -> 3300 | M77: =L77/$L$7 -> 0.00020037182 | O77: =IF(I77<>0,I77*H77*K77,) -> 3300 | R77: =IF(J77<>0,J77/1.03-K77,0) -> -2.184466
A78: =LEN(C78) -> 4 | C78: 03.2 | D78: Documentação de segurança do trabalho | K78: =IF(A78=0,VLOOKUP(D78,'03. Insumos'!A:F,4,0),"") | L78: =SUMIF(A79:A92,6,L79:L94) -> 8878.1 | M78: =L78/$L$7 -> 0.000539067
A79: =LEN(C79) -> 6 | C79: 03.2.1 | D79: Documentação de segurança do trabalho | K79: =IF(A79=0,VLOOKUP(D79,'03. Insumos'!A:F,4,0),"") | L79: =SUM(L80:L94) -> 8878.1 | M79: =L79/$L$7 -> 0.000539067
A80: =LEN(C80) -> 0 | D80: 01.01.2632 | E80: =VLOOKUP(D80,'03. Insumos'!A:D,2,0) -> Avaliação de Agente Químico (Poeira) | F80: FAT DIRETO | G80: =VLOOKUP(D80,'03. Insumos'!A:F,3,0) -> unid | H80: 1 | I80: 2 | J80: =IFERROR(IF(K80<>0,K80*$K$5,0),0) -> 700 | K80: =IF(A80=0,VLOOKUP(D80,'03. Insumos'!A:F,4,0),"") -> 700 | L80: =H80*J80*I80 -> 1400 | M80: =L80/$L$7 -> 8.5006228e-05
A81: =LEN(C81) -> 0 | D81: 01.01.2633 | E81: =VLOOKUP(D81,'03. Insumos'!A:D,2,0) -> Avaliação de Podeira Respirável | F81: FAT DIRETO | G81: =VLOOKUP(D81,'03. Insumos'!A:F,3,0) -> unid | H81: 1 | I81: 3 | J81: =IFERROR(IF(K81<>0,K81*$K$5,0),0) -> 700 | K81: =IF(A81=0,VLOOKUP(D81,'03. Insumos'!A:F,4,0),"") -> 700 | L81: =H81*J81*I81 -> 2100 | M81: =L81/$L$7 -> 0.00012750934
A82: =LEN(C82) -> 0 | D82: 01.01.2634 | E82: =VLOOKUP(D82,'03. Insumos'!A:D,2,0) -> Avaliação de Calor | F82: FAT DIRETO | G82: =VLOOKUP(D82,'03. Insumos'!A:F,3,0) -> unid | H82: 1 | I82: 3 | J82: =IFERROR(IF(K82<>0,K82*$K$5,0),0) -> 90 | K82: =IF(A82=0,VLOOKUP(D82,'03. Insumos'!A:F,4,0),"") -> 90 | L82: =H82*J82*I82 -> 270 | M82: =L82/$L$7 -> 1.6394058e-05
A83: =LEN(C83) -> 0 | D83: 01.01.2635 | E83: =VLOOKUP(D83,'03. Insumos'!A:D,2,0) -> Avaliação de Vibração | F83: FAT DIRETO | G83: =VLOOKUP(D83,'03. Insumos'!A:F,3,0) -> unid | I83: 5 | J83: =IFERROR(IF(K83<>0,K83*$K$5,0),0) -> 800 | K83: =IF(A83=0,VLOOKUP(D83,'03. Insumos'!A:F,4,0),"") -> 800 | L83: =H83*J83*I83 -> 0 | M83: =L83/$L$7 -> 0
A84: =LEN(C84) -> 0 | D84: 01.01.2636 | E84: =VLOOKUP(D84,'03. Insumos'!A:D,2,0) -> Exame de Dosimetria de Ruído | F84: FAT DIRETO | G84: =VLOOKUP(D84,'03. Insumos'!A:F,3,0) -> unid | H84: 1 | I84: 3 | J84: =IFERROR(IF(K84<>0,K84*$K$5,0),0) -> 233.7 | K84: =IF(A84=0,VLOOKUP(D84,'03. Insumos'!A:F,4,0),"") -> 233.7 | L84: =H84*J84*I84 -> 701.1 | M84: =L84/$L$7 -> 4.2569905e-05
A85: =LEN(C85) -> 0 | D85: 01.01.2637 | E85: =VLOOKUP(D85,'03. Insumos'!A:D,2,0) -> Laudo Egonômico - NR 17 | F85: FAT DIRETO | G85: =VLOOKUP(D85,'03. Insumos'!A:F,3,0) -> unid | I85: 1 | J85: =IFERROR(IF(K85<>0,K85*$K$5,0),0) -> 650 | K85: =IF(A85=0,VLOOKUP(D85,'03. Insumos'!A:F,4,0),"") -> 650 | L85: =H85*J85*I85 -> 0 | M85: =L85/$L$7 -> 0
A86: =LEN(C86) -> 0 | D86: 01.01.2638 | E86: =VLOOKUP(D86,'03. Insumos'!A:D,2,0) -> Elaboração de PPP | F86: FAT DIRETO | G86: =VLOOKUP(D86,'03. Insumos'!A:F,3,0) -> unid | I86: 15 | J86: =IFERROR(IF(K86<>0,K86*$K$5,0),0) -> 45 | K86: =IF(A86=0,VLOOKUP(D86,'03. Insumos'!A:F,4,0),"") -> 45 | L86: =H86*J86*I86 -> 0 | M86: =L86/$L$7 -> 0
A87: =LEN(C87) -> 0 | D87: 01.01.0790 | E87: =VLOOKUP(D87,'03. Insumos'!A:D,2,0) -> Revisão do PCMAT | F87: FAT DIRETO | G87: =VLOOKUP(D87,'03. Insumos'!A:F,3,0) -> unid | J87: =IFERROR(IF(K87<>0,K87*$K$5,0),0) -> 300 | K87: =IF(A87=0,VLOOKUP(D87,'03. Insumos'!A:F,4,0),"") -> 300 | L87: =H87*J87*I87 -> 0 | M87: =L87/$L$7 -> 0
A88: =LEN(C88) -> 0 | D88: 01.01.0791 | E88: =VLOOKUP(D88,'03. Insumos'!A:D,2,0) -> PGR por fase da obra | F88: FAT DIRETO | G88: =VLOOKUP(D88,'03. Insumos'!A:F,3,0) -> unid | H88: 1 | I88: 1 | J88: =IFERROR(IF(K88<>0,K88*$K$5,0),0) -> 1500 | K88: =IF(A88=0,VLOOKUP(D88,'03. Insumos'!A:F,4,0),"") -> 1500 | L88: =H88*J88*I88 -> 1500 | M88: =L88/$L$7 -> 9.1078102e-05
A89: =LEN(C89) -> 0 | D89: 01.01.0792 | E89: =VLOOKUP(D89,'03. Insumos'!A:D,2,0) -> Revisão PGR | F89: FAT DIRETO | G89: =VLOOKUP(D89,'03. Insumos'!A:F,3,0) -> unid | H89: 1 | I89: 3 | J89: =IFERROR(IF(K89<>0,K89*$K$5,0),0) -> 369 | K89: =IF(A89=0,VLOOKUP(D89,'03. Insumos'!A:F,4,0),"") -> 369 | L89: =H89*J89*I89 -> 1107 | M89: =L89/$L$7 -> 6.7215639e-05
A90: =LEN(C90) -> 0 | D90: 01.01.0793 | E90: =VLOOKUP(D90,'03. Insumos'!A:D,2,0) -> Mapa de risco por fase da obra | F90: FAT DIRETO | G90: =VLOOKUP(D90,'03. Insumos'!A:F,3,0) -> unid | J90: =IFERROR(IF(K90<>0,K90*$K$5,0),0) -> 180 | K90: =IF(A90=0,VLOOKUP(D90,'03. Insumos'!A:F,4,0),"") -> 180 | L90: =H90*J90*I90 -> 0 | M90: =L90/$L$7 -> 0
A91: =LEN(C91) -> 0 | D91: 01.01.0794 | E91: =VLOOKUP(D91,'03. Insumos'!A:D,2,0) -> PCMAT por fase da obra | F91: FAT DIRETO | G91: =VLOOKUP(D91,'03. Insumos'!A:F,3,0) -> unid | H91: 1 | I91: 1 | J91: =IFERROR(IF(K91<>0,K91*$K$5,0),0) -> 1800 | K91: =IF(A91=0,VLOOKUP(D91,'03. Insumos'!A:F,4,0),"") -> 1800 | L91: =H91*J91*I91 -> 1800 | M91: =L91/$L$7 -> 0.00010929372
A92: =LEN(C92) -> 0 | D92: 01.01.1323 | E92: =VLOOKUP(D92,'03. Insumos'!A:D,2,0) -> Exame admissional / demissional / períodico | F92: FAT DIRETO | G92: =VLOOKUP(D92,'03. Insumos'!A:F,3,0) -> unid | H92: =SUM(H208:H231) -> 9 | J92: =IFERROR(IF(K92<>0,K92*$K$5,0),0) -> 50 | K92: =IF(A92=0,VLOOKUP(D92,'03. Insumos'!A:F,4,0),"") -> 50 | L92: =H92*J92*I92 -> 0 | M92: =L92/$L$7 -> 0
A93: =LEN(C93) -> 0 | D93: 01.01.0796 | E93: =VLOOKUP(D93,'03. Insumos'!A:D,2,0) -> Implantação e gerenciamento da CIPA | F93: FAT DIRETO | G93: =VLOOKUP(D93,'03. Insumos'!A:F,3,0) -> mês | J93: =IFERROR(IF(K93<>0,K93*$K$5,0),0) -> 300 | K93: =IF(A93=0,VLOOKUP(D93,'03. Insumos'!A:F,4,0),"") -> 300 | L93: =H93*J93*I93 -> 0 | M93: =L93/$L$7 -> 0
A94: =LEN(C94) -> 0 | D94: 01.01.0797 | E94: =VLOOKUP(D94,'03. Insumos'!A:D,2,0) -> Treinamento para CIPA | F94: FAT DIRETO | G94: =VLOOKUP(D94,'03. Insumos'!A:F,3,0) -> unid | J94: =IFERROR(IF(K94<>0,K94*$K$5,0),0) -> 2000 | K94: =IF(A94=0,VLOOKUP(D94,'03. Insumos'!A:F,4,0),"") -> 2000 | L94: =H94*J94*I94 -> 0 | M94: =L94/$L$7 -> 0
A95: =LEN(C95) -> 4 | C95: 03.3 | D95: Proteções Coletivas | K95: =IF(A95=0,VLOOKUP(D95,'03. Insumos'!A:F,4,0),"") | L95: =SUMIF(A96:A106,6,L96:L106) -> 173455.53 | M95: =L95/$L$7 -> 0.010532
A96: =LEN(C96) -> 6 | C96: 03.3.1 | D96: Proteções Gerais | K96: =IF(A96=0,VLOOKUP(D96,'03. Insumos'!A:F,4,0),"") | L96: =SUM(L97:L106) -> 173455.53 | M96: =L96/$L$7 -> 0.010532
A97: =LEN(C97) -> 0 | D97: 01.01.2811 | E97: =VLOOKUP(D97,'03. Insumos'!A:D,2,0) -> Proteções Diveras - Mão de Obra | F97: FAT DIRETO | G97: =VLOOKUP(D97,'03. Insumos'!A:F,3,0) -> vb | I97: 1 | J97: =IFERROR(IF(K97<>0,K97*$K$5,0),0) -> 1 | K97: =IF(A97=0,VLOOKUP(D97,'03. Insumos'!A:F,4,0),"") -> 1 | L97: =H97*J97*I97 -> 0 | M97: =L97/$L$7 -> 0
A98: =LEN(C98) -> 0 | D98: 01.01.2811 | E98: Proteção Coletiva - Linha de Vida | F98: FAT DIRETO | G98: unid | H98: 5 | I98: 1 | J98: 550 | K98: =IF(A98=0,VLOOKUP(D98,'03. Insumos'!A:F,4,0),"") -> 1 | L98: =H98*J98*I98 -> 2750 | M98: =L98/$L$7 -> 0.00016697652
A99: =LEN(C99) -> 0 | D99: 01.01.2811 | E99: Proteção Coletiva - Guarda corpo de Concretagem | F99: FAT DIRETO | G99: m² | H99: =H100*1.1*5 -> 796.18 | I99: 1 | J99: 9 | K99: =IF(A99=0,VLOOKUP(D99,'03. Insumos'!A:F,4,0),"") -> 1 | L99: =H99*J99*I99 -> 7165.62 | M99: =L99/$L$7 -> 0.00043508738
A100: =LEN(C100) -> 0 | D100: 01.01.2811 | E100: Proteção Coletiva - Bandejão Primário | F100: FAT DIRETO | G100: m | H100: 144.76 | I100: 1 | J100: 800 | K100: =IF(A100=0,VLOOKUP(D100,'03. Insumos'!A:F,4,0),"") -> 1 | L100: =H100*J100*I100 -> 115808 | M100: =L100/$L$7 -> 0.0070317152
A101: =LEN(C101) -> 0 | D101: 01.01.2811 | E101: Proteção Coletiva - Tela SLQA | F101: FAT DIRETO | G101: unid | H101: 4 | J101: 10500 | K101: =IF(A101=0,VLOOKUP(D101,'03. Insumos'!A:F,4,0),"") -> 1 | L101: =H101*J101*I101 -> 0 | M101: =L101/$L$7 -> 0
...

Sheet 03. Insumos
A2: TABELA DE INSUMOS
A3: CÓDIGO | B3: DESCRIÇÃO | C3: UNIDADE | D3: PREÇO | E3: OBS | F3: DATA
A4: 01.01.0001 | B4: Placa de Obra | C4: vb | D4: 1 | E4: Valor Estimado | F4: 42878
A5: 01.01.0002 | B5: Ensaio de compressão simples | C5: vb | D5: 2000 | E5: Valor Estimado | F5: 42761 | G5: 1.02
A6: 01.01.0003 | B6: Módulo de deformação | C6: vb | D6: 2000 | E6: Valor Estimado | F6: 42761
A7: 01.01.0004 | B7: Módulo de elasticidade | C7: vb | D7: 2000 | E7: Valor Estimado | F7: 42761
A8: 01.01.0005 | B8: Consultoria Estrutura | C8: mês | D8: 3000 | F8: 43766
A9: 01.01.0006 | B9: Levantamento Topográfico Planialtimétrico | C9: uni | D9: 2600 | E9: Toptec | F9: 42761
A10: 01.01.0007 | B10: Madeiramento em Telhado a ser feito | C10: m | D10: =(((((55.85+8.74+10.21)*1.3)*1.03)/1.03)*1.02)/1.02 -> 97.24 | E10: Sco | F10: 43754
A11: 01.01.0008 | B11: Caibro quadrado 5x5x300cm | C11: uni | D11: 20 | E11: Preço Leroy Merlin | F11: 42760
A12: 01.01.0009 | B12: Caibro 5x2,5cm | C12: uni | D12: 12 | E12: Preço Leroy Merlin | F12: 42760
A13: 01.01.0010 | B13: Madeirite | C13: uni | D13: 62 | E13: Preço Comprado Xian | F13: 42760
A14: 01.01.0011 | B14: Malha de aço 10x10cm 2x3m | C14: uni | D14: 60 | E14: Preço Leroy Merlin | F14: 42760
A15: 01.01.0012 | B15: Projeto, Ampliação em Estrutura Metálica, Reforço de Paredes internas | C15: vb | D15: =((((90600+17000)*1.03)/1.03)*1.02)/1.02 -> 107600 | E15: D & G Serviços de Engenharia / Romana - 17000 correção de valor | F15: 43752
A16: 01.01.0013 | B16: Bombeamento de concreto - até 40m³ | C16: dia | D16: 2400 | E16: Supermix | F16: 45383
A17: 01.01.0014 | B17: Bombeamento de concreto - acima 40m³ | C17: m² | D17: 65 | E17: Supermix | F17: 45383
A18: 01.01.0015 | B18: Mesa de escritório | C18: uni | D18: 150 | E18: Preço Comprado Xian | F18: 42760
A19: 01.01.0016 | B19: Cadeira de escritório simples | C19: uni | D19: 100 | E19: Valor Estimado | F19: 42760
A20: 01.01.0017 | B20: Estante de aço | C20: uni | D20: 400 | E20: Valor Estimado | F20: 42760
A21: 01.01.0018 | B21: Ar condicionado | C21: uni | D21: 1500 | E21: Valor Estimado | F21: 42760
A22: 01.01.0019 | B22: Bebedouro de aço | C22: mês | D22: 400 | E22: Preço Comprado Xian | F22: 42760
A23: 01.01.0020 | B23: Kit Primeiros Socorros | C23: uni | D23: 100 | E23: Valor Estimado | F23: 42760
A24: 01.01.0021 | B24: Cafeteira | C24: uni | D24: 100 | E24: Valor Estimado | F24: 42760
A25: 01.01.0022 | B25: Computador | C25: uni | D25: 1000 | E25: Valor Estimado | F25: 42760
A26: 01.01.0023 | B26: Compra de Impressora A3 | C26: uni | D26: 2500 | E26: Valor Estimado | F26: 42760
A27: 01.01.0024 | B27: Cartuchos de impressora | C27: mês | D27: 300 | E27: Valor Estimado | F27: 42760
A28: 01.01.0025 | B28: Extintor de Pó Químico 4kg | C28: uni | D28: =((((4*135)*1.03)/1.03)*1.02)/1.02 -> 540 | E28: Compra Meet | F28: 44118
A29: 01.01.0026 | B29: Extintor CO2 4Kg | C29: uni | D29: 370 | E29: Compra Meet | F29: 44118
A30: 01.01.0027 | B30: EPI EVENTUAL | C30: mês | D30: 300 | E30: Valor Estimado | F30: 42760
A31: 01.01.0028 | B31: Acompanhamento Mensal Tec. Seg. | C31: mês | D31: 1000 | E31: Brascipa | F31: 43040
A32: 01.01.0029 | B32: Bandeja primária | C32: m | D32: 100 | E32: Preço Material | F32: 42760
A33: 01.01.0030 | B33: Proteção periférica - locação | C33: m | D33: 5.3 | E33: Scora | F33: 42878
A34: 01.01.0031 | B34: Munk Locação | C34: dia | D34: 800 | E34: Local | F34: 42760
A35: 01.01.0032 | B35: Velox Locação | C35: mês | D35: 290 | E35: Valor Estimado | F35: 42760
A36: 01.01.0033 | B36: Frete Velox Ida e Volta | C36: uni | D36: 180 | E36: Valor Estimado | F36: 42760
A37: 01.01.0034 | B37: Escavadeira Locação | C37: mês | D37: =((((115*8*22)*1.03)/1.03)*1.02)/1.02 -> 20240 | E37: Transmater | F37: 42878
A38: 01.01.0035 | B38: Frete Escavadeira Ida e Volta | C38: uni | D38: 1400 | E38: Transmater | F38: 42878
A39: 01.01.0036 | B39: Retroescavadeira Locação | C39: mês | D39: 32000 | E39: Transmater | F39: 42878
A40: 01.01.0037 | B40: Frete Retroescavadeira Ida e Volta | C40: uni | D40: 1400 | E40: Transmater | F40: 42878
A41: 01.01.0038 | B41: Locação de máquinas geral | C41: mês | D41: 850 | E41: Valor Estimado | F41: 42760
A42: 01.01.0039 | B42: Trena padrão | C42: uni | D42: 30 | E42: Valor Estimado | F42: 42760
A43: 01.01.0040 | B43: Régua de alumínio | C43: uni | D43: 50 | E43: Valor Estimado | F43: 42760
A44: 01.01.0041 | B44: Esquadro | C44: uni | D44: 30 | E44: Valor Estimado | F44: 42760
A45: 01.01.0042 | B45: Nível de mão | C45: uni | D45: 40 | E45: Valor Estimado | F45: 42760
A46: 01.01.0043 | B46: Diversos materiais de canteiro | C46: uni | D46: 450 | E46: Valor Estimado | F46: 42760
A47: 01.01.0044 | B47: Andaime Tubular 6m | C47: mês | D47: =((((245.6*1.25)*1.03)/1.03)*1.02)/1.02 -> 307 | E47: Seletto 4,5m + 25% | F47: 42935
A48: 01.01.0045 | B48: Material de escritório | C48: mês | D48: 550 | E48: Anibal | F48: 45448
A49: 01.01.0046 | B49: Material de limpeza e higiene | C49: mês | D49: 600 | E49: Anibal | F49: 45448
A50: 01.01.0047 | B50: Material de higiene | C50: mês | D50: 60 | E50: Valor Estimado | F50: 42760
A51: 01.01.0048 | B51: Motoboy | C51: mês | D51: 100 | E51: Valor Estimado | F51: 42760
A52: 01.01.0049 | B52: Cópias e plotagens | C52: mês | D52: 450 | E52: Rodrigo, planilha | F52: 44584
A53: 01.01.0050 | B53: Telefonia e Internet | C53: mês | D53: 100 | E53: Valor Estimado | F53: 42760
A54: 01.01.0051 | B54: Caçamba para entulho | C54: uni | D54: 400 | F54: 43711
A55: 01.01.0052 | B55: Caçamba Classe D | C55: uni | D55: 700 | E55: Valor Estimado | F55: 42760
A56: 01.01.0053 | B56: Caixinha de Obra | C56: mês | D56: 1000 | E56: Valor Estimado | F56: 42760
A57: 01.01.0054 | B57: Estaca Metálica - Mobilização e Montagem | C57: uni | D57: 6500 | E57: Estimativa | F57: 42760
A58: 01.01.0055 | B58: Estaca Metálica - Cravação | C58: m | D58: 48.5 | E58: Estimativa | F58: 42760
A59: 01.01.0056 | B59: Estaca Metálica - Emendas | C59: uni | D59: 75 | E59: Estimativa | F59: 42760
A60: 01.01.0057 | B60: Arrasamento de estacas | C60: uni | D60: 150 | E60: JFB | F60: 45792
A61: 01.01.0058 | B61: Ampliação em Estr. Metálica + Laje | C61: m² | D61: =(((((500)+(106.86)*1.2)*1.03)/1.03)*1.02)/1.02 -> 628.232 | E61: Acerto de Verba | F61: 43755
A62: 01.01.0059 | B62: Corte e Dobra de Aço - MO | C62: kg | D62: 0.75 | E62: Arcelormittal | F62: 44784
A63: 01.01.0060 | B63: Mobilização e desmobilização de Estaca Raiz | C63: unid | D63: 23000 | E63: Rei das Estacas | F63: 45336
A64: 01.01.0061 | B64: Ensaio PIT | C64: vb | D64: 5000 | E64: Valor Estimado | F64: 42760
A65: 01.01.0062 | B65: Forma Mat | C65: m² | D65: 0 | E65: Valor Estimado | F65: 42760
A66: 01.01.0063 | B66: Brita 0 | C66: m³ | D66: =((((3*70)*1.03)/1.03)*1.02)/1.02 -> 210 | E66: Cruzada | F66: 44188
A67: 01.01.0064 | B67: Estrutura Metálica mais telhas termo acústicas com EPS 30mm. - MO + MAT | C67: vb | D67: 36500 | E67: Mauricio | F67: 44476
A68: 01.01.0065 | B68: Manta Asfáltica MAT+MO Completo | C68: m² | D68: 115 | E68: Aceimper | F68: 44552
A69: 01.01.0066 | B69: Primer 18l | C69: uni | D69: 130 | E69: Valor Estimado | F69: 42760
A70: 01.01.0067 | B70: Proteção Mecânica | C70: m² | D70: 11.8 | E70: Valor Estimado | F70: 42760
A71: 01.01.0068 | B71: Impermeabilização com cimento polimérico MAT+MO | C71: m² | D71: 45 | E71: Bleza | F71: 43045
A72: 01.01.0069 | B72: Argamassa revestimento externo 50kg | C72: sc | D72: 36 | E72: Votorantim | F72: ALVENARIA | G72: 44650
A73: 01.01.0070 | B73: Argamassa multiuso 50kg (pequenas Qtde) | C73: uni | D73: 21.5 | E73: Cruzada | F73: 44476
A74: 01.01.0071 | B74: Tela galvanizada | C74: Cx | D74: 245 | E74: Cruzada | F74: 43754
A75: 01.01.0072 | B75: Argamassa chapisco 20Kg | C75: sc | D75: 17 | E75: Riomix | F75: 42762
A76: 01.01.0073 | B76: Tinta acrílica 18l | C76: uni | D76: 220 | E76: Valor Estimado | F76: 42760
A77: 01.01.0074 | B77: Selador para pintura 18l - Suvinil | C77: uni | D77: 169.99 | E77: Cruzada | F77: 43754
A78: 01.01.0075 | B78: Massa Acrílica | C78: uni | D78: 90 | E78: Valor Estimado | F78: 42760
A79: 01.01.0076 | B79: Lastro de concreto 5cm | C79: m³ | D79: 225 | E79: Supermix | F79: 42760
A80: 01.01.0077 | B80: Piso cerâmico Forma Branco 45x45 Eliane | C80: m² | D80: 26.9 | E80: Valor Estimado | F80: 42760
A81: 01.01.0078 | B81: Argamassa colante 20kg | C81: uni | D81: 21.9 | E81: Amoedo | F81: 43074
A82: 01.01.0079 | B82: Soleira granito cinza andorinha | C82: m | D82: 20 | E82: Valor Estimado | F82: 42760
A83: 01.01.0080 | B83: Cimento branco | C83: kg | D83: 2.5 | E83: Valor Estimado | F83: 42760
A84: 01.01.0081 | B84: Cerâmica ref. 32530 - Incefra 32x56cm | C84: m² | D84: 13.9 | E84: Valor Estimado | F84: 42760
A85: 01.01.0082 | B85: Tinta Esmalte Sintético 3,6l | C85: uni | D85: 59.9 | E85: Valor Estimado | F85: 42760
A86: 01.01.0083 | B86: Forro de gesso drywall - ST MAT+MO | C86: m² | D86: =((((75*1.15)*1.03)/1.03)*1.02)/1.02 -> 86.25 | E86: SW Gesso | F86: 44551
A87: 01.01.0084 | B87: Bacia Sanitária Com Caixa Izy | C87: uni | D87: 299 | E87: Valor Estimado | F87: 42760
A88: 01.01.0085 | B88: Lavatório Aspen/Vogue Plus Branco 44,5x35,5cm | C88: uni | D88: 126.9 | E88: Valor Estimado | F88: 42760
A89: 01.01.0086 | B89: Torneira para lavatório de mesa Zenit Docol Tronic Leed | C89: uni | D89: 0 | E89: Não orçado | F89: 42760
A90: 01.01.0087 | B90: Barra de Apoio Conforto Aço Polido 70cm DECA | C90: uni | D90: 423.9 | E90: CeC | F90: 42936
A91: 01.01.0088 | B91: Barra de apoio lavatório Deca 2390.C.Pol | C91: uni | D91: 0 | E91: Não orçado | F91: 42760
A92: 01.01.0089 | B92: Porta de madeira revestido em fórmica - (0,90 x 2,10)m | C92: uni | D92: 650 | E92: Valor Estimado | F92: 42760
A93: 01.01.0090 | B93: Porta de madeira revestido em fórmica - (3,2 x 2,10)m | C93: uni | D93: =((((D92*2)*1.03)/1.03)*1.02)/1.02 -> 1300 | E93: Valor Estimado | F93: 42760
A94: 01.01.0091 | B94: Colocação de porta de madeira | C94: uni | D94: 100 | E94: Valor Estimado | F94: 42760
A95: 01.01.0092 | B95: PCF - P60 - (1,40 x 2,50)m dupla | C95: uni | D95: 1440 | E95: Valor por m² com base em Xian | F95: 42779
A96: 01.01.0093 | B96: PCF -P60 - (0,90 x 2,50)m - Escadas, S.Tecnica cob | C96: uni | D96: 1100 | E96: Valor por m² com base em Xian | F96: 42779
A97: 01.01.0094 | B97: Rufo em chapa galvanizada - platibandas | C97: m | D97: 60 | E97: Valor Estimado | F97: 42760
A98: 01.01.0095 | B98: Corrimão em ferro tubular Ø 2" | C98: m | D98: 120 | E98: Valor Estimado | F98: 42760
A99: 01.01.0096 | B99: Guarda corpo metálico em aço galvanizado tubular - Cobertura | C99: m | D99: 180 | E99: Valor Estimado | F99: 42760
A100: 01.01.0097 | B100: Parede de Drywall ST MAT+MO | C100: m² | D100: 116 | E100: Com nota | F100: 43760
A101: 01.01.0098 | B101: Vidro simples 3mm | C101: m² | D101: 65 | E101: Valor Estimado | F101: 42760
...

Sheet 04. Histograma MO
B2: HISTOGRAMA DE MÃO DE OBRA | CF2: PRAZO (meses)
CF3: ='02. Orçamento'!L2 -> 36
A6: EQUIPE TÉCNICA E ADMINISTRATIVA DE OBRA
A7: FUNÇÃO | B7: MÊS 1 | D7: MÊS 2 | F7: MÊS 3 | H7: MÊS 4 | J7: MÊS 5 | L7: MÊS 6 | N7: MÊS 7 | P7: MÊS 8 | R7: MÊS 9 | T7: MÊS 10 | V7: MÊS 11 | X7: MÊS 12 | Z7: MÊS 13 | AB7: MÊS 14 | AD7: MÊS 15 | AF7: MÊS 16 | AH7: MÊS 17 | AJ7: MÊS 18 | AL7: MÊS 19 | AN7: MÊS 20 | AP7: MÊS 21 | AR7: MÊS 22 | AT7: MÊS 23 | AV7: MÊS 24 | AX7: MÊS 25 | AZ7: MÊS 26 | BB7: MÊS 27 | BD7: MÊS 28 | BF7: MÊS 29 | BH7: MÊS 30 | BJ7: MÊS 31 | BL7: MÊS 32 | BN7: MÊS 33 | BP7: MÊS 34 | BR7: MÊS 35 | BT7: MÊS 36 | BV7: MÊS 37 | BX7: MÊS 38 | BZ7: MÊS 39 | CB7: MÊS 40 | CD7: Total | CE7: R$ | CF7: R$ Total
B8: Qtd | C8: HE | D8: Qtd | E8: HE | F8: Qtd | G8: HE | H8: Qtd | I8: HE | J8: Qtd | K8: HE | L8: Qtd | M8: HE | N8: Qtd | O8: HE | P8: Qtd | Q8: HE | R8: Qtd | S8: HE | T8: Qtd | U8: HE | V8: Qtd | W8: HE | X8: Qtd | Y8: HE | Z8: Qtd | AA8: HE | AB8: Qtd | AC8: HE | AD8: Qtd | AE8: HE | AF8: Qtd | AG8: HE | AH8: Qtd | AI8: HE | AJ8: Qtd | AK8: HE | AL8: Qtd | AM8: HE | AN8: Qtd | AO8: HE | AP8: Qtd | AQ8: HE | AR8: Qtd | AS8: HE | AT8: Qtd | AU8: HE | AV8: Qtd | AW8: HE | AX8: Qtd | AY8: HE | AZ8: Qtd | BA8: HE | BB8: Qtd | BC8: HE | BD8: Qtd | BE8: HE | BF8: Qtd | BG8: HE | BH8: Qtd | BI8: HE | BJ8: Qtd | BK8: HE | BL8: Qtd | BM8: HE | BN8: Qtd | BO8: HE | BP8: Qtd | BQ8: HE | BR8: Qtd | BS8: HE | BT8: Qtd | BU8: HE | BV8: Qtd | BW8: HE | BX8: Qtd | BY8: HE | BZ8: Qtd | CA8: HE | CB8: Qtd | CC8: HE
A9: REGIME PJ | CF9: =SUM(CF10:CF15) -> 320400
A10: ENGENHEIRO - PART TIME | B10: 0.5 | D10: =B10 -> 0.5 | F10: =D10 -> 0.5 | H10: =F10 -> 0.5 | J10: =H10 -> 0.5 | L10: =J10 -> 0.5 | N10: =L10 -> 0.5 | P10: =N10 -> 0.5 | R10: =P10 -> 0.5 | T10: =R10 -> 0.5 | V10: =T10 -> 0.5 | X10: =V10 -> 0.5 | Z10: =X10 -> 0.5 | AB10: =Z10 -> 0.5 | AD10: =AB10 -> 0.5 | AF10: =AD10 -> 0.5 | AH10: =R10 -> 0.5 | AJ10: =AH10 -> 0.5 | AL10: =AJ10 -> 0.5 | AN10: =AL10 -> 0.5 | AP10: =AN10 -> 0.5 | AR10: =AP10 -> 0.5 | AT10: =AR10 -> 0.5 | AV10: =AT10 -> 0.5 | AX10: =AV10 -> 0.5 | AZ10: =AX10 -> 0.5 | BB10: =AZ10 -> 0.5 | BD10: =BB10 -> 0.5 | BF10: =BD10 -> 0.5 | BH10: =BF10 -> 0.5 | BJ10: =BH10 -> 0.5 | BL10: =BJ10 -> 0.5 | BN10: =BL10 -> 0.5 | BP10: =BN10 -> 0.5 | BR10: =BP10 -> 0.5 | BT10: =BR10 -> 0.5 | BX10: =BV10 -> 0 | BZ10: =BX10 -> 0 | CB10: =BZ10 -> 0 | CD10: =SUMIF($B$8:$CC$8,"QTD",B10:CC10) -> 18 | CE10: 14000 | CF10: =CD10*CE10 -> 252000
A11: ARQUITETA | D11: =B11 -> 0 | F11: =D11 -> 0 | H11: =F11 -> 0 | J11: =H11 -> 0 | L11: =J11 -> 0 | N11: =L11 -> 0 | P11: =N11 -> 0 | R11: =P11 -> 0 | T11: =R11 -> 0 | V11: =T11 -> 0 | X11: =V11 -> 0 | Z11: =X11 -> 0 | AB11: =Z11 -> 0 | AD11: =AB11 -> 0 | AF11: =AD11 -> 0 | AH11: =R11 -> 0 | AJ11: =AH11 -> 0 | AL11: =AJ11 -> 0 | AN11: =AL11 -> 0 | AP11: =AN11 -> 0 | AR11: =AP11 -> 0 | AT11: =AR11 -> 0 | AV11: =AT11 -> 0 | AX11: =AV11 -> 0 | AZ11: =AX11 -> 0 | BB11: =AZ11 -> 0 | BD11: =BB11 -> 0 | BF11: =BD11 -> 0 | BH11: =BF11 -> 0 | BJ11: =BH11 -> 0 | BL11: =BJ11 -> 0 | BN11: =BL11 -> 0 | BP11: =BN11 -> 0 | BR11: =BP11 -> 0 | BT11: =BR11 -> 0 | BX11: =BV11 -> 0 | BZ11: =BX11 -> 0 | CB11: =BZ11 -> 0 | CD11: =SUMIF($B$8:$CC$8,"QTD",B11:CC11) -> 0 | CE11: 4000 | CF11: =CD11*CE11 -> 0
A12: ESTAGIÁRIO | B12: 1 | D12: =B12 -> 1 | F12: =D12 -> 1 | H12: =F12 -> 1 | J12: =H12 -> 1 | L12: =J12 -> 1 | N12: =L12 -> 1 | P12: =N12 -> 1 | R12: =P12 -> 1 | T12: =R12 -> 1 | V12: =T12 -> 1 | X12: =V12 -> 1 | Z12: =X12 -> 1 | AB12: =Z12 -> 1 | AD12: =AB12 -> 1 | AF12: =AD12 -> 1 | AH12: =AF12 -> 1 | AJ12: =AH12 -> 1 | AL12: =AJ12 -> 1 | AN12: =AL12 -> 1 | AP12: =AN12 -> 1 | AR12: =AP12 -> 1 | AT12: =AR12 -> 1 | AV12: =AT12 -> 1 | AX12: =AV12 -> 1 | AZ12: =AX12 -> 1 | BB12: =AZ12 -> 1 | BD12: =BB12 -> 1 | BF12: =BD12 -> 1 | BH12: =BF12 -> 1 | BJ12: =BH12 -> 1 | BL12: =BJ12 -> 1 | BN12: =BL12 -> 1 | BP12: =BN12 -> 1 | BR12: =BP12 -> 1 | BT12: =BR12 -> 1 | BX12: =BV12 -> 0 | BZ12: =BX12 -> 0 | CB12: =BZ12 -> 0 | CD12: =SUMIF($B$8:$CC$8,"QTD",B12:CC12) -> 36 | CE12: 1900 | CF12: =CD12*CE12 -> 68400
A13: TÉCNICO DE EDIFICAÇÕES | D13: =B13 -> 0 | F13: =D13 -> 0 | H13: =F13 -> 0 | J13: =H13 -> 0 | L13: =J13 -> 0 | N13: =L13 -> 0 | P13: =N13 -> 0 | R13: =P13 -> 0 | T13: =R13 -> 0 | V13: =T13 -> 0 | X13: =V13 -> 0 | Z13: =X13 -> 0 | AB13: =Z13 -> 0 | AD13: =AB13 -> 0 | AF13: =AD13 -> 0 | AH13: =R13 -> 0 | AJ13: =AH13 -> 0 | AL13: =AJ13 -> 0 | AN13: =AL13 -> 0 | AP13: =AN13 -> 0 | AR13: =AP13 -> 0 | AT13: =AR13 -> 0 | AV13: =AT13 -> 0 | AX13: =AV13 -> 0 | AZ13: =AX13 -> 0 | BB13: =AZ13 -> 0 | BD13: =BB13 -> 0 | BF13: =BD13 -> 0 | BH13: =BF13 -> 0 | BJ13: =BH13 -> 0 | BL13: =BJ13 -> 0 | BN13: =BL13 -> 0 | BP13: =BN13 -> 0 | BR13: =BP13 -> 0 | BT13: =BR13 -> 0 | BX13: =BV13 -> 0 | BZ13: =BX13 -> 0 | CB13: =BZ13 -> 0 | CD13: =SUMIF($B$8:$CC$8,"QTD",B13:CC13) -> 0 | CE13: 10000 | CF13: =CD13*CE13 -> 0
A14: MESTRE DE OBRA | D14: =B14 -> 0 | F14: =D14 -> 0 | H14: =F14 -> 0 | J14: =H14 -> 0 | L14: =J14 -> 0 | N14: =L14 -> 0 | P14: =N14 -> 0 | R14: =P14 -> 0 | T14: =R14 -> 0 | V14: =T14 -> 0 | X14: =V14 -> 0 | Z14: =X14 -> 0 | AB14: =Z14 -> 0 | AD14: =AB14 -> 0 | AF14: =AD14 -> 0 | AH14: =R14 -> 0 | AJ14: =AH14 -> 0 | AL14: =AJ14 -> 0 | AN14: =AL14 -> 0 | AP14: =AN14 -> 0 | AR14: =AP14 -> 0 | AT14: =AR14 -> 0 | AV14: =AT14 -> 0 | AX14: =AV14 -> 0 | AZ14: =AX14 -> 0 | BB14: =AZ14 -> 0 | BD14: =BB14 -> 0 | BF14: =BD14 -> 0 | BH14: =BF14 -> 0 | BJ14: =BH14 -> 0 | BL14: =BJ14 -> 0 | BN14: =BL14 -> 0 | BP14: =BN14 -> 0 | BR14: =BP14 -> 0 | BT14: =BR14 -> 0 | BX14: =BV14 -> 0 | BZ14: =BX14 -> 0 | CB14: =BZ14 -> 0 | CD14: =SUMIF($B$8:$CC$8,"QTD",B14:CC14) -> 0 | CE14: 16000 | CF14: =CD14*CE14 -> 0
A15: ENC. ADMINISTRATIVO | D15: =B15 -> 0 | F15: =D15 -> 0 | H15: =F15 -> 0 | J15: =H15 -> 0 | L15: =J15 -> 0 | N15: =L15 -> 0 | P15: =N15 -> 0 | R15: =P15 -> 0 | T15: =R15 -> 0 | V15: =T15 -> 0 | X15: =V15 -> 0 | Z15: =X15 -> 0 | AB15: =Z15 -> 0 | AD15: =AB15 -> 0 | AF15: =AD15 -> 0 | AH15: =R15 -> 0 | AJ15: =AH15 -> 0 | AL15: =AJ15 -> 0 | AN15: =AL15 -> 0 | AP15: =AN15 -> 0 | AR15: =AP15 -> 0 | AT15: =AR15 -> 0 | AV15: =AT15 -> 0 | AX15: =AV15 -> 0 | AZ15: =AX15 -> 0 | BB15: =AZ15 -> 0 | BD15: =BB15 -> 0 | BF15: =BD15 -> 0 | BH15: =BF15 -> 0 | BJ15: =BH15 -> 0 | BL15: =BJ15 -> 0 | BN15: =BL15 -> 0 | BP15: =BN15 -> 0 | BR15: =BP15 -> 0 | BT15: =BR15 -> 0 | BX15: =BV15 -> 0 | BZ15: =BX15 -> 0 | CB15: =BZ15 -> 0 | CD15: =SUMIF($B$8:$CC$8,"QTD",B15:CC15) -> 0 | CE15: 6000 | CF15: =CD15*CE15 -> 0
A16: TÉCNICO EM SEGURANÇA DO TRABALHO | D16: =B16 -> 0 | F16: =D16 -> 0 | H16: =F16 -> 0 | J16: =H16 -> 0 | L16: =J16 -> 0 | N16: =L16 -> 0 | P16: =N16 -> 0 | R16: =P16 -> 0 | T16: =R16 -> 0 | V16: =T16 -> 0 | X16: =V16 -> 0 | Z16: =X16 -> 0 | AB16: =Z16 -> 0 | AD16: =AB16 -> 0 | AF16: =AD16 -> 0 | AH16: =R16 -> 0 | AJ16: =AH16 -> 0 | AL16: =AJ16 -> 0 | AN16: =AL16 -> 0 | AP16: =AN16 -> 0 | AR16: =AP16 -> 0 | AT16: =AR16 -> 0 | AV16: =AT16 -> 0 | AX16: =AV16 -> 0 | AZ16: =AX16 -> 0 | BB16: =AZ16 -> 0 | BD16: =BB16 -> 0 | BF16: =BD16 -> 0 | BH16: =BF16 -> 0 | BJ16: =BH16 -> 0 | BL16: =BJ16 -> 0 | BN16: =BL16 -> 0 | BP16: =BN16 -> 0 | BR16: =BP16 -> 0 | BT16: =BR16 -> 0 | BX16: =BV16 -> 0 | BZ16: =BX16 -> 0 | CB16: =BZ16 -> 0 | CD16: =SUMIF($B$8:$CC$8,"QTD",B16:CC16) -> 0 | CE16: 5000 | CF16: =CD16*CE16 -> 0
A17: REGIME CLT | CF17: =SUM(CF18:CF34) -> 1021021.5
A18: ENGENHEIRO | D18: =B18 -> 0 | F18: =D18 -> 0 | H18: =F18 -> 0 | J18: =H18 -> 0 | L18: =J18 -> 0 | N18: =L18 -> 0 | P18: =N18 -> 0 | R18: =P18 -> 0 | T18: =R18 -> 0 | V18: =T18 -> 0 | X18: =V18 -> 0 | Z18: =X18 -> 0 | AB18: =Z18 -> 0 | AD18: =AB18 -> 0 | AF18: =AD18 -> 0 | AH18: =R18 -> 0 | AJ18: =AH18 -> 0 | AL18: =AJ18 -> 0 | AN18: =AL18 -> 0 | AP18: =AN18 -> 0 | AR18: =AP18 -> 0 | AT18: =AR18 -> 0 | AV18: =AT18 -> 0 | AX18: =AV18 -> 0 | AZ18: =AX18 -> 0 | BB18: =AZ18 -> 0 | BD18: =BB18 -> 0 | BF18: =BD18 -> 0 | BH18: =BF18 -> 0 | BJ18: =BH18 -> 0 | BL18: =BJ18 -> 0 | BN18: =BL18 -> 0 | BP18: =BN18 -> 0 | BR18: =BP18 -> 0 | BT18: =BR18 -> 0 | BX18: =BV18 -> 0 | BZ18: =BX18 -> 0 | CB18: =BZ18 -> 0 | CD18: =SUMIF($B$8:$CC$8,"QTD",B18:CC18) -> 0 | CE18: 12900 | CF18: =CD18*CE18 -> 0
A19: ARQUITETA | D19: =B19 -> 0 | F19: =D19 -> 0 | H19: =F19 -> 0 | J19: =H19 -> 0 | L19: =J19 -> 0 | N19: =L19 -> 0 | P19: =N19 -> 0 | R19: =P19 -> 0 | T19: =R19 -> 0 | V19: =T19 -> 0 | X19: =V19 -> 0 | Z19: =X19 -> 0 | AB19: =Z19 -> 0 | AD19: =AB19 -> 0 | AF19: =AD19 -> 0 | AH19: =R19 -> 0 | AJ19: =AH19 -> 0 | AL19: =AJ19 -> 0 | AN19: =AL19 -> 0 | AP19: =AN19 -> 0 | AR19: =AP19 -> 0 | AT19: =AR19 -> 0 | AV19: =AT19 -> 0 | AX19: =AV19 -> 0 | AZ19: =AX19 -> 0 | BB19: =AZ19 -> 0 | BD19: =BB19 -> 0 | BF19: =BD19 -> 0 | BH19: =BF19 -> 0 | BJ19: =BH19 -> 0 | BL19: =BJ19 -> 0 | BN19: =BL19 -> 0 | BP19: =BN19 -> 0 | BR19: =BP19 -> 0 | BT19: =BR19 -> 0 | BX19: =BV19 -> 0 | BZ19: =BX19 -> 0 | CB19: =BZ19 -> 0 | CD19: =SUMIF($B$8:$CC$8,"QTD",B19:CC19) -> 0 | CE19: 9000 | CF19: =CD19*CE19 -> 0
A20: TÉCNICO DE EDIFICAÇÕES | D20: =B20 -> 0 | F20: =D20 -> 0 | H20: =F20 -> 0 | J20: =H20 -> 0 | L20: =J20 -> 0 | N20: =L20 -> 0 | P20: =N20 -> 0 | R20: =P20 -> 0 | T20: =R20 -> 0 | V20: =T20 -> 0 | X20: =V20 -> 0 | Z20: =X20 -> 0 | AB20: =Z20 -> 0 | AD20: =AB20 -> 0 | AF20: =AD20 -> 0 | AH20: =R20 -> 0 | AJ20: =AH20 -> 0 | AL20: =AJ20 -> 0 | AN20: =AL20 -> 0 | AP20: =AN20 -> 0 | AR20: =AP20 -> 0 | AT20: =AR20 -> 0 | AV20: =AT20 -> 0 | AX20: =AV20 -> 0 | AZ20: =AX20 -> 0 | BB20: =AZ20 -> 0 | BD20: =BB20 -> 0 | BF20: =BD20 -> 0 | BH20: =BF20 -> 0 | BJ20: =BH20 -> 0 | BL20: =BJ20 -> 0 | BN20: =BL20 -> 0 | BP20: =BN20 -> 0 | BR20: =BP20 -> 0 | BT20: =BR20 -> 0 | BX20: =BV20 -> 0 | BZ20: =BX20 -> 0 | CB20: =BZ20 -> 0 | CD20: =SUMIF($B$8:$CC$8,"QTD",B20:CC20) -> 0 | CE20: 4000 | CF20: =CD20*CE20 -> 0
A21: MESTRE DE OBRA | B21: 1 | D21: =B21 -> 1 | F21: =D21 -> 1 | H21: =F21 -> 1 | J21: =H21 -> 1 | L21: =J21 -> 1 | N21: =L21 -> 1 | P21: =N21 -> 1 | R21: =P21 -> 1 | T21: =R21 -> 1 | V21: =T21 -> 1 | X21: =V21 -> 1 | Z21: =X21 -> 1 | AB21: =Z21 -> 1 | AD21: =AB21 -> 1 | AF21: =AD21 -> 1 | AH21: =R21 -> 1 | AJ21: =AH21 -> 1 | AL21: =AJ21 -> 1 | AN21: =AL21 -> 1 | AP21: =AN21 -> 1 | AR21: =AP21 -> 1 | AT21: =AR21 -> 1 | AV21: =AT21 -> 1 | AX21: =AV21 -> 1 | AZ21: =AX21 -> 1 | BB21: =AZ21 -> 1 | BD21: =BB21 -> 1 | BF21: =BD21 -> 1 | BH21: =BF21 -> 1 | BJ21: =BH21 -> 1 | BL21: =BJ21 -> 1 | BN21: =BL21 -> 1 | BP21: =BN21 -> 1 | BR21: =BP21 -> 1 | BT21: =BR21 -> 1 | BX21: =BV21 -> 0 | BZ21: =BX21 -> 0 | CB21: =BZ21 -> 0 | CD21: =SUMIF($B$8:$CC$8,"QTD",B21:CC21) -> 36 | CE21: 10000 | CF21: =CD21*CE21 -> 360000
A22: ENC. ADMINISTRATIVO | B22: 1 | D22: =B22 -> 1 | F22: =D22 -> 1 | G22: 0.2 | H22: =F22 -> 1 | I22: 0.2 | J22: =H22 -> 1 | K22: 0.2 | L22: =J22 -> 1 | M22: 0.2 | N22: =L22 -> 1 | O22: 0.2 | P22: =N22 -> 1 | Q22: 0.2 | R22: =P22 -> 1 | S22: 0.2 | T22: =R22 -> 1 | U22: 0.2 | V22: =T22 -> 1 | W22: 0.2 | X22: =V22 -> 1 | Y22: 0.2 | Z22: =X22 -> 1 | AB22: =Z22 -> 1 | AD22: =AB22 -> 1 | AF22: =AD22 -> 1 | AH22: =R22 -> 1 | AJ22: =AH22 -> 1 | AL22: =AJ22 -> 1 | AN22: =AL22 -> 1 | AP22: =AN22 -> 1 | AR22: =AP22 -> 1 | AT22: =AR22 -> 1 | AV22: =AT22 -> 1 | AX22: =AV22 -> 1 | AZ22: =AX22 -> 1 | BB22: =AZ22 -> 1 | BD22: =BB22 -> 1 | BF22: =BD22 -> 1 | BG22: 0.2 | BH22: =BF22 -> 1 | BI22: 0.2 | BJ22: =BH22 -> 1 | BK22: 0.2 | BL22: =BJ22 -> 1 | BM22: 0.2 | BN22: =BL22 -> 1 | BO22: 0.2 | BP22: =BN22 -> 1 | BQ22: 0.2 | BR22: =BP22 -> 1 | BS22: 0.2 | BT22: =BR22 -> 1 | BU22: 0.2 | BX22: =BV22 -> 0 | BZ22: =BX22 -> 0 | CB22: =BZ22 -> 0 | CD22: =SUMIF($B$8:$CC$8,"QTD",B22:CC22) -> 36 | CE22: 4813.952 | CF22: =CD22*CE22 -> 173302.27
A23: TÉCNICO EM SEGURANÇA DO TRABALHO | D23: =B23 -> 0 | F23: =D23 -> 0 | H23: =F23 -> 0 | J23: =H23 -> 0 | L23: =J23 -> 0 | N23: =L23 -> 0 | P23: =N23 -> 0 | R23: =P23 -> 0 | T23: =R23 -> 0 | V23: =T23 -> 0 | X23: =V23 -> 0 | Z23: =X23 -> 0 | AB23: =Z23 -> 0 | AD23: =AB23 -> 0 | AF23: =AD23 -> 0 | AH23: =R23 -> 0 | AJ23: =AH23 -> 0 | AL23: =AJ23 -> 0 | AN23: =AL23 -> 0 | AP23: =AN23 -> 0 | AR23: =AP23 -> 0 | AT23: =AR23 -> 0 | AV23: =AT23 -> 0 | AX23: =AV23 -> 0 | AZ23: =AX23 -> 0 | BB23: =AZ23 -> 0 | BD23: =BB23 -> 0 | BF23: =BD23 -> 0 | BH23: =BF23 -> 0 | BJ23: =BH23 -> 0 | BL23: =BJ23 -> 0 | BN23: =BL23 -> 0 | BP23: =BN23 -> 0 | BR23: =BP23 -> 0 | BT23: =BR23 -> 0 | BX23: =BV23 -> 0 | BZ23: =BX23 -> 0 | CB23: =BZ23 -> 0 | CD23: =SUMIF($B$8:$CC$8,"QTD",B23:CC23) -> 0 | CE23: 3580.72 | CF23: =CD23*CE23 -> 0
A24: ALMOXARIFE | D24: =B24 -> 0 | F24: =D24 -> 0 | H24: =F24 -> 0 | J24: =H24 -> 0 | L24: =J24 -> 0 | N24: =L24 -> 0 | P24: =N24 -> 0 | R24: =P24 -> 0 | T24: =R24 -> 0 | V24: =T24 -> 0 | X24: =V24 -> 0 | Z24: =X24 -> 0 | AB24: =Z24 -> 0 | AD24: =AB24 -> 0 | AF24: =AD24 -> 0 | AH24: =R24 -> 0 | AJ24: =AH24 -> 0 | AL24: =AJ24 -> 0 | AN24: =AL24 -> 0 | AP24: =AN24 -> 0 | AR24: =AP24 -> 0 | AT24: =AR24 -> 0 | AV24: =AT24 -> 0 | AX24: =AV24 -> 0 | AZ24: =AX24 -> 0 | BB24: =AZ24 -> 0 | BD24: =BB24 -> 0 | BF24: =BD24 -> 0 | BH24: =BF24 -> 0 | BJ24: =BH24 -> 0 | BL24: =BJ24 -> 0 | BN24: =BL24 -> 0 | BP24: =BN24 -> 0 | BR24: =BP24 -> 0 | BT24: =BR24 -> 0 | BX24: =BV24 -> 0 | BZ24: =BX24 -> 0 | CB24: =BZ24 -> 0 | CD24: =SUMIF($B$8:$CC$8,"QTD",B24:CC24) -> 0 | CE24: 3422.848 | CF24: =CD24*CE24 -> 0
A25: AUXILIAR ALMOXARIFE | B25: 0 | D25: =B25 -> 0 | F25: =D25 -> 0 | H25: =F25 -> 0 | J25: =H25 -> 0 | L25: =J25 -> 0 | N25: =L25 -> 0 | P25: =N25 -> 0 | R25: =P25 -> 0 | T25: =R25 -> 0 | V25: =T25 -> 0 | X25: =V25 -> 0 | Z25: 1 | AB25: =Z25 -> 1 | AD25: =AB25 -> 1 | AF25: =AD25 -> 1 | AH25: =AF25 -> 1 | AJ25: =AH25 -> 1 | AL25: =AJ25 -> 1 | AN25: =AL25 -> 1 | AP25: =AN25 -> 1 | AR25: =AP25 -> 1 | AT25: =AR25 -> 1 | AV25: =AT25 -> 1 | AX25: =AV25 -> 1 | AZ25: =AX25 -> 1 | BB25: =AZ25 -> 1 | BD25: =BB25 -> 1 | BF25: =BD25 -> 1 | BH25: =BF25 -> 1 | BJ25: =BH25 -> 1 | BL25: =BJ25 -> 1 | BN25: =BL25 -> 1 | BP25: =BN25 -> 1 | BR25: =BP25 -> 1 | BT25: =BR25 -> 1 | BX25: =BV25 -> 0 | BZ25: =BX25 -> 0 | CB25: =BZ25 -> 0 | CD25: =SUMIF($B$8:$CC$8,"QTD",B25:CC25) -> 24 | CE25: 2203.344 | CF25: =CD25*CE25 -> 52880.256
A26: ENCARREGADO DE OBRA | D26: =B26 -> 0 | F26: =D26 -> 0 | H26: =F26 -> 0 | J26: =H26 -> 0 | L26: =J26 -> 0 | N26: =L26 -> 0 | P26: =N26 -> 0 | R26: =P26 -> 0 | T26: =R26 -> 0 | V26: =T26 -> 0 | X26: =V26 -> 0 | Z26: =X26 -> 0 | AB26: =Z26 -> 0 | AD26: =AB26 -> 0 | AF26: =AD26 -> 0 | AH26: =R26 -> 0 | AJ26: =AH26 -> 0 | AL26: =AJ26 -> 0 | AN26: =AL26 -> 0 | AP26: =AN26 -> 0 | AR26: =AP26 -> 0 | AT26: =AR26 -> 0 | AV26: =AT26 -> 0 | AX26: =AV26 -> 0 | AZ26: =AX26 -> 0 | BB26: =AZ26 -> 0 | BD26: =BB26 -> 0 | BF26: =BD26 -> 0 | BH26: =BF26 -> 0 | BJ26: =BH26 -> 0 | BL26: =BJ26 -> 0 | BN26: =BL26 -> 0 | BP26: =BN26 -> 0 | BR26: =BP26 -> 0 | BT26: =BR26 -> 0 | BX26: =BV26 -> 0 | BZ26: =BX26 -> 0 | CB26: =BZ26 -> 0 | CD26: =SUMIF($B$8:$CC$8,"QTD",B26:CC26) -> 0 | CE26: 6240 | CF26: =CD26*CE26 -> 0
A27: OPERADOR DE CREMALHEIRA | D27: =B27 -> 0 | F27: =D27 -> 0 | H27: =F27 -> 0 | J27: =H27 -> 0 | L27: =J27 -> 0 | N27: =L27 -> 0 | P27: =N27 -> 0 | R27: =P27 -> 0 | T27: =R27 -> 0 | V27: =T27 -> 0 | X27: =V27 -> 0 | Z27: =X27 -> 0 | AB27: =Z27 -> 0 | AD27: =AB27 -> 0 | AF27: =AD27 -> 0 | AH27: =R27 -> 0 | AJ27: =AH27 -> 0 | AL27: =AJ27 -> 0 | AN27: =AL27 -> 0 | AP27: =AN27 -> 0 | AR27: =AP27 -> 0 | AT27: =AR27 -> 0 | AV27: =AT27 -> 0 | AX27: =AV27 -> 0 | AZ27: =AX27 -> 0 | BB27: =AZ27 -> 0 | BD27: =BB27 -> 0 | BF27: =BD27 -> 0 | BH27: =BF27 -> 0 | BJ27: =BH27 -> 0 | BL27: =BJ27 -> 0 | BN27: =BL27 -> 0 | BP27: =BN27 -> 0 | BR27: =BP27 -> 0 | BT27: =BR27 -> 0 | BX27: =BV27 -> 0 | BZ27: =BX27 -> 0 | CB27: =BZ27 -> 0 | CD27: =SUMIF($B$8:$CC$8,"QTD",B27:CC27) -> 0 | CE27: 2892.032 | CF27: =CD27*CE27 -> 0
A28: OPERADOR DE GRUA | D28: =B28 -> 0 | F28: =D28 -> 0 | H28: =F28 -> 0 | J28: =H28 -> 0 | L28: =J28 -> 0 | N28: =L28 -> 0 | P28: =N28 -> 0 | R28: =P28 -> 0 | T28: =R28 -> 0 | V28: =T28 -> 0 | X28: =V28 -> 0 | Z28: =X28 -> 0 | AB28: =Z28 -> 0 | AD28: =AB28 -> 0 | AF28: =AD28 -> 0 | AH28: =R28 -> 0 | AJ28: =AH28 -> 0 | AL28: =AJ28 -> 0 | AN28: =AL28 -> 0 | AP28: =AN28 -> 0 | AR28: =AP28 -> 0 | AT28: =AR28 -> 0 | AV28: =AT28 -> 0 | AX28: =AV28 -> 0 | AZ28: =AX28 -> 0 | BB28: =AZ28 -> 0 | BD28: =BB28 -> 0 | BF28: =BD28 -> 0 | BH28: =BF28 -> 0 | BJ28: =BH28 -> 0 | BL28: =BJ28 -> 0 | BN28: =BL28 -> 0 | BP28: =BN28 -> 0 | BR28: =BP28 -> 0 | BT28: =BR28 -> 0 | BX28: =BV28 -> 0 | BZ28: =BX28 -> 0 | CB28: =BZ28 -> 0 | CD28: =SUMIF($B$8:$CC$8,"QTD",B28:CC28) -> 0 | CF28: =CD28*CE28 -> 0
A29: PEDREIRO | D29: =B29 -> 0 | F29: =D29 -> 0 | H29: =F29 -> 0 | J29: =H29 -> 0 | L29: =J29 -> 0 | N29: =L29 -> 0 | P29: =N29 -> 0 | R29: =P29 -> 0 | T29: =R29 -> 0 | V29: =T29 -> 0 | X29: =V29 -> 0 | Z29: 2 | AB29: =Z29 -> 2 | AD29: =AB29 -> 2 | AF29: =AD29 -> 2 | AH29: =AF29 -> 2 | AJ29: =AH29 -> 2 | AL29: =AJ29 -> 2 | AN29: =AL29 -> 2 | AP29: =AN29 -> 2 | AR29: =AP29 -> 2 | AT29: =AR29 -> 2 | AV29: =AT29 -> 2 | AX29: =AV29 -> 2 | AZ29: =AX29 -> 2 | BB29: =AZ29 -> 2 | BD29: =BB29 -> 2 | BF29: =BD29 -> 2 | BH29: =BF29 -> 2 | BI29: 0.2 | BJ29: =BH29 -> 2 | BK29: 0.2 | BL29: =BJ29 -> 2 | BM29: 0.2 | BN29: =BL29 -> 2 | BO29: 0.2 | BP29: =BN29 -> 2 | BQ29: 0.2 | BR29: =BP29 -> 2 | BS29: 0.2 | BT29: =BR29 -> 2 | BU29: 0.2 | BX29: =BV29 -> 0 | BZ29: =BX29 -> 0 | CB29: =BZ29 -> 0 | CD29: =SUMIF($B$8:$CC$8,"QTD",B29:CC29) -> 48 | CE29: 3113.968 | CF29: =CD29*CE29 -> 149470.46
A30: CARPINTEIRO | B30: 1 | D30: =B30 -> 1 | F30: =D30 -> 1 | G30: 0.2 | H30: =F30 -> 1 | I30: 0.2 | J30: =H30 -> 1 | K30: 0.2 | L30: =J30 -> 1 | M30: 0.2 | N30: =L30 -> 1 | O30: 0.2 | P30: =N30 -> 1 | Q30: 0.2 | R30: =P30 -> 1 | S30: 0.2 | T30: =R30 -> 1 | U30: 0.2 | V30: =T30 -> 1 | W30: 0.2 | X30: =V30 -> 1 | Y30: 0.2 | AB30: =Z30 -> 0 | AD30: =AB30 -> 0 | AF30: =AD30 -> 0 | AH30: =AF30 -> 0 | AJ30: =AH30 -> 0 | AL30: =AJ30 -> 0 | AN30: =AL30 -> 0 | AP30: =AN30 -> 0 | AR30: =AP30 -> 0 | AT30: =AR30 -> 0 | AV30: =AT30 -> 0 | AX30: =AV30 -> 0 | AZ30: =AX30 -> 0 | BB30: =AZ30 -> 0 | BD30: =BB30 -> 0 | BF30: =BD30 -> 0 | BH30: =BF30 -> 0 | BJ30: =BH30 -> 0 | BL30: =BJ30 -> 0 | BN30: =BL30 -> 0 | BP30: =BN30 -> 0 | BR30: =BP30 -> 0 | BT30: =BR30 -> 0 | BX30: =BV30 -> 0 | BZ30: =BX30 -> 0 | CB30: =BZ30 -> 0 | CD30: =SUMIF($B$8:$CC$8,"QTD",B30:CC30) -> 12 | CE30: 3113.968 | CF30: =CD30*CE30 -> 37367.616
A31: ELETRICISTA | B31: 1 | D31: =B31 -> 1 | F31: =D31 -> 1 | G31: 0.2 | H31: =F31 -> 1 | I31: 0.2 | J31: =H31 -> 1 | K31: 0.2 | L31: =J31 -> 1 | M31: 0.2 | N31: =L31 -> 1 | O31: 0.2 | P31: =N31 -> 1 | Q31: 0.2 | X31: =V31 -> 0 | Z31: =X31 -> 0 | AB31: =Z31 -> 0 | AD31: =AB31 -> 0 | AF31: =AD31 -> 0 | AH31: =AF31 -> 0 | AJ31: =AH31 -> 0 | AL31: =AJ31 -> 0 | AN31: =AL31 -> 0 | AP31: =AN31 -> 0 | AR31: =AP31 -> 0 | AT31: =AR31 -> 0 | AV31: =AT31 -> 0 | AX31: =AV31 -> 0 | AZ31: =AX31 -> 0 | BB31: =AZ31 -> 0 | BD31: =BB31 -> 0 | BF31: =BD31 -> 0 | BH31: =BF31 -> 0 | BJ31: =BH31 -> 0 | BL31: =BJ31 -> 0 | BN31: =BL31 -> 0 | BP31: =BN31 -> 0 | BR31: =BP31 -> 0 | BT31: =BR31 -> 0 | BX31: =BV31 -> 0 | BZ31: =BX31 -> 0 | CB31: =BZ31 -> 0 | CD31: =SUMIF($B$8:$CC$8,"QTD",B31:CC31) -> 8 | CE31: 2768.48 | CF31: =CD31*CE31 -> 22147.84
A32: BOMBEIRO | D32: =B32 -> 0 | F32: =D32 -> 0 | H32: =F32 -> 0 | J32: =H32 -> 0 | L32: =J32 -> 0 | N32: =L32 -> 0 | P32: =N32 -> 0 | R32: =P32 -> 0 | T32: =R32 -> 0 | V32: =T32 -> 0 | X32: =V32 -> 0 | Z32: =X32 -> 0 | AB32: =Z32 -> 0 | AD32: =AB32 -> 0 | AF32: =AD32 -> 0 | AH32: =R32 -> 0 | AJ32: =AH32 -> 0 | AL32: =AJ32 -> 0 | AN32: =AL32 -> 0 | AP32: =AN32 -> 0 | AR32: =AP32 -> 0 | AT32: =AR32 -> 0 | AV32: =AT32 -> 0 | AX32: =AV32 -> 0 | AZ32: =AX32 -> 0 | BB32: =AZ32 -> 0 | BD32: =BB32 -> 0 | BF32: =BD32 -> 0 | BH32: =BF32 -> 0 | BJ32: =BH32 -> 0 | BL32: =BJ32 -> 0 | BN32: =BL32 -> 0 | BP32: =BN32 -> 0 | BR32: =BP32 -> 0 | BT32: =BR32 -> 0 | BX32: =BV32 -> 0 | BZ32: =BX32 -> 0 | CB32: =BZ32 -> 0 | CD32: =SUMIF($B$8:$CC$8,"QTD",B32:CC32) -> 0 | CE32: 2768.48 | CF32: =CD32*CE32 -> 0
A33: SERVENTE | B33: 3 | D33: 3 | F33: 3 | G33: 0.2 | H33: 3 | I33: 0.2 | J33: 3 | K33: 0.2 | L33: 3 | M33: 0.2 | N33: 3 | O33: 0.2 | P33: 3 | Q33: 0.2 | R33: 3 | S33: 0.2 | T33: 3 | U33: 0.2 | V33: 3 | W33: 0.2 | X33: 3 | Y33: 0.2 | Z33: =SUM(Z29:Z31)+1 -> 3 | AA33: 0.1 | AB33: =SUM(AB29:AB31)+1 -> 3 | AC33: 0.1 | AD33: =SUM(AD29:AD31)+1 -> 3 | AE33: 0.1 | AF33: =SUM(AF29:AF31)+1 -> 3 | AG33: 0.1 | AH33: =SUM(AH29:AH31)+1 -> 3 | AI33: 0.1 | AJ33: =SUM(AJ29:AJ31)+1 -> 3 | AK33: 0.1 | AL33: =SUM(AL29:AL31)+1 -> 3 | AM33: 0.1 | AN33: =SUM(AN29:AN31)+1 -> 3 | AO33: 0.1 | AP33: =SUM(AP29:AP31)+1 -> 3 | AQ33: 0.1 | AR33: =SUM(AR29:AR31)+1 -> 3 | AS33: 0.1 | AT33: =SUM(AT29:AT31)+1 -> 3 | AU33: 0.1 | AV33: =SUM(AV29:AV31)+1 -> 3 | AW33: 0.1 | AX33: =SUM(AX29:AX31)+1 -> 3 | AY33: 0.1 | AZ33: =SUM(AZ29:AZ31)+1 -> 3 | BA33: 0.1 | BB33: =SUM(BB29:BB31)+1 -> 3 | BC33: 0.1 | BD33: =SUM(BD29:BD31)+1 -> 3 | BE33: 0.1 | BF33: =SUM(BF29:BF31)+1 -> 3 | BG33: 0.1 | BH33: =SUM(BH29:BH31)+1 -> 3 | BI33: 0.2 | BJ33: =SUM(BJ29:BJ31)+1 -> 3 | BK33: 0.2 | BL33: =SUM(BL29:BL31)+1 -> 3 | BM33: 0.2 | BN33: =SUM(BN29:BN31)+1 -> 3 | BO33: 0.2 | BP33: =SUM(BP29:BP31)+1 -> 3 | BQ33: 0.2 | BR33: =SUM(BR29:BR31)+1 -> 3 | BS33: 0.2 | BT33: =SUM(BT29:BT31)+1 -> 3 | BU33: 0.2 | CD33: =SUMIF($B$8:$CC$8,"QTD",B33:CC33) -> 108 | CE33: 2091.232 | CF33: =CD33*CE33 -> 225853.06
CD34: =SUMIF($B$8:$CC$8,"QTD",B34:CC34) -> 0 | CF34: =CD34*CE34 -> 0
A35: Nº DE FUNCIONÁRIOS | B35: =SUM(B$10:B$34) -> 8.5 | D35: =SUM(D$10:D$34) -> 8.5 | F35: =SUM(F$10:F$34) -> 8.5 | H35: =SUM(H$10:H$34) -> 8.5 | J35: =SUM(J$10:J$34) -> 8.5 | L35: =SUM(L$10:L$34) -> 8.5 | N35: =SUM(N$10:N$34) -> 8.5 | P35: =SUM(P$10:P$34) -> 8.5 | R35: =SUM(R$10:R$34) -> 7.5 | T35: =SUM(T$10:T$34) -> 7.5 | V35: =SUM(V$10:V$34) -> 7.5 | X35: =SUM(X$10:X$34) -> 7.5 | Z35: =SUM(Z$10:Z$34) -> 9.5 | AB35: =SUM(AB$10:AB$34) -> 9.5 | AD35: =SUM(AD$10:AD$34) -> 9.5 | AF35: =SUM(AF$10:AF$34) -> 9.5 | AH35: =SUM(AH$10:AH$34) -> 9.5 | AJ35: =SUM(AJ$10:AJ$34) -> 9.5 | AL35: =SUM(AL$10:AL$34) -> 9.5 | AN35: =SUM(AN$10:AN$34) -> 9.5 | AP35: =SUM(AP$10:AP$34) -> 9.5 | AR35: =SUM(AR$10:AR$34) -> 9.5 | AT35: =SUM(AT$10:AT$34) -> 9.5 | AV35: =SUM(AV$10:AV$34) -> 9.5 | AX35: =SUM(AX$10:AX$34) -> 9.5 | AZ35: =SUM(AZ$10:AZ$34) -> 9.5 | BB35: =SUM(BB$10:BB$34) -> 9.5 | BD35: =SUM(BD$10:BD$34) -> 9.5 | BF35: =SUM(BF$10:BF$34) -> 9.5 | BH35: =SUM(BH$10:BH$34) -> 9.5 | BJ35: =SUM(BJ$10:BJ$34) -> 9.5 | BL35: =SUM(BL$10:BL$34) -> 9.5 | BN35: =SUM(BN$10:BN$34) -> 9.5 | BP35: =SUM(BP$10:BP$34) -> 9.5 | BR35: =SUM(BR$10:BR$34) -> 9.5 | BT35: =SUM(BT$10:BT$34) -> 9.5 | BV35: =SUM(BV$10:BV$34) -> 0 | BX35: =SUM(BX$10:BX$34) -> 0 | BZ35: =SUM(BZ$10:BZ$34) -> 0 | CB35: =SUM(CB$10:CB$34) -> 0
A36: CUSTO PJ | B36: =SUMPRODUCT(B10:B16,$CE$10:$CE$16) -> 8900 | D36: =SUMPRODUCT(D10:D16,$CE$10:$CE$16) -> 8900 | F36: =SUMPRODUCT(F10:F16,$CE$10:$CE$16) -> 8900 | H36: =SUMPRODUCT(H10:H16,$CE$10:$CE$16) -> 8900 | J36: =SUMPRODUCT(J10:J16,$CE$10:$CE$16) -> 8900 | L36: =SUMPRODUCT(L10:L16,$CE$10:$CE$16) -> 8900 | N36: =SUMPRODUCT(N10:N16,$CE$10:$CE$16) -> 8900 | P36: =SUMPRODUCT(P10:P16,$CE$10:$CE$16) -> 8900 | R36: =SUMPRODUCT(R10:R16,$CE$10:$CE$16) -> 8900 | T36: =SUMPRODUCT(T10:T16,$CE$10:$CE$16) -> 8900 | V36: =SUMPRODUCT(V10:V16,$CE$10:$CE$16) -> 8900 | X36: =SUMPRODUCT(X10:X16,$CE$10:$CE$16) -> 8900 | Z36: =SUMPRODUCT(Z10:Z16,$CE$10:$CE$16) -> 8900 | AB36: =SUMPRODUCT(AB10:AB16,$CE$10:$CE$16) -> 8900 | AD36: =SUMPRODUCT(AD10:AD16,$CE$10:$CE$16) -> 8900 | AF36: =SUMPRODUCT(AF10:AF16,$CE$10:$CE$16) -> 8900 | AH36: =SUMPRODUCT(AH10:AH16,$CE$10:$CE$16) -> 8900 | AJ36: =SUMPRODUCT(AJ10:AJ16,$CE$10:$CE$16) -> 8900 | AL36: =SUMPRODUCT(AL10:AL16,$CE$10:$CE$16) -> 8900 | AN36: =SUMPRODUCT(AN10:AN16,$CE$10:$CE$16) -> 8900 | AP36: =SUMPRODUCT(AP10:AP16,$CE$10:$CE$16) -> 8900 | AR36: =SUMPRODUCT(AR10:AR16,$CE$10:$CE$16) -> 8900 | AT36: =SUMPRODUCT(AT10:AT16,$CE$10:$CE$16) -> 8900 | AV36: =SUMPRODUCT(AV10:AV16,$CE$10:$CE$16) -> 8900 | AX36: =SUMPRODUCT(AX10:AX16,$CE$10:$CE$16) -> 8900 | AZ36: =SUMPRODUCT(AZ10:AZ16,$CE$10:$CE$16) -> 8900 | BB36: =SUMPRODUCT(BB10:BB16,$CE$10:$CE$16) -> 8900 | BD36: =SUMPRODUCT(BD10:BD16,$CE$10:$CE$16) -> 8900 | BF36: =SUMPRODUCT(BF10:BF16,$CE$10:$CE$16) -> 8900 | BH36: =SUMPRODUCT(BH10:BH16,$CE$10:$CE$16) -> 8900 | BJ36: =SUMPRODUCT(BJ10:BJ16,$CE$10:$CE$16) -> 8900 | BL36: =SUMPRODUCT(BL10:BL16,$CE$10:$CE$16) -> 8900 | BN36: =SUMPRODUCT(BN10:BN16,$CE$10:$CE$16) -> 8900 | BP36: =SUMPRODUCT(BP10:BP16,$CE$10:$CE$16) -> 8900 | BR36: =SUMPRODUCT(BR10:BR16,$CE$10:$CE$16) -> 8900 | BT36: =SUMPRODUCT(BT10:BT16,$CE$10:$CE$16) -> 8900 | BV36: =SUMPRODUCT(BV10:BV16,$CE$10:$CE$16) -> 0 | BX36: =SUMPRODUCT(BX10:BX16,$CE$10:$CE$16) -> 0 | BZ36: =SUMPRODUCT(BZ10:BZ16,$CE$10:$CE$16) -> 0 | CB36: =SUMPRODUCT(CB10:CB16,$CE$10:$CE$16) -> 0 | CF36: =SUM(B36:CC36) -> 320400
A37: FOLHA OPERACIONAL | B37: =SUMPRODUCT(B18:B34,$CE$18:$CE$34) -> 26970.096 | D37: =SUMPRODUCT(D18:D34,$CE$18:$CE$34) -> 26970.096 | F37: =SUMPRODUCT(F18:F34,$CE$18:$CE$34) -> 26970.096 | H37: =SUMPRODUCT(H18:H34,$CE$18:$CE$34) -> 26970.096 | J37: =SUMPRODUCT(J18:J34,$CE$18:$CE$34) -> 26970.096 | L37: =SUMPRODUCT(L18:L34,$CE$18:$CE$34) -> 26970.096 | N37: =SUMPRODUCT(N18:N34,$CE$18:$CE$34) -> 26970.096 | P37: =SUMPRODUCT(P18:P34,$CE$18:$CE$34) -> 26970.096 | R37: =SUMPRODUCT(R18:R34,$CE$18:$CE$34) -> 24201.616 | T37: =SUMPRODUCT(T18:T34,$CE$18:$CE$34) -> 24201.616 | V37: =SUMPRODUCT(V18:V34,$CE$18:$CE$34) -> 24201.616 | X37: =SUMPRODUCT(X18:X34,$CE$18:$CE$34) -> 24201.616 | Z37: =SUMPRODUCT(Z18:Z34,$CE$18:$CE$34) -> 29518.928 | AB37: =SUMPRODUCT(AB18:AB34,$CE$18:$CE$34) -> 29518.928 | AD37: =SUMPRODUCT(AD18:AD34,$CE$18:$CE$34) -> 29518.928 | AF37: =SUMPRODUCT(AF18:AF34,$CE$18:$CE$34) -> 29518.928 | AH37: =SUMPRODUCT(AH18:AH34,$CE$18:$CE$34) -> 29518.928 | AJ37: =SUMPRODUCT(AJ18:AJ34,$CE$18:$CE$34) -> 29518.928 | AL37: =SUMPRODUCT(AL18:AL34,$CE$18:$CE$34) -> 29518.928 | AN37: =SUMPRODUCT(AN18:AN34,$CE$18:$CE$34) -> 29518.928 | AP37: =SUMPRODUCT(AP18:AP34,$CE$18:$CE$34) -> 29518.928 | AR37: =SUMPRODUCT(AR18:AR34,$CE$18:$CE$34) -> 29518.928 | AT37: =SUMPRODUCT(AT18:AT34,$CE$18:$CE$34) -> 29518.928 | AV37: =SUMPRODUCT(AV18:AV34,$CE$18:$CE$34) -> 29518.928 | AX37: =SUMPRODUCT(AX18:AX34,$CE$18:$CE$34) -> 29518.928 | AZ37: =SUMPRODUCT(AZ18:AZ34,$CE$18:$CE$34) -> 29518.928 | BB37: =SUMPRODUCT(BB18:BB34,$CE$18:$CE$34) -> 29518.928 | BD37: =SUMPRODUCT(BD18:BD34,$CE$18:$CE$34) -> 29518.928 | BF37: =SUMPRODUCT(BF18:BF34,$CE$18:$CE$34) -> 29518.928 | BH37: =SUMPRODUCT(BH18:BH34,$CE$18:$CE$34) -> 29518.928 | BJ37: =SUMPRODUCT(BJ18:BJ34,$CE$18:$CE$34) -> 29518.928 | BL37: =SUMPRODUCT(BL18:BL34,$CE$18:$CE$34) -> 29518.928 | BN37: =SUMPRODUCT(BN18:BN34,$CE$18:$CE$34) -> 29518.928 | BP37: =SUMPRODUCT(BP18:BP34,$CE$18:$CE$34) -> 29518.928 | BR37: =SUMPRODUCT(BR18:BR34,$CE$18:$CE$34) -> 29518.928 | BT37: =SUMPRODUCT(BT18:BT34,$CE$18:$CE$34) -> 29518.928 | BV37: =SUMPRODUCT(BV18:BV34,$CE$18:$CE$34) -> 0 | BX37: =SUMPRODUCT(BX18:BX34,$CE$18:$CE$34) -> 0 | BZ37: =SUMPRODUCT(BZ18:BZ34,$CE$18:$CE$34) -> 0 | CB37: =SUMPRODUCT(CB18:CB34,$CE$18:$CE$34) -> 0 | CF37: =SUM(B37:CC37) -> 1021021.5
A38: ENCARGOS SOCIAIS | B38: =(SUMPRODUCT(B18:B34,$CE$18:$CE$34)+B39)*$CE$38 -> 23188.889 | D38: =(SUMPRODUCT(D18:D34,$CE$18:$CE$34)+D39)*$CE$38 -> 23188.889 | F38: =(SUMPRODUCT(F18:F34,$CE$18:$CE$34)+F39)*$CE$38 -> 26107.066 | H38: =(SUMPRODUCT(H18:H34,$CE$18:$CE$34)+H39)*$CE$38 -> 26107.066 | J38: =(SUMPRODUCT(J18:J34,$CE$18:$CE$34)+J39)*$CE$38 -> 26107.066 | L38: =(SUMPRODUCT(L18:L34,$CE$18:$CE$34)+L39)*$CE$38 -> 26107.066 | N38: =(SUMPRODUCT(N18:N34,$CE$18:$CE$34)+N39)*$CE$38 -> 26107.066 | P38: =(SUMPRODUCT(P18:P34,$CE$18:$CE$34)+P39)*$CE$38 -> 26107.066 | R38: =(SUMPRODUCT(R18:R34,$CE$18:$CE$34)+R39)*$CE$38 -> 23250.659 | T38: =(SUMPRODUCT(T18:T34,$CE$18:$CE$34)+T39)*$CE$38 -> 23250.659 | V38: =(SUMPRODUCT(V18:V34,$CE$18:$CE$34)+V39)*$CE$38 -> 23250.659 | X38: =(SUMPRODUCT(X18:X34,$CE$18:$CE$34)+X39)*$CE$38 -> 23250.659 | Z38: =(SUMPRODUCT(Z18:Z34,$CE$18:$CE$34)+Z39)*$CE$38 -> 25919.787 | AB38: =(SUMPRODUCT(AB18:AB34,$CE$18:$CE$34)+AB39)*$CE$38 -> 25919.787 | AD38: =(SUMPRODUCT(AD18:AD34,$CE$18:$CE$34)+AD39)*$CE$38 -> 25919.787 | AF38: =(SUMPRODUCT(AF18:AF34,$CE$18:$CE$34)+AF39)*$CE$38 -> 25919.787 | AH38: =(SUMPRODUCT(AH18:AH34,$CE$18:$CE$34)+AH39)*$CE$38 -> 25919.787 | AJ38: =(SUMPRODUCT(AJ18:AJ34,$CE$18:$CE$34)+AJ39)*$CE$38 -> 25919.787 | AL38: =(SUMPRODUCT(AL18:AL34,$CE$18:$CE$34)+AL39)*$CE$38 -> 25919.787 | AN38: =(SUMPRODUCT(AN18:AN34,$CE$18:$CE$34)+AN39)*$CE$38 -> 25919.787 | AP38: =(SUMPRODUCT(AP18:AP34,$CE$18:$CE$34)+AP39)*$CE$38 -> 25919.787 | AR38: =(SUMPRODUCT(AR18:AR34,$CE$18:$CE$34)+AR39)*$CE$38 -> 25919.787 | AT38: =(SUMPRODUCT(AT18:AT34,$CE$18:$CE$34)+AT39)*$CE$38 -> 25919.787 | AV38: =(SUMPRODUCT(AV18:AV34,$CE$18:$CE$34)+AV39)*$CE$38 -> 25919.787 | AX38: =(SUMPRODUCT(AX18:AX34,$CE$18:$CE$34)+AX39)*$CE$38 -> 25919.787 | AZ38: =(SUMPRODUCT(AZ18:AZ34,$CE$18:$CE$34)+AZ39)*$CE$38 -> 25919.787 | BB38: =(SUMPRODUCT(BB18:BB34,$CE$18:$CE$34)+BB39)*$CE$38 -> 25919.787 | BD38: =(SUMPRODUCT(BD18:BD34,$CE$18:$CE$34)+BD39)*$CE$38 -> 25919.787 | BF38: =(SUMPRODUCT(BF18:BF34,$CE$18:$CE$34)+BF39)*$CE$38 -> 26747.594 | BH38: =(SUMPRODUCT(BH18:BH34,$CE$18:$CE$34)+BH39)*$CE$38 -> 28357.962 | BJ38: =(SUMPRODUCT(BJ18:BJ34,$CE$18:$CE$34)+BJ39)*$CE$38 -> 28357.962 | BL38: =(SUMPRODUCT(BL18:BL34,$CE$18:$CE$34)+BL39)*$CE$38 -> 28357.962 | BN38: =(SUMPRODUCT(BN18:BN34,$CE$18:$CE$34)+BN39)*$CE$38 -> 28357.962 | BP38: =(SUMPRODUCT(BP18:BP34,$CE$18:$CE$34)+BP39)*$CE$38 -> 28357.962 | BR38: =(SUMPRODUCT(BR18:BR34,$CE$18:$CE$34)+BR39)*$CE$38 -> 28357.962 | BT38: =(SUMPRODUCT(BT18:BT34,$CE$18:$CE$34)+BT39)*$CE$38 -> 28357.962 | BV38: =(SUMPRODUCT(BV18:BV34,$CE$18:$CE$34)+BV39)*$CE$38 -> 0 | BX38: =(SUMPRODUCT(BX18:BX34,$CE$18:$CE$34)+BX39)*$CE$38 -> 0 | BZ38: =(SUMPRODUCT(BZ18:BZ34,$CE$18:$CE$34)+BZ39)*$CE$38 -> 0 | CB38: =(SUMPRODUCT(CB18:CB34,$CE$18:$CE$34)+CB39)*$CE$38 -> 0 | CE38: 0.8598 | CF38: =SUM(B38:CC38) -> 935992.73
A39: HORAS EXTRAS | B39: =SUMPRODUCT(B18:B34,C18:C34,$CE$18:$CE$34) -> 0 | D39: =SUMPRODUCT(D18:D34,E18:E34,$CE$18:$CE$34) -> 0 | F39: =SUMPRODUCT(F18:F34,G18:G34,$CE$18:$CE$34) -> 3394.0192 | H39: =SUMPRODUCT(H18:H34,I18:I34,$CE$18:$CE$34) -> 3394.0192 | J39: =SUMPRODUCT(J18:J34,K18:K34,$CE$18:$CE$34) -> 3394.0192 | L39: =SUMPRODUCT(L18:L34,M18:M34,$CE$18:$CE$34) -> 3394.0192 | N39: =SUMPRODUCT(N18:N34,O18:O34,$CE$18:$CE$34) -> 3394.0192 | P39: =SUMPRODUCT(P18:P34,Q18:Q34,$CE$18:$CE$34) -> 3394.0192 | R39: =SUMPRODUCT(R18:R34,S18:S34,$CE$18:$CE$34) -> 2840.3232 | T39: =SUMPRODUCT(T18:T34,U18:U34,$CE$18:$CE$34) -> 2840.3232 | V39: =SUMPRODUCT(V18:V34,W18:W34,$CE$18:$CE$34) -> 2840.3232 | X39: =SUMPRODUCT(X18:X34,Y18:Y34,$CE$18:$CE$34) -> 2840.3232 | Z39: =SUMPRODUCT(Z18:Z34,AA18:AA34,$CE$18:$CE$34) -> 627.3696 | AB39: =SUMPRODUCT(AB18:AB34,AC18:AC34,$CE$18:$CE$34) -> 627.3696 | AD39: =SUMPRODUCT(AD18:AD34,AE18:AE34,$CE$18:$CE$34) -> 627.3696 | AF39: =SUMPRODUCT(AF18:AF34,AG18:AG34,$CE$18:$CE$34) -> 627.3696 | AH39: =SUMPRODUCT(AH18:AH34,AI18:AI34,$CE$18:$CE$34) -> 627.3696 | AJ39: =SUMPRODUCT(AJ18:AJ34,AK18:AK34,$CE$18:$CE$34) -> 627.3696 | AL39: =SUMPRODUCT(AL18:AL34,AM18:AM34,$CE$18:$CE$34) -> 627.3696 | AN39: =SUMPRODUCT(AN18:AN34,AO18:AO34,$CE$18:$CE$34) -> 627.3696 | AP39: =SUMPRODUCT(AP18:AP34,AQ18:AQ34,$CE$18:$CE$34) -> 627.3696 | AR39: =SUMPRODUCT(AR18:AR34,AS18:AS34,$CE$18:$CE$34) -> 627.3696 | AT39: =SUMPRODUCT(AT18:AT34,AU18:AU34,$CE$18:$CE$34) -> 627.3696 | AV39: =SUMPRODUCT(AV18:AV34,AW18:AW34,$CE$18:$CE$34) -> 627.3696 | AX39: =SUMPRODUCT(AX18:AX34,AY18:AY34,$CE$18:$CE$34) -> 627.3696 | AZ39: =SUMPRODUCT(AZ18:AZ34,BA18:BA34,$CE$18:$CE$34) -> 627.3696 | BB39: =SUMPRODUCT(BB18:BB34,BC18:BC34,$CE$18:$CE$34) -> 627.3696 | BD39: =SUMPRODUCT(BD18:BD34,BE18:BE34,$CE$18:$CE$34) -> 627.3696 | BF39: =SUMPRODUCT(BF18:BF34,BG18:BG34,$CE$18:$CE$34) -> 1590.16 | BH39: =SUMPRODUCT(BH18:BH34,BI18:BI34,$CE$18:$CE$34) -> 3463.1168 | BJ39: =SUMPRODUCT(BJ18:BJ34,BK18:BK34,$CE$18:$CE$34) -> 3463.1168 | BL39: =SUMPRODUCT(BL18:BL34,BM18:BM34,$CE$18:$CE$34) -> 3463.1168 | BN39: =SUMPRODUCT(BN18:BN34,BO18:BO34,$CE$18:$CE$34) -> 3463.1168 | BP39: =SUMPRODUCT(BP18:BP34,BQ18:BQ34,$CE$18:$CE$34) -> 3463.1168 | BR39: =SUMPRODUCT(BR18:BR34,BS18:BS34,$CE$18:$CE$34) -> 3463.1168 | BT39: =SUMPRODUCT(BT18:BT34,BU18:BU34,$CE$18:$CE$34) -> 3463.1168 | BV39: =SUMPRODUCT(BV18:BV34,BW18:BW34,$CE$18:$CE$34) -> 0 | BX39: =SUMPRODUCT(BX18:BX34,BY18:BY34,$CE$18:$CE$34) -> 0 | BZ39: =SUMPRODUCT(BZ18:BZ34,CA18:CA34,$CE$18:$CE$34) -> 0 | CB39: =SUMPRODUCT(CB18:CB34,CC18:CC34,$CE$18:$CE$34) -> 0 | CF39: =SUM(B39:CC39) -> 67595.299
A40: REFEIÇÃO | B40: =SUM(B$10:B$34)*$CE$40 -> 4675 | D40: =SUM(D$10:D$34)*$CE$40 -> 4675 | F40: =SUM(F$10:F$34)*$CE$40 -> 4675 | H40: =SUM(H$10:H$34)*$CE$40 -> 4675 | J40: =SUM(J$10:J$34)*$CE$40 -> 4675 | L40: =SUM(L$10:L$34)*$CE$40 -> 4675 | N40: =SUM(N$10:N$34)*$CE$40 -> 4675 | P40: =SUM(P$10:P$34)*$CE$40 -> 4675 | R40: =SUM(R$10:R$34)*$CE$40 -> 4125 | T40: =SUM(T$10:T$34)*$CE$40 -> 4125 | V40: =SUM(V$10:V$34)*$CE$40 -> 4125 | X40: =SUM(X$10:X$34)*$CE$40 -> 4125 | Z40: =SUM(Z$10:Z$34)*$CE$40 -> 5225 | AB40: =SUM(AB$10:AB$34)*$CE$40 -> 5225 | AD40: =SUM(AD$10:AD$34)*$CE$40 -> 5225 | AF40: =SUM(AF$10:AF$34)*$CE$40 -> 5225 | AH40: =SUM(AH$10:AH$34)*$CE$40 -> 5225 | AJ40: =SUM(AJ$10:AJ$34)*$CE$40 -> 5225 | AL40: =SUM(AL$10:AL$34)*$CE$40 -> 5225 | AN40: =SUM(AN$10:AN$34)*$CE$40 -> 5225 | AP40: =SUM(AP$10:AP$34)*$CE$40 -> 5225 | AR40: =SUM(AR$10:AR$34)*$CE$40 -> 5225 | AT40: =SUM(AT$10:AT$34)*$CE$40 -> 5225 | AV40: =SUM(AV$10:AV$34)*$CE$40 -> 5225 | AX40: =SUM(AX$10:AX$34)*$CE$40 -> 5225 | AZ40: =SUM(AZ$10:AZ$34)*$CE$40 -> 5225 | BB40: =SUM(BB$10:BB$34)*$CE$40 -> 5225 | BD40: =SUM(BD$10:BD$34)*$CE$40 -> 5225 | BF40: =SUM(BF$10:BF$34)*$CE$40 -> 5225 | BH40: =SUM(BH$10:BH$34)*$CE$40 -> 5225 | BJ40: =SUM(BJ$10:BJ$34)*$CE$40 -> 5225 | BL40: =SUM(BL$10:BL$34)*$CE$40 -> 5225 | BN40: =SUM(BN$10:BN$34)*$CE$40 -> 5225 | BP40: =SUM(BP$10:BP$34)*$CE$40 -> 5225 | BR40: =SUM(BR$10:BR$34)*$CE$40 -> 5225 | BT40: =SUM(BT$10:BT$34)*$CE$40 -> 5225 | BV40: =SUM(BV$10:BV$34)*$CE$40 -> 0 | BX40: =SUM(BX$10:BX$34)*$CE$40 -> 0 | BZ40: =SUM(BZ$10:BZ$34)*$CE$40 -> 0 | CB40: =SUM(CB$10:CB$34)*$CE$40 -> 0 | CE40: =(6.25+18.75)*22 -> 550 | CF40: =SUM(B40:CC40) -> 179300
A41: TRANSPORTE | B41: =SUM(B$18:B$33)*$CE$41 -> 4589.2 | D41: =SUM(D$18:D$33)*$CE$41 -> 4589.2 | F41: =SUM(F$18:F$33)*$CE$41 -> 4589.2 | H41: =SUM(H$18:H$33)*$CE$41 -> 4589.2 | J41: =SUM(J$18:J$33)*$CE$41 -> 4589.2 | L41: =SUM(L$18:L$33)*$CE$41 -> 4589.2 | N41: =SUM(N$18:N$33)*$CE$41 -> 4589.2 | P41: =SUM(P$18:P$33)*$CE$41 -> 4589.2 | R41: =SUM(R$18:R$33)*$CE$41 -> 3933.6 | T41: =SUM(T$18:T$33)*$CE$41 -> 3933.6 | V41: =SUM(V$18:V$33)*$CE$41 -> 3933.6 | X41: =SUM(X$18:X$33)*$CE$41 -> 3933.6 | Z41: =SUM(Z$18:Z$33)*$CE$41 -> 5244.8 | AB41: =SUM(AB$18:AB$33)*$CE$41 -> 5244.8 | AD41: =SUM(AD$18:AD$33)*$CE$41 -> 5244.8 | AF41: =SUM(AF$18:AF$33)*$CE$41 -> 5244.8 | AH41: =SUM(AH$18:AH$33)*$CE$41 -> 5244.8 | AJ41: =SUM(AJ$18:AJ$33)*$CE$41 -> 5244.8 | AL41: =SUM(AL$18:AL$33)*$CE$41 -> 5244.8 | AN41: =SUM(AN$18:AN$33)*$CE$41 -> 5244.8 | AP41: =SUM(AP$18:AP$33)*$CE$41 -> 5244.8 | AR41: =SUM(AR$18:AR$33)*$CE$41 -> 5244.8 | AT41: =SUM(AT$18:AT$33)*$CE$41 -> 5244.8 | AV41: =SUM(AV$18:AV$33)*$CE$41 -> 5244.8 | AX41: =SUM(AX$18:AX$33)*$CE$41 -> 5244.8 | AZ41: =SUM(AZ$18:AZ$33)*$CE$41 -> 5244.8 | BB41: =SUM(BB$18:BB$33)*$CE$41 -> 5244.8 | BD41: =SUM(BD$18:BD$33)*$CE$41 -> 5244.8 | BF41: =SUM(BF$18:BF$33)*$CE$41 -> 5244.8 | BH41: =SUM(BH$18:BH$33)*$CE$41 -> 5244.8 | BJ41: =SUM(BJ$18:BJ$33)*$CE$41 -> 5244.8 | BL41: =SUM(BL$18:BL$33)*$CE$41 -> 5244.8 | BN41: =SUM(BN$18:BN$33)*$CE$41 -> 5244.8 | BP41: =SUM(BP$18:BP$33)*$CE$41 -> 5244.8 | BR41: =SUM(BR$18:BR$33)*$CE$41 -> 5244.8 | BT41: =SUM(BT$18:BT$33)*$CE$41 -> 5244.8 | BV41: =SUM(BV$18:BV$33)*$CE$41 -> 0 | BX41: =SUM(BX$18:BX$33)*$CE$41 -> 0 | BZ41: =SUM(BZ$18:BZ$33)*$CE$41 -> 0 | CB41: =SUM(CB$18:CB$33)*$CE$41 -> 0 | CE41: =(7.4+7.5)*2*22 -> 655.6 | CF41: =SUM(B41:CC41) -> 178323.2
A42: SEGURO DE VIDA | B42: =ROUNDUP(SUM(B$9:B$34),0)*$CE$42 -> 720 | D42: =ROUNDUP(SUM(D$9:D$34),0)*$CE$42 -> 720 | F42: =ROUNDUP(SUM(F$9:F$34),0)*$CE$42 -> 720 | H42: =ROUNDUP(SUM(H$9:H$34),0)*$CE$42 -> 720 | J42: =ROUNDUP(SUM(J$9:J$34),0)*$CE$42 -> 720 | L42: =ROUNDUP(SUM(L$9:L$34),0)*$CE$42 -> 720 | N42: =ROUNDUP(SUM(N$9:N$34),0)*$CE$42 -> 720 | P42: =ROUNDUP(SUM(P$9:P$34),0)*$CE$42 -> 720 | R42: =ROUNDUP(SUM(R$9:R$34),0)*$CE$42 -> 640 | T42: =ROUNDUP(SUM(T$9:T$34),0)*$CE$42 -> 640 | V42: =ROUNDUP(SUM(V$9:V$34),0)*$CE$42 -> 640 | X42: =ROUNDUP(SUM(X$9:X$34),0)*$CE$42 -> 640 | Z42: =ROUNDUP(SUM(Z$9:Z$34),0)*$CE$42 -> 800 | AB42: =ROUNDUP(SUM(AB$9:AB$34),0)*$CE$42 -> 800 | AD42: =ROUNDUP(SUM(AD$9:AD$34),0)*$CE$42 -> 800 | AF42: =ROUNDUP(SUM(AF$9:AF$34),0)*$CE$42 -> 800 | AH42: =ROUNDUP(SUM(AH$9:AH$34),0)*$CE$42 -> 800 | AJ42: =ROUNDUP(SUM(AJ$9:AJ$34),0)*$CE$42 -> 800 | AL42: =ROUNDUP(SUM(AL$9:AL$34),0)*$CE$42 -> 800 | AN42: =ROUNDUP(SUM(AN$9:AN$34),0)*$CE$42 -> 800 | AP42: =ROUNDUP(SUM(AP$9:AP$34),0)*$CE$42 -> 800 | AR42: =ROUNDUP(SUM(AR$9:AR$34),0)*$CE$42 -> 800 | AT42: =ROUNDUP(SUM(AT$9:AT$34),0)*$CE$42 -> 800 | AV42: =ROUNDUP(SUM(AV$9:AV$34),0)*$CE$42 -> 800 | AX42: =ROUNDUP(SUM(AX$9:AX$34),0)*$CE$42 -> 800 | AZ42: =ROUNDUP(SUM(AZ$9:AZ$34),0)*$CE$42 -> 800 | BB42: =ROUNDUP(SUM(BB$9:BB$34),0)*$CE$42 -> 800 | BD42: =ROUNDUP(SUM(BD$9:BD$34),0)*$CE$42 -> 800 | BF42: =ROUNDUP(SUM(BF$9:BF$34),0)*$CE$42 -> 800 | BH42: =ROUNDUP(SUM(BH$9:BH$34),0)*$CE$42 -> 800 | BJ42: =ROUNDUP(SUM(BJ$9:BJ$34),0)*$CE$42 -> 800 | BL42: =ROUNDUP(SUM(BL$9:BL$34),0)*$CE$42 -> 800 | BN42: =ROUNDUP(SUM(BN$9:BN$34),0)*$CE$42 -> 800 | BP42: =ROUNDUP(SUM(BP$9:BP$34),0)*$CE$42 -> 800 | BR42: =ROUNDUP(SUM(BR$9:BR$34),0)*$CE$42 -> 800 | BT42: =ROUNDUP(SUM(BT$9:BT$34),0)*$CE$42 -> 800 | BV42: =ROUNDUP(SUM(BV$9:BV$34),0)*$CE$42 -> 0 | BX42: =ROUNDUP(SUM(BX$9:BX$34),0)*$CE$42 -> 0 | BZ42: =ROUNDUP(SUM(BZ$9:BZ$34),0)*$CE$42 -> 0 | CB42: =ROUNDUP(SUM(CB$9:CB$34),0)*$CE$42 -> 0 | CE42: 80 | CF42: =SUM(B42:CC42) -> 27520
A43: ALIMENTAÇÃO - ASSIDUIDADE | B43: =SUM(B$18:B$34)*$CE$43 -> 1750 | D43: =SUM(D$18:D$34)*$CE$43 -> 1750 | F43: =SUM(F$18:F$34)*$CE$43 -> 1750 | H43: =SUM(H$18:H$34)*$CE$43 -> 1750 | J43: =SUM(J$18:J$34)*$CE$43 -> 1750 | L43: =SUM(L$18:L$34)*$CE$43 -> 1750 | N43: =SUM(N$18:N$34)*$CE$43 -> 1750 | P43: =SUM(P$18:P$34)*$CE$43 -> 1750 | R43: =SUM(R$18:R$34)*$CE$43 -> 1500 | T43: =SUM(T$18:T$34)*$CE$43 -> 1500 | V43: =SUM(V$18:V$34)*$CE$43 -> 1500 | X43: =SUM(X$18:X$34)*$CE$43 -> 1500 | Z43: =SUM(Z$18:Z$34)*$CE$43 -> 2000 | AB43: =SUM(AB$18:AB$34)*$CE$43 -> 2000 | AD43: =SUM(AD$18:AD$34)*$CE$43 -> 2000 | AF43: =SUM(AF$18:AF$34)*$CE$43 -> 2000 | AH43: =SUM(AH$18:AH$34)*$CE$43 -> 2000 | AJ43: =SUM(AJ$18:AJ$34)*$CE$43 -> 2000 | AL43: =SUM(AL$18:AL$34)*$CE$43 -> 2000 | AN43: =SUM(AN$18:AN$34)*$CE$43 -> 2000 | AP43: =SUM(AP$18:AP$34)*$CE$43 -> 2000 | AR43: =SUM(AR$18:AR$34)*$CE$43 -> 2000 | AT43: =SUM(AT$18:AT$34)*$CE$43 -> 2000 | AV43: =SUM(AV$18:AV$34)*$CE$43 -> 2000 | AX43: =SUM(AX$18:AX$34)*$CE$43 -> 2000 | AZ43: =SUM(AZ$18:AZ$34)*$CE$43 -> 2000 | BB43: =SUM(BB$18:BB$34)*$CE$43 -> 2000 | BD43: =SUM(BD$18:BD$34)*$CE$43 -> 2000 | BF43: =SUM(BF$18:BF$34)*$CE$43 -> 2000 | BH43: =SUM(BH$18:BH$34)*$CE$43 -> 2000 | BJ43: =SUM(BJ$18:BJ$34)*$CE$43 -> 2000 | BL43: =SUM(BL$18:BL$34)*$CE$43 -> 2000 | BN43: =SUM(BN$18:BN$34)*$CE$43 -> 2000 | BP43: =SUM(BP$18:BP$34)*$CE$43 -> 2000 | BR43: =SUM(BR$18:BR$34)*$CE$43 -> 2000 | BT43: =SUM(BT$18:BT$34)*$CE$43 -> 2000 | BV43: =SUM(BV$18:BV$34)*$CE$43 -> 0 | BX43: =SUM(BX$18:BX$34)*$CE$43 -> 0 | BZ43: =SUM(BZ$18:BZ$34)*$CE$43 -> 0 | CB43: =SUM(CB$18:CB$34)*$CE$43 -> 0 | CE43: 250 | CF43: =SUM(B43:CC43) -> 68000
A44: EXAMES ADMISSIONAIS/PERIÓDICOS | B44: =ROUNDUP(SUM(B$9:B$34),0)*$CE$44 -> 630 | D44: =ROUNDUP(SUM(D$9:D$34),0)*$CE$44 -> 630 | F44: =ROUNDUP(SUM(F$9:F$34),0)*$CE$44 -> 630 | H44: =ROUNDUP(SUM(H$9:H$34),0)*$CE$44 -> 630 | J44: =ROUNDUP(SUM(J$9:J$34),0)*$CE$44 -> 630 | L44: =ROUNDUP(SUM(L$9:L$34),0)*$CE$44 -> 630 | N44: =ROUNDUP(SUM(N$9:N$34),0)*$CE$44 -> 630 | P44: =ROUNDUP(SUM(P$9:P$34),0)*$CE$44 -> 630 | R44: =ROUNDUP(SUM(R$9:R$34),0)*$CE$44 -> 560 | T44: =ROUNDUP(SUM(T$9:T$34),0)*$CE$44 -> 560 | V44: =ROUNDUP(SUM(V$9:V$34),0)*$CE$44 -> 560 | X44: =ROUNDUP(SUM(X$9:X$34),0)*$CE$44 -> 560 | Z44: =ROUNDUP(SUM(Z$9:Z$34),0)*$CE$44 -> 700 | AB44: =ROUNDUP(SUM(AB$9:AB$34),0)*$CE$44 -> 700 | AD44: =ROUNDUP(SUM(AD$9:AD$34),0)*$CE$44 -> 700 | AF44: =ROUNDUP(SUM(AF$9:AF$34),0)*$CE$44 -> 700 | AH44: =ROUNDUP(SUM(AH$9:AH$34),0)*$CE$44 -> 700 | AJ44: =ROUNDUP(SUM(AJ$9:AJ$34),0)*$CE$44 -> 700 | AL44: =ROUNDUP(SUM(AL$9:AL$34),0)*$CE$44 -> 700 | AN44: =ROUNDUP(SUM(AN$9:AN$34),0)*$CE$44 -> 700 | AP44: =ROUNDUP(SUM(AP$9:AP$34),0)*$CE$44 -> 700 | AR44: =ROUNDUP(SUM(AR$9:AR$34),0)*$CE$44 -> 700 | AT44: =ROUNDUP(SUM(AT$9:AT$34),0)*$CE$44 -> 700 | AV44: =ROUNDUP(SUM(AV$9:AV$34),0)*$CE$44 -> 700 | AX44: =ROUNDUP(SUM(AX$9:AX$34),0)*$CE$44 -> 700 | AZ44: =ROUNDUP(SUM(AZ$9:AZ$34),0)*$CE$44 -> 700 | BB44: =ROUNDUP(SUM(BB$9:BB$34),0)*$CE$44 -> 700 | BD44: =ROUNDUP(SUM(BD$9:BD$34),0)*$CE$44 -> 700 | BF44: =ROUNDUP(SUM(BF$9:BF$34),0)*$CE$44 -> 700 | BH44: =ROUNDUP(SUM(BH$9:BH$34),0)*$CE$44 -> 700 | BJ44: =ROUNDUP(SUM(BJ$9:BJ$34),0)*$CE$44 -> 700 | BL44: =ROUNDUP(SUM(BL$9:BL$34),0)*$CE$44 -> 700 | BN44: =ROUNDUP(SUM(BN$9:BN$34),0)*$CE$44 -> 700 | BP44: =ROUNDUP(SUM(BP$9:BP$34),0)*$CE$44 -> 700 | BR44: =ROUNDUP(SUM(BR$9:BR$34),0)*$CE$44 -> 700 | BT44: =ROUNDUP(SUM(BT$9:BT$34),0)*$CE$44 -> 700 | BV44: =ROUNDUP(SUM(BV$9:BV$34),0)*$CE$44 -> 0 | BX44: =ROUNDUP(SUM(BX$9:BX$34),0)*$CE$44 -> 0 | BZ44: =ROUNDUP(SUM(BZ$9:BZ$34),0)*$CE$44 -> 0 | CB44: =ROUNDUP(SUM(CB$9:CB$34),0)*$CE$44 -> 0 | CE44: 70 | CF44: =SUM(B44:CC44) -> 24080
A45: IMPOSTO NF DE M.O. (19,76%) | B45: =IF($CE$45=0,0,(SUM(B37,B38,B39)/(1-$CE$45))-SUM(B37,B38,B39)) -> 0 | D45: =IF($CE$45=0,0,(SUM(D37,D38,D39)/(1-$CE$45))-SUM(D37,D38,D39)) -> 0 | F45: =IF($CE$45=0,0,(SUM(F37,F38,F39)/(1-$CE$45))-SUM(F37,F38,F39)) -> 0 | H45: =IF($CE$45=0,0,(SUM(H37,H38,H39)/(1-$CE$45))-SUM(H37,H38,H39)) -> 0 | J45: =IF($CE$45=0,0,(SUM(J37,J38,J39)/(1-$CE$45))-SUM(J37,J38,J39)) -> 0 | L45: =IF($CE$45=0,0,(SUM(L37,L38,L39)/(1-$CE$45))-SUM(L37,L38,L39)) -> 0 | N45: =IF($CE$45=0,0,(SUM(N37,N38,N39)/(1-$CE$45))-SUM(N37,N38,N39)) -> 0 | P45: =IF($CE$45=0,0,(SUM(P37,P38,P39)/(1-$CE$45))-SUM(P37,P38,P39)) -> 0 | R45: =IF($CE$45=0,0,(SUM(R37,R38,R39)/(1-$CE$45))-SUM(R37,R38,R39)) -> 0 | T45: =IF($CE$45=0,0,(SUM(T37,T38,T39)/(1-$CE$45))-SUM(T37,T38,T39)) -> 0 | V45: =IF($CE$45=0,0,(SUM(V37,V38,V39)/(1-$CE$45))-SUM(V37,V38,V39)) -> 0 | X45: =IF($CE$45=0,0,(SUM(X37,X38,X39)/(1-$CE$45))-SUM(X37,X38,X39)) -> 0 | Z45: =IF($CE$45=0,0,(SUM(Z37,Z38,Z39)/(1-$CE$45))-SUM(Z37,Z38,Z39)) -> 0 | AB45: =IF($CE$45=0,0,(SUM(AB37,AB38,AB39)/(1-$CE$45))-SUM(AB37,AB38,AB39)) -> 0 | AD45: =IF($CE$45=0,0,(SUM(AD37,AD38,AD39)/(1-$CE$45))-SUM(AD37,AD38,AD39)) -> 0 | AF45: =IF($CE$45=0,0,(SUM(AF37,AF38,AF39)/(1-$CE$45))-SUM(AF37,AF38,AF39)) -> 0 | AH45: =IF($CE$45=0,0,(SUM(AH37,AH38,AH39)/(1-$CE$45))-SUM(AH37,AH38,AH39)) -> 0 | AJ45: =IF($CE$45=0,0,(SUM(AJ37,AJ38,AJ39)/(1-$CE$45))-SUM(AJ37,AJ38,AJ39)) -> 0 | AL45: =IF($CE$45=0,0,(SUM(AL37,AL38,AL39)/(1-$CE$45))-SUM(AL37,AL38,AL39)) -> 0 | AN45: =IF($CE$45=0,0,(SUM(AN37,AN38,AN39)/(1-$CE$45))-SUM(AN37,AN38,AN39)) -> 0 | AP45: =IF($CE$45=0,0,(SUM(AP37,AP38,AP39)/(1-$CE$45))-SUM(AP37,AP38,AP39)) -> 0 | AR45: =IF($CE$45=0,0,(SUM(AR37,AR38,AR39)/(1-$CE$45))-SUM(AR37,AR38,AR39)) -> 0 | AT45: =IF($CE$45=0,0,(SUM(AT37,AT38,AT39)/(1-$CE$45))-SUM(AT37,AT38,AT39)) -> 0 | AV45: =IF($CE$45=0,0,(SUM(AV37,AV38,AV39)/(1-$CE$45))-SUM(AV37,AV38,AV39)) -> 0 | AX45: =IF($CE$45=0,0,(SUM(AX37,AX38,AX39)/(1-$CE$45))-SUM(AX37,AX38,AX39)) -> 0 | AZ45: =IF($CE$45=0,0,(SUM(AZ37,AZ38,AZ39)/(1-$CE$45))-SUM(AZ37,AZ38,AZ39)) -> 0 | BB45: =IF($CE$45=0,0,(SUM(BB37,BB38,BB39)/(1-$CE$45))-SUM(BB37,BB38,BB39)) -> 0 | BD45: =IF($CE$45=0,0,(SUM(BD37,BD38,BD39)/(1-$CE$45))-SUM(BD37,BD38,BD39)) -> 0 | BF45: =IF($CE$45=0,0,(SUM(BF37,BF38,BF39)/(1-$CE$45))-SUM(BF37,BF38,BF39)) -> 0 | BH45: =IF($CE$45=0,0,(SUM(BH37,BH38,BH39)/(1-$CE$45))-SUM(BH37,BH38,BH39)) -> 0 | BJ45: =IF($CE$45=0,0,(SUM(BJ37,BJ38,BJ39)/(1-$CE$45))-SUM(BJ37,BJ38,BJ39)) -> 0 | BL45: =IF($CE$45=0,0,(SUM(BL37,BL38,BL39)/(1-$CE$45))-SUM(BL37,BL38,BL39)) -> 0 | BN45: =IF($CE$45=0,0,(SUM(BN37,BN38,BN39)/(1-$CE$45))-SUM(BN37,BN38,BN39)) -> 0 | BP45: =IF($CE$45=0,0,(SUM(BP37,BP38,BP39)/(1-$CE$45))-SUM(BP37,BP38,BP39)) -> 0 | BR45: =IF($CE$45=0,0,(SUM(BR37,BR38,BR39)/(1-$CE$45))-SUM(BR37,BR38,BR39)) -> 0 | BT45: =IF($CE$45=0,0,(SUM(BT37,BT38,BT39)/(1-$CE$45))-SUM(BT37,BT38,BT39)) -> 0 | BV45: =IF($CE$45=0,0,(SUM(BV37,BV38,BV39)/(1-$CE$45))-SUM(BV37,BV38,BV39)) -> 0 | BX45: =IF($CE$45=0,0,(SUM(BX37,BX38,BX39)/(1-$CE$45))-SUM(BX37,BX38,BX39)) -> 0 | BZ45: =IF($CE$45=0,0,(SUM(BZ37,BZ38,BZ39)/(1-$CE$45))-SUM(BZ37,BZ38,BZ39)) -> 0 | CB45: =IF($CE$45=0,0,(SUM(CB37,CB38,CB39)/(1-$CE$45))-SUM(CB37,CB38,CB39)) -> 0 | CF45: =SUM(B45:CC45) -> 0
A47: TOTAL | B47: =SUM(B36:C45) -> 71423.185 | D47: =SUM(D36:E45) -> 71423.185 | F47: =SUM(F36:G45) -> 77735.381 | H47: =SUM(H36:I45) -> 77735.381 | J47: =SUM(J36:K45) -> 77735.381 | L47: =SUM(L36:M45) -> 77735.381 | N47: =SUM(N36:O45) -> 77735.381 | P47: =SUM(P36:Q45) -> 77735.381 | R47: =SUM(R36:S45) -> 69951.199 | T47: =SUM(T36:U45) -> 69951.199 | V47: =SUM(V36:W45) -> 69951.199 | X47: =SUM(X36:Y45) -> 69951.199 | Z47: =SUM(Z36:AA45) -> 78935.884 | AB47: =SUM(AB36:AC45) -> 78935.884 | AD47: =SUM(AD36:AE45) -> 78935.884 | AF47: =SUM(AF36:AG45) -> 78935.884 | AH47: =SUM(AH36:AI45) -> 78935.884 | AJ47: =SUM(AJ36:AK45) -> 78935.884 | AL47: =SUM(AL36:AM45) -> 78935.884 | AN47: =SUM(AN36:AO45) -> 78935.884 | AP47: =SUM(AP36:AQ45) -> 78935.884 | AR47: =SUM(AR36:AS45) -> 78935.884 | AT47: =SUM(AT36:AU45) -> 78935.884 | AV47: =SUM(AV36:AW45) -> 78935.884 | AX47: =SUM(AX36:AY45) -> 78935.884 | AZ47: =SUM(AZ36:BA45) -> 78935.884 | BB47: =SUM(BB36:BC45) -> 78935.884 | BD47: =SUM(BD36:BE45) -> 78935.884 | BF47: =SUM(BF36:BG45) -> 80726.482 | BH47: =SUM(BH36:BI45) -> 84209.807 | BJ47: =SUM(BJ36:BK45) -> 84209.807 | BL47: =SUM(BL36:BM45) -> 84209.807 | BN47: =SUM(BN36:BO45) -> 84209.807 | BP47: =SUM(BP36:BQ45) -> 84209.807 | BR47: =SUM(BR36:BS45) -> 84209.807 | BT47: =SUM(BT36:BU45) -> 84209.807 | BV47: =SUM(BV36:BW45) -> 0 | BX47: =SUM(BX36:BY45) -> 0 | BZ47: =SUM(BZ36:CA45) -> 0 | CB47: =SUM(CB36:CC45) -> 0 | CF47: =SUM(CF36:CF45) -> 2822232.7

Sheet Consideraçoes
C3: 01. | D3: SERVIÇOS TÉCNICOS E PRELIMINARES
C5: 1) incuir valor dos projetos no custo de contruçao - | H5: 168500
C6: 2) Licenças de obra e barracao
C7: 3) Consultoria de Planejamento e orçamento de obras - o que é ? Precisa ?
C9: 04. | D9: MÁQUINAS E EQUIPAMENTOS
C12: 06.4.1 | D12: Despesas de Consumo
C13: Consumo de Luz | E13: Subdimensionados
C14: Consumo de Água | E14: Subdimensionados
C17: 08.2 | D17: Fundações
C18: 1) Controle tecnologico pode estar subdimensionado
C21: Geral
C23: 2) Telhados
C24: 3) acabamentos de eletrica

Sheet 05. Histograma Equip
C2: HISTOGRAMA DE EQUIPAMENTOS | AC2: PRAZO (meses)
AC3: ='02. Orçamento'!L2 -> 36
A6: EQUIPE TÉCNICA E ADMINISTRATIVA DE OBRA
A7: DESCRIÇÃO | B7: UNIDADE | C7: MÊS 1 | D7: MÊS 2 | E7: MÊS 3 | F7: MÊS 4 | G7: MÊS 5 | H7: MÊS 6 | I7: MÊS 7 | J7: MÊS 8 | K7: MÊS 9 | L7: MÊS 10 | M7: MÊS 11 | N7: MÊS 12 | O7: MÊS 13 | P7: MÊS 14 | Q7: MÊS 15 | R7: MÊS 16 | S7: MÊS 17 | T7: MÊS 18 | U7: MÊS 19 | V7: MÊS 20 | W7: MÊS 21 | X7: MÊS 22 | Y7: MÊS 23 | Z7: MÊS 24 | AA7: TOTAL | AB7: R$
A8: ENGENHEIRO - PJ | B8: 1 | C8: 1 | D8: 1 | E8: 1 | F8: 1 | G8: 1 | H8: 1 | I8: 1 | J8: 1 | K8: 1 | L8: 1 | M8: 1 | N8: 1 | O8: 1 | P8: 1 | Q8: 1 | R8: 1 | S8: 1 | T8: 1 | U8: 1 | V8: 1 | W8: 1 | X8: 1 | Y8: 1 | Z8: 1 | AA8: =SUMIF($C$7:$Z$7,"QTD",C8:Z8) -> 0 | AB8: 14000 | AC8: =AA8*AB8 -> 0
A9: ARQUITETA - PJ | B9: 1 | C9: 1 | D9: 1 | E9: 1 | F9: 1 | G9: 1 | H9: 1 | I9: 1 | J9: 1 | K9: 1 | L9: 1 | M9: 1 | N9: 1 | O9: 1 | P9: 1 | Q9: 1 | R9: 1 | S9: 1 | T9: 1 | U9: 1 | V9: 1 | W9: 1 | X9: 1 | AA9: =SUMIF($C$7:$Z$7,"QTD",C9:Z9) -> 0 | AB9: 4000 | AC9: =AA9*AB9 -> 0
A10: ESTAGIÁRIO | B10: 1 | C10: 1 | D10: =C10 -> 1 | E10: =D10 -> 1 | F10: =E10 -> 1 | G10: =F10 -> 1 | H10: 1 | I10: 2 | J10: =I10 -> 2 | K10: =J10 -> 2 | L10: =K10 -> 2 | M10: =L10 -> 2 | N10: =M10 -> 2 | O10: =N10 -> 2 | P10: =O10 -> 2 | Q10: =P10 -> 2 | ... V10: =U10 -> 2 | W10: =T10 -> 2 | X10: =W10 -> 2 | Y10: 1 | Z10: =Y10 -> 1 | AA10: =SUMIF($C$7:$Z$7,"QTD",C10:Z10) -> 0 | AB10: 1700 | AC10: =AA10*AB10 -> 0
A11: TÉCNICO DE EDIFICAÇÕES | AA11: =SUMIF($C$7:$Z$7,"QTD",C11:Z11) -> 0 | AB11: 3650 | AC11: =AA11*AB11 -> 0
A12: MESTRE DE OBRA | B12: 1 | C12: 1 | D12: 1 | E12: 1 | F12: 1 | G12: 1 | H12: 1 | I12: 1 | J12: 1 | K12: 1 | L12: 1 | M12: 1 | N12: 1 | O12: 1 | P12: 1 | Q12: 1 | R12: 1 | S12: 1 | T12: 1 | U12: 1 | V12: 1 | W12: 1 | X12: 1 | AA12: =SUMIF($C$7:$Z$7,"QTD",C12:Z12) -> 0 | AB12: 10000 | AC12: =AA12*AB12 -> 0
A13: ADMINISTRATIVO | B13: 1 | C13: 1 | D13: =C13 -> 1 | E13: =D13 -> 1 | F13: =E13 -> 1 | G13: =F13 -> 1 | H13: =G13 -> 1 | I13: =H13 -> 1 | J13: =I13 -> 1 | K13: =J13 -> 1 | ... V13: =U13 -> 1 | W13: =T13 -> 1 | X13: =W13 -> 1 | Y13: =V13 -> 1 | Z13: =Y13 -> 1 | AA13: =SUMIF($C$7:$Z$7,"QTD",C13:Z13) -> 0 | AB13: 4428.6 | AC13: =AA13*AB13 -> 0
A14: TÉCNICO EM SEGURANÇA DO TRABALHO | B14: 0.5 | C14: 0.5 | D14: =C14 -> 0.5 | E14: =D14 -> 0.5 | F14: =E14 -> 0.5 | G14: =F14 -> 0.5 | H14: =G14 -> 0.5 | I14: =H14 -> 0.5 | J14: =I14 -> 0.5 | K14: =J14 -> 0.5 | ... V14: =U14 -> 0.5 | W14: =T14 -> 0.5 | X14: =W14 -> 0.5 | AA14: =SUMIF($C$7:$Z$7,"QTD",C14:Z14) -> 0 | AB14: 3295.6 | AC14: =AA14*AB14 -> 0
A15: ALMOXARIFE | B15: 1 | C15: 1 | D15: 1 | E15: 1 | F15: 1 | G15: 1 | H15: =G15 -> 1 | I15: =H15 -> 1 | J15: =I15 -> 1 | K15: =J15 -> 1 | L15: =K15 -> 1 | M15: =L15 -> 1 | N15: =M15 -> 1 | O15: =N15 -> 1 | ... V15: =U15 -> 1 | W15: =T15 -> 1 | X15: =W15 -> 1 | AA15: =SUMIF($C$7:$Z$7,"QTD",C15:Z15) -> 0 | AB15: 3150.4 | AC15: =AA15*AB15 -> 0
A16: AUXILIAR ALMOXARIFE | B16: 0 | C16: 0 | D16: =C16 -> 0 | E16: =D16 -> 0 | F16: =E16 -> 0 | G16: =F16 -> 0 | H16: =G16 -> 0 | I16: =H16 -> 0 | J16: =I16 -> 0 | K16: =J16 -> 0 | ... V16: =U16 -> 0 | W16: =T16 -> 0 | X16: =W16 -> 0 | Y16: =V16 -> 0 | Z16: =Y16 -> 0 | AA16: =SUMIF($C$7:$Z$7,"QTD",C16:Z16) -> 0 | AB16: 2028.4 | AC16: =AA16*AB16 -> 0
A17: ENCARREGADO DE OBRA | D17: =C17 -> 0 | E17: =D17 -> 0 | F17: =E17 -> 0 | G17: =F17 -> 0 | H17: =G17 -> 0 | I17: =H17 -> 0 | J17: =I17 -> 0 | K17: =J17 -> 0 | ... V17: =U17 -> 0 | W17: =T17 -> 0 | X17: =W17 -> 0 | Y17: =V17 -> 0 | Z17: =Y17 -> 0 | AA17: =SUMIF($C$7:$Z$7,"QTD",C17:Z17) -> 0 | AB17: 6000 | AC17: =AA17*AB17 -> 0
A18: ENCARREGADO DE TURMA | D18: =C18 -> 0 | E18: =D18 -> 0 | F18: =E18 -> 0 | G18: =F18 -> 0 | H18: =G18 -> 0 | I18: =H18 -> 0 | J18: =I18 -> 0 | K18: =J18 -> 0 | ... V18: =U18 -> 0 | W18: =T18 -> 0 | X18: =W18 -> 0 | Y18: =V18 -> 0 | Z18: =Y18 -> 0 | AA18: =SUMIF($C$7:$Z$7,"QTD",C18:Z18) -> 0 | AC18: =AA18*AB18 -> 0
A19: OPERADOR DE CREMALHEIRA | D19: =C19 -> 0 | E19: =D19 -> 0 | F19: =E19 -> 0 | G19: =F19 -> 0 | H19: =G19 -> 0 | I19: =H19 -> 0 | J19: =I19 -> 0 | K19: 1 | L19: =K19 -> 1 | M19: =L19 -> 1 | N19: =M19 -> 1 | O19: =N19 -> 1 | P19: =O19 -> 1 | Q19: =P19 -> 1 | R19: =Q19 -> 1 | S19: =R19 -> 1 | ... U19: =T19 -> 1 | V19: 0 | W19: 0 | X19: =W19 -> 0 | Y19: =V19 -> 0 | Z19: =Y19 -> 0 | AA19: =SUMIF($C$7:$Z$7,"QTD",C19:Z19) -> 0 | AB19: 2662 | AC19: =AA19*AB19 -> 0
A20: OPERADOR DE GRUA | D20: =C20 -> 0 | E20: =D20 -> 0 | F20: =E20 -> 0 | G20: =F20 -> 0 | H20: =G20 -> 0 | I20: =H20 -> 0 | J20: =I20 -> 0 | K20: =J20 -> 0 | ... V20: =U20 -> 0 | W20: =T20 -> 0 | X20: =W20 -> 0 | Y20: =V20 -> 0 | Z20: =Y20 -> 0 | AA20: =SUMIF($C$7:$Z$7,"QTD",C20:Z20) -> 0 | AC20: =AA20*AB20 -> 0
A21: PEDREIRO | B21: 0 | C21: 0 | D21: =C21 -> 0 | E21: =D21 -> 0 | F21: =E21 -> 0 | G21: 0 | H21: =G21 -> 0 | I21: =H21 -> 0 | J21: =I21 -> 0 | K21: =J21 -> 0 | L21: 1 | M21: 1 | N21: 2 | O21: =N21 -> 2 | P21: =O21 -> 2 | Q21: =P21 -> 2 | R21: =Q21 -> 2 | S21: =R21 -> 2 | T21: =S21 -> 2 | U21: =T21 -> 2 | V21: =U21 -> 2 | W21: =T21 -> 2 | X21: =W21 -> 2 | Y21: 2 | Z21: =Y21 -> 2 | AA21: =SUMIF($C$7:$Z$7,"QTD",C21:Z21) -> 0 | AB21: 2864.4 | AC21: =AA21*AB21 -> 0
A22: CARPINTEIRO | B22: 1 | C22: 1 | D22: =C22 -> 1 | E22: =D22 -> 1 | F22: 2 | G22: =F22 -> 2 | H22: =G22 -> 2 | I22: =H22 -> 2 | J22: =I22 -> 2 | K22: =J22 -> 2 | L22: 1 | M22: =L22 -> 1 | N22: 0 | O22: =N22 -> 0 | P22: =O22 -> 0 | Q22: =P22 -> 0 | R22: =Q22 -> 0 | S22: =R22 -> 0 | T22: =S22 -> 0 | U22: =T22 -> 0 | V22: =U22 -> 0 | W22: =T22 -> 0 | X22: =W22 -> 0 | Y22: =V22 -> 0 | Z22: =Y22 -> 0 | AA22: =SUMIF($C$7:$Z$7,"QTD",C22:Z22) -> 0 | AB22: 2864.4 | AC22: =AA22*AB22 -> 0
A23: ELETRICISTA | D23: =C23 -> 0 | E23: =D23 -> 0 | F23: =E23 -> 0 | G23: =F23 -> 0 | H23: =G23 -> 0 | I23: =H23 -> 0 | J23: =I23 -> 0 | K23: =J23 -> 0 | ... V23: =U23 -> 0 | W23: =T23 -> 0 | X23: =W23 -> 0 | Y23: =V23 -> 0 | Z23: =Y23 -> 0 | AA23: =SUMIF($C$7:$Z$7,"QTD",C23:Z23) -> 0 | AB23: 2662 | AC23: =AA23*AB23 -> 0
A24: BOMBEIRO | D24: =C24 -> 0 | E24: =D24 -> 0 | F24: =E24 -> 0 | G24: =F24 -> 0 | H24: =G24 -> 0 | I24: =H24 -> 0 | J24: =I24 -> 0 | K24: =J24 -> 0 | ... V24: =U24 -> 0 | W24: =T24 -> 0 | X24: =W24 -> 0 | Y24: =V24 -> 0 | Z24: =Y24 -> 0 | AA24: =SUMIF($C$7:$Z$7,"QTD",C24:Z24) -> 0 | AB24: 2662 | AC24: =AA24*AB24 -> 0
A25: 1/2 OFICIAL | D25: =C25 -> 0 | E25: =D25 -> 0 | F25: =E25 -> 0 | G25: =F25 -> 0 | H25: =G25 -> 0 | I25: =H25 -> 0 | J25: =I25 -> 0 | K25: =J25 -> 0 | ... V25: =U25 -> 0 | W25: =T25 -> 0 | X25: =W25 -> 0 | Y25: =V25 -> 0 | Z25: =Y25 -> 0 | AA25: =SUMIF($C$7:$Z$7,"QTD",C25:Z25) -> 0 | AB25: 2028.4 | AC25: =AA25*AB25 -> 0
A26: SERVENTE | B26: 2 | C26: 2 | D26: =C26 -> 2 | E26: =D26 -> 2 | F26: 3 | G26: =F26 -> 3 | H26: =G26 -> 3 | I26: =H26 -> 3 | J26: =I26 -> 3 | K26: =J26 -> 3 | L26: =K26 -> 3 | M26: =L26 -> 3 | N26: =M26 -> 3 | ... V26: =U26 -> 3 | W26: =T26 -> 3 | X26: =W26 -> 3 | Y26: 2 | Z26: =Y26 -> 2 | AA26: =SUMIF($C$7:$Z$7,"QTD",C26:Z26) -> 0 | AB26: 1925 | AC26: =AA26*AB26 -> 0
D27: =C27 -> 0 | E27: =D27 -> 0 | F27: =E27 -> 0 | G27: =F27 -> 0 | H27: =G27 -> 0 | I27: =H27 -> 0 | J27: =I27 -> 0 | K27: =J27 -> 0 | ... V27: =U27 -> 0 | W27: =T27 -> 0 | X27: =W27 -> 0 | Y27: =V27 -> 0 | Z27: =Y27 -> 0 | AA27: =SUMIF($C$7:$Z$7,"QTD",C27:Z27) -> 0 | AC27: =AA27*AB27 -> 0
AA28: =SUMIF($C$7:$Z$7,"QTD",C28:Z28) -> 0 | AC28: =AA28*AB28 -> 0
AA29: =SUMIF($C$7:$Z$7,"QTD",C29:Z29) -> 0 | AC29: =AA29*AB29 -> 0
AA30: =SUMIF($C$7:$Z$7,"QTD",C30:Z30) -> 0 | AC30: =AA30*AB30 -> 0
AA31: =SUMIF($C$7:$Z$7,"QTD",C31:Z31) -> 0 | AC31: =AA31*AB31 -> 0
A32: SUBTOTAL | C32: =SUM(#REF!) -> #REF! | D32: =SUM(#REF!) -> #REF! | E32: =SUM(#REF!) -> #REF! | F32: =SUM(#REF!) -> #REF! | G32: =SUM(#REF!) -> #REF! | H32: =SUM(#REF!) -> #REF! | I32: =SUM(#REF!) -> #REF! | J32: =SUM(#REF!) -> #REF! | ... Z32: =SUM(#REF!) -> #REF! | AC32: =SUM(#REF!) -> #REF!

Sheet 06. Controle de Premissas
C1: CONSIDERAÇÕES GERAIS
B5: PREMISSAS E EXCLUSÕES
B6: GRUPO 01 | C6: Serviços preliminares - Toda a gestão de legalizações será realizada pela construtora. Serviços Técnicos - Foram considerados todos os testes e ensaios normativos, bem como o Seguro de Responsabilidade civil / Risco Engenharia. Consultorias - Todas as consultorias estão consideradas. Projetos - Todos foram desconsiderados do custo.
B7: GRUPO 02 | C7: Implantação de Canteiro - Todos os custos com as instalações provisórias foram incluídos.
B8: GRUPO 03 | C8: Segurança do trabalho - Todos os custos com proteções e requisitos de normas de segurança foram considerados, fazendo parte do orçamento em questão.
B9: GRUPO 04 | C9: Máquinas e Equipamentos - Todos os custos com máquinas, ferramentas e equipamentos que se façam necessários fazem parte do orçamento em questão.
B10: GRUPO 05 | C10: Equipe - Toda a equipe administrativa foi considerada, incluindo seus custos diretos e indiretos.
B11: GRUPO 06 | C11: Despesas operacionais - Todos os custos operacionais que se façam necessários fazem parte do orçamento em questão.
B12: GRUPO 07 | C12: Demolições - Não foram consideradas demolições de estruturas ou rochas de qualquer natureza que possam aparecer ao longo da execução das fundações. Caso ocorra, o custo de sua retirada será a cargo do incorporador.
B13: GRUPO 08 | C13: Contenções - Considerada contenção conforme projeto da Consultrix. Fundações - Considerado fundação conforme projeto. Utilizado quantitativo fornecido pelo projetista
B14: GRUPO 09 | C14: Estrutura de Concreto Armado Forma - Quantitativo fornecido pelo projetista Armação - Quantitativo fornecido pelo projetista Concreto - Quantitativo fornecido pelo projetista
B15: GRUPO 10 | C15: Vedações - Considerados blocos cerâmicos e blocos de concreto conforme legenda em projeto de arquitetura. Considerado drywall conforme projeto de vedações
B16: GRUPO 11 | C16: Instalações prediais - Considerados acabamentos conforme memorial Considerado todas as Instalações Especiais conforme projeto. Foram considerados aquecimento central conforme memorial e projetos. Não foram consideradas de Luminárias Considerado fornecimento e instalçao de Gerador 20Kva Equipamentos de Piscina - Considerado equipamentos de piscina: filtro, tratamento de água e aquecimento
B17: GRUPO 12 | C17: Impermeabilizações - Todas as impermeabilizações foram consideradas.
... B30: GRUPO 25 | C30: Sem comentários

Sheet Planilha1
B2: 4681.6 | C2: 80 | D2: =B2/C2 -> 58.52 | G2: 0.19 | H2: =G2*G3*G4 -> 1 | I2: =0.8*G4 -> 10.796221 | K2: 10.796221
B3: 13585 | C3: 130 | D3: =B3/C3 -> 104.5 | G3: 0.39 | I3: =0.2*G4*2 -> 5.3981107 | K3: 5.3981107
B4: 8208 | C4: 120 | D4: =B4/C4 -> 68.4 | G4: 13.495277
B5: 10450 | C5: 125 | D5: =B5/C5 -> 83.6
B6: 10450 | C6: 125 | D6: =B6/C6 -> 83.6
B7: 12787.5 | C7: 125 | D7: =B7/C7 -> 102.3 | G7: 11.88 | H7: =0.19*0.39 -> 0.0741 | I7: =G7*H7 -> 0.880308 | J7: =I7/I9 -> 0.80016579
B8: 10107.5 | C8: 130 | D8: =B8/C8 -> 77.75 | G8: 6.09 | H8: =0.19*0.19 -> 0.0361 | I8: =G8*H8 -> 0.219849 | J8: =I8/I9 -> 0.19983421
B9: 8299.2 | C9: 120 | D9: =B9/C9 -> 69.16 | I9: =SUM(I7:I8) -> 1.100157
B10: 43068 | C10: 120 | D10: =B10/C10 -> 358.9 | Q10: =8500/15 -> 566.66667
B11: 9097.2 | C11: 120 | D11: =B11/C11 -> 75.81 | Q11: =35560/111 -> 320.36036
B12: 3312 | C12: 115 | D12: =B12/C12 -> 28.8
B13: 1242 | C13: 115 | D13: =B13/C13 -> 10.8 | Q13: 3750
B14: =SUM(B2:B13) -> 135288 | C14: =B14/D14 -> 120.5625 | D14: =SUM(D2:D13) -> 1122.14 | Q14: =Q13/25 -> 150
F15: 11.55
F16: 6.796 | J16: =100/4.5 -> 22.222222 | K16: =(100*8)/20 -> 40
F17: 2.056
F18: =4.65*2.2 -> 10.23
F19: 1.647 | I19: = 11,55+ 6,796+2,056+( 4,65*2,2 )+1,647+ 4,07+3,372 )*13,31
F20: 4.07 | I20: =(11.55+6.796+2.056+(4.65*2.2)+1.647+4.07+3.372)*13.31 -> 528.68651 | P20: 418 | Q20: 206.29 | R20: =SUM(P20:Q20) -> 624.29
F21: 3.372 | P21: 0.14 | Q21: 0.14
F22: =SUM(F15:F21) -> 39.721 | G22: =F22*13.31 -> 528.68651 | P22: =P20*P21 -> 58.52 | Q22: =Q20*Q21 -> 28.8806 | R22: =SUM(P22:Q22) -> 87.4006
O23: =P23/P20 -> 0.28 | P23: 117.04 | Q23: =Q20*O23 -> 57.7612 | R23: =SUM(P23:Q23) -> 174.8012
P24: 80 | Q24: 80
G25: ='02. Orçamento'!L335 -> 0 | H25: =G25*0.1 -> 0 | I25: =H27-H25 -> 0 | J25: =G25+H25+I25 -> 0 | P25: =P22*P24 -> 4681.6 | Q25: =Q22*Q24 -> 2310.448 | R25: =SUM(P25:Q25) -> 6992.048
H26: =(1-0.1959) -> 0.8041
H27: =H25/H26 -> 0
G29: ='02. Orçamento'!H709-'02. Orçamento'!H703 -> -3884 | H29: =G29*0.1 -> -388.4 | I29: =H31-H29 -> -94.624499 | J29: =G29+H29+I29 -> -4367.0245
H30: =(1-0.1959) -> 0.8041
H31: =H29/H30 -> -483.0245
G33: =(('02. Orçamento'!#REF!)) -> #REF! | H33: =G33*0.1 -> #REF! | I33: =H35-H33 -> #REF! | J33: =G33+H33+I33 -> #REF!
H34: =(1-0.1959) -> 0.8041
H35: =H33/H34 -> #REF!

Sheet Comparativo
B2: Custo Total 15/01/2021 | C2: 5189933.1
B3: Reduções | C3: =SUM(C4:C9) -> #REF!
B4: Esquadrias de Alumínio | C4: -1116538.1
B5: Mármores e Granitos | C5: -250718.61
B6: Piso Vinílico | C6: -107200.76
B7: Porcelanato Munari | C7: -114978.28
B8: Forro em Lambri 10 cm | C8: #REF!
B9: Diversos | C9: =-8433.12114155519*1.12 -> -9445.0957
B10: Custo Total Reduzido | C10: =C2+C3 -> #REF!
B12: Adições | C12: =SUM(C13:C17) -> #REF!
B13: Luminárias | C13: =#REF!*1.12 -> #REF!
B14: Gerador | C14: =#REF!*1.12 -> #REF!
B15: Boiler | C15: =#REF!*1.12 -> #REF!
B16: Piscina, Sauna e Espelho d'água | C16: =#REF!*1.12 -> #REF!
B17: Muros Laterais e Fundos | C17: -204637.19
B18: Custo Total 04/02/2021 | C18: =#REF! -> #REF!

Sheet 07. Lista de Projetos
C1: LISTA DE PROJETOS
C5: NOME | D5: REVISÃO | E5: DATA REV
B7: 01. | C7: ARQUITETURA
B8: 01.1 | C8: Arquitetura Executiva
C9: SC-127-AEX-PEX-100-PB-SUBS_R01.pdf | D9: 1 | E9: 44729
C10: SC-127-AEX-PEX-101-PB-TERR_R01.pdf | D10: 1 | E10: 44729
C11: SC-127-AEX-PEX-102-PB-1PAV_R01.pdf | D11: 1 | E11: 44729
C12: SC-127-AEX-PEX-103-PB-TIPO_R01.pdf | D12: 1 | E12: 44729
C13: SC-127-AEX-PEX-104-PB-11PV_R01.pdf | D13: 1 | E13: 44729
C14: SC-127-AEX-PEX-105-PB-COBE_R01.pdf | D14: 1 | E14: 44729
C15: SC-127-AEX-PEX-106-PB-PTEC_R02.pdf | D15: 2 | E15: 44729
C16: SC-127-AEX-PEX-200-PB-TELH_R01.pdf | D16: 1 | E16: 44729
C17: SC-127-AEX-PEX-300-CT-CORT_R01.pdf | D17: 1
C18: SC-127-AEX-PEX-301-CT-CORT_R00.pdf | D18: 0
C19: SC-127-AEX-PEX-400-FC-FACH_R01.pdf | D19: 1
C20: SC-127-AEX-MEM-001-ACABAMENTOS_R14.xlsx | D20: 14
B21: 01.2 | C21: Detalhes
C22: SC-127-AEX-PE-500-ES-ESC_R00.pdf | D22: 0 | E22: 44729
C23: SC-127-AEX-PE-501-ES-ESC_R00.pdf | D23: 0 | E23: 44729
C24: SC-127-AEX-PE-600-ES-ESQ_R01.pdf | D24: 1
C25: SC-127-AEX-PE-601-ES-ESQ_R02.pdf | D25: 2
C26: SC-127-AEX-PE-602-ES-ESQ_R02.pdf | D26: 2
C27: SC-127-AEX-PE-603-ES-ESQ_R02.pdf | D27: 2
C28: SC-127-AEX-PE-604-ES-ESQ_R01.pdf | D28: 1 | E28: 44729
C29: SC-127-AEX-PE-605-ES-ESQ_R00.pdf | D29: 0 | E29: 44729
C30: SC-127-AEX-PE-606-ES-ESQ_R00.pdf | D30: 0
C31: SC-127-AEX-PE-700-AM-COL01_R00.pdf | D31: 0
C32: SC-127-AEX-PE-701-AM-COL02_R00.pdf | D32: 0
C33: SC-127-AEX-PE-702-AM-COL03_R00.pdf | D33: 0
C34: SC-127-AEX-PE-703-AM-COL04_R00.pdf | D34: 0 | E34: 44729
C35: SC-127-AEX-PE-704-AM-COL05_R00.pdf | D35: 0 | E35: 44729
C36: SC-127-AEX-PE-705-AM-1103_R00.pdf | D36: 0
C37: SC-127-AEX-PE-706-AM-COB01_R00.pdf | D37: 0
C38: SC-127-AEX-PE-707-AM-COB02_R00.pdf | D38: 0
C39: SC-127-AEX-PE-708-AM-COB03_R00.pdf | D39: 0
C40: SC-127-AEX-PE-709-AM-REF_R00.pdf | D40: 0 | E40: 44729
C41: SC-127-AEX-PE-710-AM-PED_R00.pdf | D41: 0 | E41: 44729
C42: SC-127-AEX-PE-711-AM-PED_R00.pdf | D42: 0
B43: 01.3 | C43: Mini Executivo
C44: SC-127-ESP-ME-001-AP-TIPO-R01.pdf | D44: 1 | E44: 44729
C45: SC-ME-IE-001-TIPO-COL02-R03.pdf | D45: 3 | E45: 44729
C46: SC-ME-IG-002-TIPO-COL02-R03.pdf | D46: 3
C47: SC-ME-IH-003-TIPO-COL02-R03.pdf | D47: 3
C48: SC-ME-IS-004-TIPO-COL02-R04.pdf | D48: 4
C49: SC-127-ESQ-ME-010-GE-DETALU-R02.pdf | D49: 2
C50: SC-127-ESQ-ME-011-ES-DETALU-R02.pdf | D50: 2 | E50: 44729
C51: SC-127-ESQ-ME-012-ES-DETALU-R02.pdf | D51: 2 | E51: 44729
C52: SC-127-ESQ-ME-013-ES-DETALU-R02.pdf | D52: 2 | E52: 44729
C53: SC-127-AEX-IM-ME-100-PB-TIPO_R02.pdf | D53: 2 | E53: 44729
C54: SC-127-AEX-ME-100-PB-TIPO_R03.pdf | D54: 3
C55: SC-127-AEX-ME-700-AM_R02.pdf | D55: 2
C56: SC-127-AEX-ME-900-ES-ALU_R02 CADERNO.pdf | D56: 2
C57: SC-127-AEX-ME-950-ES-MAD_R02 CADERNO.pdf | D57: 2
B58: 02. | C58: ESTRUTURA
C59: SC-127-EST-EX-000-PB-PROC_R01.pdf | D59: 1 | E59: 44729
C60: SC-127-EST-EX-001-PB-LOCA_R04.pdf | D60: 4 | E60: 44729
C61: SC-127-EST-FOR-PEX-002-Forma_dos_blocos_de_fundaþÒo_R00.pdf | D61: 0 | E61: 44729
C62: SC-127-EST-EX-003-PB-SUBS_R05.pdf | D62: 5 | E62: 44729
C63: SC-127-EST-EX-004-PB-TERR_R03.pdf | D63: 3 | E63: 44729
C64: SC-127-EST-EX-005-PB-1PAV_R03.pdf | D64: 3 | E64: 44729
C65: SC-127-EST-EX-006-PB-2PAV_R03.pdf | D65: 3 | E65: 44729
C66: SC-127-EST-EX-007-PB-TIP1_R03.pdf | D66: 3 | E66: 44729
C67: SC-127-EST-EX-008-PB-TIP2_R03.pdf | D67: 3 | E67: 44729
C68: SC-127-EST-EX-009-PB-11PV_R03.pdf | D68: 3 | E68: 44729
C69: SC-127-EST-EX-010-PB-COBE_R03.pdf | D69: 3 | E69: 44729
C70: SC-127-EST-EX-011-PB-PTEC_R03.pdf | D70: 3 | E70: 44729
... C85: SC-127-CON-EST-2__RELATORIO_DE_ANALISE_ESTRUTURAL_R00.pdf | D85: 0 | E85: 44729
B86: 03. | C86: FUNDAÇÃO
C87: SC-127-FUN-PEX-001-Relat¾rio_de_FundaþÒo_R01.pdf | D87: 1 | E87: 44729
C88: SC-127-FUN-EX-001-PB-ESTQ_R03.pdf | D88: 3 | E88: 44729
C89: SC-127-FUN-EX-002-PB-ESTQ_R02.pdf | D89: 2 | E89: 44729
C90: SC-127-FUN-PEX-003-Relat¾rio_de_contenþÒo_R01.pdf | D90: 1 | E90: 44729
C91: SC-127-CON-FUN-EXEC-VerificaþÒo_das_Fundaþ§es_-_Projeto_Executivo_R01.pdf | D91: 1 | E91: 44729
B92: 04. | C92: IMPERMEABILIZAÇÃO
C93: SC-127-IMP-EX-002-PB-TERR_R00.pdf | D93: 0 | E93: 44729
C94: SC-127-IMP-EX-003-PB-1PAV_R00.pdf | D94: 0 | E94: 44729
C95: SC-127-IMP-EX-004-PB-TIPO_R00.pdf | D95: 0 | E95: 44729
C96: SC-127-IMP-EX-005-PB-11PAV_R00.pdf | D96: 0 | E96: 44729
C97: SC-127-IMP-EX-006-PB-COBE_R00.pdf | D97: 0 | E97: 44729
C98: SC-127-IMP-EX-007-PB-PAVTEC_R00.pdf | D98: 0 | E98: 44729
C99: SC-127-IMP-EX-008-PB-TELH_R00.pdf | D99: 0 | E99: 44729
B100: 05. | C100: INSTALAÇÕES
B101: 05.1 | C101: Instalação de esgoto e pluviais
C102: SC-EX-IS-001-SUBSOLO-R02.pdf | D102: 2
C103: SC-EX-IS-002-TERREO-R01.pdf | D103: 1
C104: SC-EX-IS-003-1PAV-R02.pdf | D104: 2
C105: SC-EX-IS-004-TIPO-R02.pdf | D105: 2
C106: SC-EX-IS-005-11PAV-R02.pdf | D106: 2
C107: SC-EX-IS-006-COB-R02.pdf | D107: 2
C108: SC-EX-IS-007-TELH-R02.pdf | D108: 2
C109: SC-EX-IS-008-EQV-ES-R01.pdf | D109: 1
C110: SC-EX-IS-009-EQV-EP-R01.pdf | D110: 1
C111: SC-EX-IS-010-EQV-AP-R01.pdf | D111: 1
B112: 5.2. | C112: Instalação de gás
C113: SC-EX-IG-001-SUBSOLO-R03.pdf | D113: 3 | E113: 44750
C114: SC-EX-IG-002-TERREO-R03.pdf | D114: 3 | E114: 44750
C115: SC-EX-IG-003-1PAV-R03.pdf | D115: 3 | E115: 44750
C116: SC-EX-IG-004-TIPO-R03.pdf | D116: 3 | E116: 44750
C117: SC-EX-IG-005-11PAV-R03.pdf | D117: 3 | E117: 44750
C118: SC-EX-IG-006-COB-R03.pdf | D118: 3 | E118: 44750
...

Sheet Quadro de áreas
C3: LEOPOLDO MIGUEL 10
C5: Área do terreno | D5: 149 | E5: m²
D7: ATC | I7: AEQ | N7: AEQ (m²) | P7: R$/m² | R7: R$
D8: =SUM(D10,D15,D19,D23,D26,D29,D32) -> 1349.33 | E8: m² | I8: =SUM(I10,I15,I19,I23,I26,I29,I32) -> 1412.0575 | J8: m²
N9: =I8 -> 1412.0575 | P9: 6500 | R9: =N9*P9 -> 9178373.8
C10: Térreo | D10: =SUM(D11:D13) -> 149 | E10: m² | I10: =SUM(I11:I13) -> 327.945 | J10: m²
